Workbook

Sheet 更新履歴
A1: 更新履歴
A4: № | C4: 更新日付 | G4: 更新資料（シート名） | M4: 更新内容 | AB4: 更新者名 | AF4: 備考
A5: =IF(M5="","",ROW()-4) -> 1 | C5: 42917 | G5: 全シート | M5: 初版 | AB5: 富士通）西浦
A6: =IF(M6="","",ROW()-4)
A7: =IF(M7="","",ROW()-4)
A8: =IF(M8="","",ROW()-4)
A9: =IF(M9="","",ROW()-4)
A10: =IF(M10="","",ROW()-4)
A11: =IF(M11="","",ROW()-4)
A12: =IF(M12="","",ROW()-4)
A13: =IF(M13="","",ROW()-4)
A14: =IF(M14="","",ROW()-4)
A15: =IF(M15="","",ROW()-4)
A16: =IF(M16="","",ROW()-4)
A17: =IF(M17="","",ROW()-4)
... A33: =IF(M33="","",ROW()-4)

Sheet カラムID辞書
A1: カラムID辞書 | I1: 文字コード(UTF-8)
A2: 重複チェック | I2: 日本語平均使用率
A3: 論理名 | B3: 物理名 | C3: 項目論理名称 | D3: 項目物理名称 | E3: TYPE | F3: 桁数 | G3: ASCII以外 有無 | H3: BYTE | L3: RD工程 Type
A4: =COUNTIF($C$4:$C$1266,C4) -> 1 | B4: =COUNTIF($D$4:$D$1266,D4) -> 1 | C4: 年月日 | D4: YMD | E4: numeric | F4: 8 | H4: 8 | L4: NUMBER
A5: =COUNTIF($C$4:$C$1266,C5) -> 1 | B5: =COUNTIF($D$4:$D$1266,D5) -> 1 | C5: SEQ№ | D5: SEQNO | E5: numeric | F5: 2 | H5: 2 | I5: 合わない：商品明細ワークは8ケタ、５Byte | L5: NUMBER
A6: =COUNTIF($C$4:$C$1266,C6) -> 1 | B6: =COUNTIF($D$4:$D$1266,D6) -> 1 | C6: システムグループコード | D6: SYSGRPCD | E6: character varying | F6: 4 | H6: 4 | L6: VARCHAR2
A7: =COUNTIF($C$4:$C$1266,C7) -> 1 | B7: =COUNTIF($D$4:$D$1266,D7) -> 1 | C7: 企業グループコード | D7: KGYGRPCD | E7: character varying | F7: 3 | H7: 3 | L7: VARCHAR2
A8: =COUNTIF($C$4:$C$1266,C8) -> 1 | B8: =COUNTIF($D$4:$D$1266,D8) -> 1 | C8: 店コード | D8: TENCD | E8: character varying | F8: 4 | H8: 4 | L8: VARCHAR2
A9: =COUNTIF($C$4:$C$1266,C9) -> 1 | B9: =COUNTIF($D$4:$D$1266,D9) -> 1 | C9: 商品コード１ | D9: SHOHINCD1 | E9: character varying | F9: 6 | H9: 6 | L9: VARCHAR2
A10: =COUNTIF($C$4:$C$1266,C10) -> 1 | B10: =COUNTIF($D$4:$D$1266,D10) -> 1 | C10: 商品コード２ | D10: SHOHINCD2 | E10: character varying | F10: 6 | H10: 6 | L10: VARCHAR2
A11: =COUNTIF($C$4:$C$1266,C11) -> 1 | B11: =COUNTIF($D$4:$D$1266,D11) -> 1 | C11: 商品コード３ | D11: SHOHINCD3 | E11: character varying | F11: 6 | H11: 6 | L11: VARCHAR2
A12: =COUNTIF($C$4:$C$1266,C12) -> 1 | B12: =COUNTIF($D$4:$D$1266,D12) -> 1 | C12: 商品コード４ | D12: SHOHINCD4 | E12: character varying | F12: 6 | H12: 6 | L12: VARCHAR2
A13: =COUNTIF($C$4:$C$1266,C13) -> 1 | B13: =COUNTIF($D$4:$D$1266,D13) -> 1 | C13: 商品コード５ | D13: SHOHINCD5 | E13: character varying | F13: 6 | H13: 6 | L13: VARCHAR2
A14: =COUNTIF($C$4:$C$1266,C14) -> 1 | B14: =COUNTIF($D$4:$D$1266,D14) -> 1 | C14: 細別コード１ | D14: SIBTCD1 | E14: character varying | F14: 10 | H14: 10 | L14: VARCHAR2
A15: =COUNTIF($C$4:$C$1266,C15) -> 1 | B15: =COUNTIF($D$4:$D$1266,D15) -> 1 | C15: 細別コード２ | D15: SIBTCD2 | E15: character varying | F15: 10 | H15: 10 | L15: VARCHAR2
A16: =COUNTIF($C$4:$C$1266,C16) -> 1 | B16: =COUNTIF($D$4:$D$1266,D16) -> 1 | C16: 単品コード１ | D16: TNPNCD1 | E16: character varying | F16: 13 | H16: 13 | L16: VARCHAR2
A17: =COUNTIF($C$4:$C$1266,C17) -> 1 | B17: =COUNTIF($D$4:$D$1266,D17) -> 1 | C17: 単品コード２ | D17: TNPNCD2 | E17: character varying | F17: 13 | H17: 13 | L17: VARCHAR2
... A40: =COUNTIF($C$4:$C$1266,C40) -> 1 | B40: =COUNTIF($D$4:$D$1266,D40) -> 1 | C40: 値引額 | D40: NEBIKI_GAK | E40: numeric | F40: 13 | H40: 13 | L40: NUMBER
A41: =COUNTIF($C$4:$C$1266,C41) -> 1 | B41: =COUNTIF($D$4:$D$1266,D41) -> 1 | C41: 客数１ | D41: KYAKU1_SU | E41: numeric | F41: 10,2 | H41: 10 | L41: NUMBER
A42: =COUNTIF($C$4:$C$1266,C42) -> 1 | B42: =COUNTIF($D$4:$D$1266,D42) -> 1 | C42: 客数２ | D42: KYAKU2_SU | E42: numeric | F42: 10,2 | H42: 10 | L42: NUMBER
A43: =COUNTIF($C$4:$C$1266,C43) -> 1 | B43: =COUNTIF($D$4:$D$1266,D43) -> 1 | C43: 客数３ | D43: KYAKU3_SU | E43: numeric | F43: 10,2 | H43: 10 | L43: NUMBER
A44: =COUNTIF($C$4:$C$1266,C44) -> 1 | B44: =COUNTIF($D$4:$D$1266,D44) -> 1 | C44: 純仕入高原価 | D44: JNSHIIRED_GNK | E44: numeric | F44: 13 | H44: 13 | L44: NUMBER
A45: =COUNTIF($C$4:$C$1266,C45) -> 1 | B45: =COUNTIF($D$4:$D$1266,D45) -> 1 | C45: 純仕入高売価 | D45: JNSHIIRED_BIK | E45: numeric | F45: 13 | H45: 13 | L45: NUMBER
A46: =COUNTIF($C$4:$C$1266,C46) -> 1 | B46: =COUNTIF($D$4:$D$1266,D46) -> 1 | C46: 純仕入高数量 | D46: JNSHIIRED_SU | E46: numeric | F46: 10 | H46: 10 | L46: NUMBER
A47: =COUNTIF($C$4:$C$1266,C47) -> 1 | B47: =COUNTIF($D$4:$D$1266,D47) -> 1 | C47: 仕入高原価 | D47: SHIIRED_GNK | E47: numeric | F47: 13 | H47: 13 | L47: NUMBER
A48: =COUNTIF($C$4:$C$1266,C48) -> 1 | B48: =COUNTIF($D$4:$D$1266,D48) -> 1 | C48: 仕入高売価 | D48: SHIIRED_BIK | E48: numeric | F48: 13 | H48: 13 | L48: NUMBER
A49: =COUNTIF($C$4:$C$1266,C49) -> 1 | B49: =COUNTIF($D$4:$D$1266,D49) -> 1 | C49: 仕入高数量 | D49: SHIIRED_SU | E49: numeric | F49: 10 | H49: 10 | L49: NUMBER
A50: =COUNTIF($C$4:$C$1266,C50) -> 1 | B50: =COUNTIF($D$4:$D$1266,D50) -> 1 | C50: 付帯仕入高原価 | D50: FUTAISHIIRED_GNK | E50: numeric | F50: 13 | H50: 13 | L50: NUMBER
A51: =COUNTIF($C$4:$C$1266,C51) -> 1 | B51: =COUNTIF($D$4:$D$1266,D51) -> 1 | C51: 返品高原価 | D51: HENPND_GNK | E51: numeric | F51: 13 | H51: 13 | L51: NUMBER
A52: =COUNTIF($C$4:$C$1266,C52) -> 1 | B52: =COUNTIF($D$4:$D$1266,D52) -> 1 | C52: 返品高売価 | D52: HENPND_BIK | E52: numeric | F52: 13 | H52: 13 | L52: NUMBER
A53: =COUNTIF($C$4:$C$1266,C53) -> 1 | B53: =COUNTIF($D$4:$D$1266,D53) -> 1 | C53: 返品高数量 | D53: HENPND_SU | E53: numeric | F53: 10 | H53: 10 | L53: NUMBER
A54: =COUNTIF($C$4:$C$1266,C54) -> 1 | B54: =COUNTIF($D$4:$D$1266,D54) -> 1 | C54: 付帯返品高原価 | D54: FUTAIHENPND_GNK | E54: numeric | F54: 13 | H54: 13 | L54: NUMBER
A55: =COUNTIF($C$4:$C$1266,C55) -> 1 | B55: =COUNTIF($D$4:$D$1266,D55) -> 1 | C55: 価格訂正仕入高原価 | D55: TEISEISHIIRED_GNK | E55: numeric | F55: 13 | H55: 13 | L55: NUMBER
... A63: =COUNTIF($C$4:$C$1266,C63) -> 1 | B63: =COUNTIF($D$4:$D$1266,D63) -> 1 | C63: 値上高原価１ | D63: NEAGED1_GNK | E63: numeric | F63: 13 | H63: 13 | L63: NUMBER
A64: =COUNTIF($C$4:$C$1266,C64) -> 1 | B64: =COUNTIF($D$4:$D$1266,D64) -> 1 | C64: 値上高売価１ | D64: NEAGED1_BIK | E64: numeric | F64: 13 | H64: 13 | I64: 合わない：商品明細ワークは10ケタ、6Byte | L64: NUMBER
A65: =COUNTIF($C$4:$C$1266,C65) -> 1 | B65: =COUNTIF($D$4:$D$1266,D65) -> 1 | C65: 値下高原価１ | D65: NESAGED1_GNK | E65: numeric | F65: 13 | H65: 13 | L65: NUMBER
A66: =COUNTIF($C$4:$C$1266,C66) -> 1 | B66: =COUNTIF($D$4:$D$1266,D66) -> 1 | C66: 値下高売価１ | D66: NESAGED1_BIK | E66: numeric | F66: 13 | H66: 13 | I66: 合わない：商品明細ワークは10ケタ、6Byte | L66: NUMBER
A67: =COUNTIF($C$4:$C$1266,C67) -> 1 | B67: =COUNTIF($D$4:$D$1266,D67) -> 1 | C67: 値上高原価２ | D67: NEAGED2_GNK | E67: numeric | F67: 13 | H67: 13 | L67: NUMBER
A68: =COUNTIF($C$4:$C$1266,C68) -> 1 | B68: =COUNTIF($D$4:$D$1266,D68) -> 1 | C68: 値上高売価２ | D68: NEAGED2_BIK | E68: numeric | F68: 13 | H68: 13 | I68: 合わない：商品明細ワークは10ケタ、6Byte | L68: NUMBER
A69: =COUNTIF($C$4:$C$1266,C69) -> 1 | B69: =COUNTIF($D$4:$D$1266,D69) -> 1 | C69: 値下高原価２ | D69: NESAGED2_GNK | E69: numeric | F69: 13 | H69: 13 | L69: NUMBER
A70: =COUNTIF($C$4:$C$1266,C70) -> 1 | B70: =COUNTIF($D$4:$D$1266,D70) -> 1 | C70: 値下高売価２ | D70: NESAGED2_BIK | E70: numeric | F70: 13 | H70: 13 | I70: 合わない：商品明細ワークは10ケタ、6Byte | L70: NUMBER
A71: =COUNTIF($C$4:$C$1266,C71) -> 1 | B71: =COUNTIF($D$4:$D$1266,D71) -> 1 | C71: 店間振替高原価（払出） | D71: TNKANFURI_O_GNK | E71: numeric | F71: 13 | H71: 13 | L71: NUMBER
A72: =COUNTIF($C$4:$C$1266,C72) -> 1 | B72: =COUNTIF($D$4:$D$1266,D72) -> 1 | C72: 店間振替高売価（払出） | D72: TNKANFURI_O_BIK | E72: numeric | F72: 13 | H72: 13 | L72: NUMBER
A73: =COUNTIF($C$4:$C$1266,C73) -> 1 | B73: =COUNTIF($D$4:$D$1266,D73) -> 1 | C73: 店間振替高数量（払出） | D73: TNKANFURI_O_SU | E73: numeric | F73: 10 | H73: 10 | L73: NUMBER
A74: =COUNTIF($C$4:$C$1266,C74) -> 1 | B74: =COUNTIF($D$4:$D$1266,D74) -> 1 | C74: 店間振替高原価（受入） | D74: TNKANFURI_I_GNK | E74: numeric | F74: 13 | H74: 13 | L74: NUMBER
A75: =COUNTIF($C$4:$C$1266,C75) -> 1 | B75: =COUNTIF($D$4:$D$1266,D75) -> 1 | C75: 店間振替高売価（受入） | D75: TNKANFURI_I_BIK | E75: numeric | F75: 13 | H75: 13 | L75: NUMBER
A76: =COUNTIF($C$4:$C$1266,C76) -> 1 | B76: =COUNTIF($D$4:$D$1266,D76) -> 1 | C76: 店間振替高数量（受入） | D76: TNKANFURI_I_SU | E76: numeric | F76: 10 | H76: 10 | L76: NUMBER
A77: =COUNTIF($C$4:$C$1266,C77) -> 1 | B77: =COUNTIF($D$4:$D$1266,D77) -> 1 | C77: 店内振替高原価（払出） | D77: TNNAIFURI_O_GNK | E77: numeric | F77: 13 | H77: 13 | L77: NUMBER
A78: =COUNTIF($C$4:$C$1266,C78) -> 1 | B78: =COUNTIF($D$4:$D$1266,D78) -> 1 | C78: 店内振替高売価（払出） | D78: TNNAIFURI_O_BIK | E78: numeric | F78: 13 | H78: 13 | L78: NUMBER
A79: =COUNTIF($C$4:$C$1266,C79) -> 1 | B79: =COUNTIF($D$4:$D$1266,D79) -> 1 | C79: 店内振替高数量（払出） | D79: TNNAIFURI_O_SU | E79: numeric | F79: 10 | H79: 10 | L79: NUMBER
A80: =COUNTIF($C$4:$C$1266,C80) -> 1 | B80: =COUNTIF($D$4:$D$1266,D80) -> 1 | C80: 店内振替高原価（受入） | D80: TNNAIFURI_I_GNK | E80: numeric | F80: 13 | H80: 13 | L80: NUMBER
A81: =COUNTIF($C$4:$C$1266,C81) -> 1 | B81: =COUNTIF($D$4:$D$1266,D81) -> 1 | C81: 店内振替高売価（受入） | D81: TNNAIFURI_I_BIK | E81: numeric | F81: 13 | H81: 13 | L81: NUMBER
A82: =COUNTIF($C$4:$C$1266,C82) -> 1 | B82: =COUNTIF($D$4:$D$1266,D82) -> 1 | C82: 店内振替高数量（受入） | D82: TNNAIFURI_I_SU | E82: numeric | F82: 10 | H82: 10 | L82: NUMBER
... A136: =COUNTIF($C$4:$C$1266,C136) -> 1 | B136: =COUNTIF($D$4:$D$1266,D136) -> 1 | C136: 低価法原価率分母加算額 | D136: TEIKHOU_GNKRTBNB | E136: numeric | F136: 13 | H136: 13 | L136: NUMBER
A137: =COUNTIF($C$4:$C$1266,C137) -> 1 | B137: =COUNTIF($D$4:$D$1266,D137) -> 1 | C137: 原価法原価率 | D137: GNK_GNKRT | E137: numeric | F137: 18,11 | H137: 18 | L137: NUMBER
A138: =COUNTIF($C$4:$C$1266,C138) -> 1 | B138: =COUNTIF($D$4:$D$1266,D138) -> 1 | C138: 低価法原価率 | D138: TIK_GNKRT | E138: numeric | F138: 18,11 | H138: 18 | L138: NUMBER
A139: =COUNTIF($C$4:$C$1266,C139) -> 1 | B139: =COUNTIF($D$4:$D$1266,D139) -> 1 | C139: 利益率 | D139: RIEKIRT | E139: numeric | F139: 18,5 | H139: 18 | L139: NUMBER
A140: =COUNTIF($C$4:$C$1266,C140) -> 1 | B140: =COUNTIF($D$4:$D$1266,D140) -> 1 | C140: 削除日時 | D140: DELDTE | E140: timestamp | F140: 0 | H140: 7 | L140: DATE
A141: =COUNTIF($C$4:$C$1266,C141) -> 1 | B141: =COUNTIF($D$4:$D$1266,D141) -> 1 | C141: 登録日時 | D141: INSTDTE | E141: timestamp | F141: 0 | H141: 7 | L141: DATE
A142: =COUNTIF($C$4:$C$1266,C142) -> 1 | B142: =COUNTIF($D$4:$D$1266,D142) -> 1 | C142: 登録ユーザID | D142: INSTUSRID | E142: character varying | F142: 20 | H142: 20 | L142: VARCHAR2
A143: =COUNTIF($C$4:$C$1266,C143) -> 1 | B143: =COUNTIF($D$4:$D$1266,D143) -> 1 | C143: 登録プログラムID | D143: INSTPRGID | E143: character varying | F143: 8 | H143: 8 | L143: VARCHAR2
A144: =COUNTIF($C$4:$C$1266,C144) -> 1 | B144: =COUNTIF($D$4:$D$1266,D144) -> 1 | C144: 登録IPアドレス | D144: INSIPADDR | E144: character varying | F144: 15 | H144: 15 | L144: VARCHAR2
A145: =COUNTIF($C$4:$C$1266,C145) -> 1 | B145: =COUNTIF($D$4:$D$1266,D145) -> 1 | C145: 更新日時 | D145: UPDDTE | E145: timestamp | F145: 0 | H145: 7 | L145: DATE
A146: =COUNTIF($C$4:$C$1266,C146) -> 1 | B146: =COUNTIF($D$4:$D$1266,D146) -> 1 | C146: 更新ユーザID | D146: UPDUSRID | E146: character varying | F146: 20 | H146: 20 | L146: VARCHAR2
A147: =COUNTIF($C$4:$C$1266,C147) -> 1 | B147: =COUNTIF($D$4:$D$1266,D147) -> 1 | C147: 更新プログラムID | D147: UPDPRGID | E147: character varying | F147: 8 | H147: 8 | L147: VARCHAR2
A148: =COUNTIF($C$4:$C$1266,C148) -> 1 | B148: =COUNTIF($D$4:$D$1266,D148) -> 1 | C148: 更新IPアドレス | D148: UPDIPADDR | E148: character varying | F148: 15 | H148: 15 | L148: VARCHAR2
A149: =COUNTIF($C$4:$C$1266,C149) -> 1 | B149: =COUNTIF($D$4:$D$1266,D149) -> 1 | C149: 月初在高原価 | D149: GESSHOZAID_GNK | E149: numeric | F149: 13 | H149: 13 | L149: NUMBER
A150: =COUNTIF($C$4:$C$1266,C150) -> 1 | B150: =COUNTIF($D$4:$D$1266,D150) -> 1 | C150: 月初在高売価 | D150: GESSHOZAID_BIK | E150: numeric | F150: 13 | H150: 13 | L150: NUMBER
A151: =COUNTIF($C$4:$C$1266,C151) -> 1 | B151: =COUNTIF($D$4:$D$1266,D151) -> 1 | C151: 月初在高数量 | D151: GESSHOZAID_SU | E151: numeric | F151: 10 | H151: 10 | L151: NUMBER
... A183: =COUNTIF($C$4:$C$1266,C183) -> 1 | B183: =COUNTIF($D$4:$D$1266,D183) -> 1 | C183: 前期迄累計益高 | D183: ZENKIRUIEKID | E183: numeric | F183: 13 | H183: 13 | L183: NUMBER
A184: =COUNTIF($C$4:$C$1266,C184) -> 1 | B184: =COUNTIF($D$4:$D$1266,D184) -> 1 | C184: 原価法帳簿原価率 | D184: GNK_CHOBGNKRT | E184: numeric | F184: 18,11 | H184: 18 | L184: NUMBER
A185: =COUNTIF($C$4:$C$1266,C185) -> 1 | B185: =COUNTIF($D$4:$D$1266,D185) -> 1 | C185: 原価法棚卸原価率 | D185: GNK_TANAGNKRT | E185: numeric | F185: 18,11 | H185: 18 | L185: NUMBER
A186: =COUNTIF($C$4:$C$1266,C186) -> 1 | B186: =COUNTIF($D$4:$D$1266,D186) -> 1 | C186: 利益計算対象フラグ | D186: KEISAN_FLG | E186: character varying | F186: 1 | H186: 1 | L186: VARCHAR2
A187: =COUNTIF($C$4:$C$1266,C187) -> 1 | B187: =COUNTIF($D$4:$D$1266,D187) -> 1 | C187: 催コード | D187: MOYOSHICD | E187: character varying | F187: 8 | H187: 8 | L187: VARCHAR2
A188: =COUNTIF($C$4:$C$1266,C188) -> 1 | B188: =COUNTIF($D$4:$D$1266,D188) -> 1 | C188: 取引区分 | D188: TORIHIKIKBN | E188: character varying | F188: 4 | H188: 4 | L188: VARCHAR2
A189: =COUNTIF($C$4:$C$1266,C189) -> 1 | B189: =COUNTIF($D$4:$D$1266,D189) -> 1 | C189: 取引詳細コード | D189: TORI_SHOSAICD | E189: character varying | F189: 2 | H189: 2 | L189: VARCHAR2
A190: =COUNTIF($C$4:$C$1266,C190) -> 1 | B190: =COUNTIF($D$4:$D$1266,D190) -> 1 | C190: 発生計上区分 | D190: HASSEIKEIJOKBN | E190: character varying | F190: 1 | H190: 1 | L190: VARCHAR2
A191: =COUNTIF($C$4:$C$1266,C191) -> 1 | B191: =COUNTIF($D$4:$D$1266,D191) -> 1 | C191: 計上区分 | D191: KEIJOKBN | E191: character varying | F191: 1 | H191: 1 | L191: VARCHAR2
A192: =COUNTIF($C$4:$C$1266,C192) -> 1 | B192: =COUNTIF($D$4:$D$1266,D192) -> 1 | C192: 値引種別 | D192: NEBIKISHBT | E192: character varying | F192: 4 | H192: 4 | L192: VARCHAR2
A193: =COUNTIF($C$4:$C$1266,C193) -> 1 | B193: =COUNTIF($D$4:$D$1266,D193) -> 1 | C193: 割引種別 | D193: WARIBIKISHBT | E193: character varying | F193: 4 | H193: 4 | L193: VARCHAR2
A194: =COUNTIF($C$4:$C$1266,C194) -> 1 | B194: =COUNTIF($D$4:$D$1266,D194) -> 1 | C194: カード種別 | D194: CARDSHBT | E194: character varying | F194: 3 | H194: 3 | L194: VARCHAR2
A195: =COUNTIF($C$4:$C$1266,C195) -> 1 | B195: =COUNTIF($D$4:$D$1266,D195) -> 1 | C195: 販売場所区分 | D195: HANBAIBASHOKBN | E195: character varying | F195: 1 | H195: 1 | L195: VARCHAR2
A196: =COUNTIF($C$4:$C$1266,C196) -> 1 | B196: =COUNTIF($D$4:$D$1266,D196) -> 1 | C196: 取引先口座 | D196: TORIHIKIKOZA | E196: character varying | F196: 6 | H196: 6 | L196: VARCHAR2
A197: =COUNTIF($C$4:$C$1266,C197) -> 1 | B197: =COUNTIF($D$4:$D$1266,D197) -> 1 | C197: 明細区分１ | D197: MEISIKBN1 | E197: character varying | F197: 10 | H197: 10 | L197: VARCHAR2
... A215: =COUNTIF($C$4:$C$1266,C215) -> 1 | B215: =COUNTIF($D$4:$D$1266,D215) -> 1 | C215: 行番号 | D215: GYONOTANA | E215: numeric | F215: 4 | H215: 4 | L215: NUMBER
A216: =COUNTIF($C$4:$C$1266,C216) -> 1 | B216: =COUNTIF($D$4:$D$1266,D216) -> 1 | C216: 単価 | D216: TANKATANA | E216: numeric | F216: 10,2 | H216: 10 | L216: NUMBER
A217: =COUNTIF($C$4:$C$1266,C217) -> 1 | B217: =COUNTIF($D$4:$D$1266,D217) -> 1 | C217: 数量 | D217: SURYOTANA | E217: numeric | F217: 7,2 | H217: 7 | L217: NUMBER
A218: =COUNTIF($C$4:$C$1266,C218) -> 1 | B218: =COUNTIF($D$4:$D$1266,D218) -> 1 | C218: 金額 | D218: KINGAKU | E218: numeric | F218: 11 | H218: 11 | L218: NUMBER
A219: =COUNTIF($C$4:$C$1266,C219) -> 1 | B219: =COUNTIF($D$4:$D$1266,D219) -> 1 | C219: 正味金額 | D219: SHOMIGAKU | E219: numeric | F219: 11 | H219: 11 | L219: NUMBER
A220: =COUNTIF($C$4:$C$1266,C220) -> 1 | B220: =COUNTIF($D$4:$D$1266,D220) -> 1 | C220: 予備数値１ | D220: RSVNUM1 | E220: numeric | F220: 13,2 | H220: 13 | L220: NUMBER
A221: =COUNTIF($C$4:$C$1266,C221) -> 1 | B221: =COUNTIF($D$4:$D$1266,D221) -> 1 | C221: 予備数値２ | D221: RSVNUM2 | E221: numeric | F221: 13,2 | H221: 13 | L221: NUMBER
A222: =COUNTIF($C$4:$C$1266,C222) -> 1 | B222: =COUNTIF($D$4:$D$1266,D222) -> 1 | C222: 予備数値３ | D222: RSVNUM3 | E222: numeric | F222: 13,2 | H222: 13 | L222: NUMBER
A223: =COUNTIF($C$4:$C$1266,C223) -> 1 | B223: =COUNTIF($D$4:$D$1266,D223) -> 1 | C223: 予備数値４ | D223: RSVNUM4 | E223: numeric | F223: 13,2 | H223: 13 | L223: NUMBER
A224: =COUNTIF($C$4:$C$1266,C224) -> 1 | B224: =COUNTIF($D$4:$D$1266,D224) -> 1 | C224: 予備数値５ | D224: RSVNUM5 | E224: numeric | F224: 13,2 | H224: 13 | L224: NUMBER
A225: =COUNTIF($C$4:$C$1266,C225) -> 1 | B225: =COUNTIF($D$4:$D$1266,D225) -> 1 | C225: 値札区分 | D225: NEFUDAKB | E225: character varying | F225: 1 | H225: 1 | L225: VARCHAR2
A226: =COUNTIF($C$4:$C$1266,C226) -> 1 | B226: =COUNTIF($D$4:$D$1266,D226) -> 1 | C226: 値札税区分 | D226: NEFUDAZEIKB | E226: character varying | F226: 1 | H226: 1 | L226: VARCHAR2
A227: =COUNTIF($C$4:$C$1266,C227) -> 1 | B227: =COUNTIF($D$4:$D$1266,D227) -> 1 | C227: 予備区分１ | D227: RSVKBN1 | E227: character varying | F227: 1 | H227: 1 | L227: VARCHAR2
A228: =COUNTIF($C$4:$C$1266,C228) -> 1 | B228: =COUNTIF($D$4:$D$1266,D228) -> 1 | C228: 予備区分２ | D228: RSVKBN2 | E228: character varying | F228: 1 | H228: 1 | L228: VARCHAR2
A229: =COUNTIF($C$4:$C$1266,C229) -> 1 | B229: =COUNTIF($D$4:$D$1266,D229) -> 1 | C229: 予備区分３ | D229: RSVKBN3 | E229: character varying | F229: 1 | H229: 1 | L229: VARCHAR2
A230: =COUNTIF($C$4:$C$1266,C230) -> 1 | B230: =COUNTIF($D$4:$D$1266,D230) -> 1 | C230: 予備区分４ | D230: RSVKBN4 | E230: character varying | F230: 1 | H230: 1 | L230: VARCHAR2
...

Sheet 売価還元単位別日別実績
B2: ユーザインタフェース 設計書 | J2: サブシステム分類 | O2: ドキュメント ID | T2: ドキュメント名 | BK2: 更新者 | BN2: 最終更新日 | BR2: 履歴 | BT2: 作成者 | BW2: 作成日
J3: 商品勘定 | O3: 2.04 | T3: テーブル定義 | BR3: 第1版 | BT3: 富士通 | BW3: 42917
B5: 概念データ名／ID | J5: 売価還元単位別日別実績テーブル | U5: ／ | V5: LBT01_BAIKAN_D | AD5: OID | AK5: 最大レコード長 | AR5: =ROUNDUP((27+ROUNDUP((MAX(B:B)-COUNTIF(AB:AB,"○"))/8,0)+IF(AF5="",0,4))/8,0)*8+SUM(AO8:AO1039) -> 1888 | AU5: Byte | AW5: 用途 | BB5: 商品勘定実績を日単位で管理する。
B7: 項番 | D7: 項目論理名称 | L7: 項目物理名称 | T7: PKey | V7: IDX1 | X7: IDX2 | Z7: IDX3 | AB7: NOTNULL | AE7: DEFAULT | AH7: Type | AM7: 桁数 | AO7: Byte | AQ7: 項目説明 | BR7: 備考
B8: 1 | D8: 年月日 | L8: =VLOOKUP(D8,カラムID辞書!$C$4:$D$1266,2,FALSE) -> YMD | T8: 1 | AB8: =IF(L8="DELDTE","","○") -> ○ | AE8: =IF(AB8="○",IF(AH8="timestamp","now()",IF(LEFT(AH8,9)="character","' '","0")),"") -> 0 | AH8: =VLOOKUP(D8,カラムID辞書!C:H,3,FALSE) -> numeric | AM8: =VLOOKUP(D8,カラムID辞書!C:H,4,FALSE) -> 8 | AO8: =VLOOKUP(D8,カラムID辞書!C:H,6,FALSE) -> 8 | AQ8: 伝票計上日（修正伝票は月末日）
B9: =IF($D9="","",MAX(OFFSET($B$8,0,0,ROW()-ROW($B$8),2))+1) -> 2 | D9: SEQ№ | L9: =VLOOKUP(D9,カラムID辞書!$C$4:$D$1266,2,FALSE) -> SEQNO | T9: 2 | AB9: =IF(L9="DELDTE","","○") -> ○ | AE9: =IF(AB9="○",IF(AH9="timestamp","now()",IF(LEFT(AH9,9)="character","' '","0")),"") -> 0 | AH9: =VLOOKUP(D9,カラムID辞書!C:H,3,FALSE) -> numeric | AM9: =VLOOKUP(D9,カラムID辞書!C:H,4,FALSE) -> 2 | AO9: =VLOOKUP(D9,カラムID辞書!C:H,6,FALSE) -> 2
B10: =IF($D10="","",MAX(OFFSET($B$8,0,0,ROW()-ROW($B$8),2))+1) -> 3 | D10: システムグループコード | L10: =VLOOKUP(D10,カラムID辞書!$C$4:$D$1266,2,FALSE) -> SYSGRPCD | T10: 3 | AB10: =IF(L10="DELDTE","","○") -> ○ | AE10: =IF(AB10="○",IF(AH10="timestamp","now()",IF(LEFT(AH10,9)="character","' '","0")),"") -> ' ' | AH10: =VLOOKUP(D10,カラムID辞書!C:H,3,FALSE) -> character varying | AM10: =VLOOKUP(D10,カラムID辞書!C:H,4,FALSE) -> 4 | AO10: =VLOOKUP(D10,カラムID辞書!C:H,6,FALSE) -> 4 | AQ10: ユーザ分類コード | BR10: "0010"固定
B11: =IF($D11="","",MAX(OFFSET($B$8,0,0,ROW()-ROW($B$8),2))+1) -> 4 | D11: 企業グループコード | L11: =VLOOKUP(D11,カラムID辞書!$C$4:$D$1266,2,FALSE) -> KGYGRPCD | T11: 4 | AB11: =IF(L11="DELDTE","","○") -> ○ | AE11: =IF(AB11="○",IF(AH11="timestamp","now()",IF(LEFT(AH11,9)="character","' '","0")),"") -> ' ' | AH11: =VLOOKUP(D11,カラムID辞書!C:H,3,FALSE) -> character varying | AM11: =VLOOKUP(D11,カラムID辞書!C:H,4,FALSE) -> 3 | AO11: =VLOOKUP(D11,カラムID辞書!C:H,6,FALSE) -> 3 | AQ11: 売上、仕入伝票の企業グループコード
B12: =IF($D12="","",MAX(OFFSET($B$8,0,0,ROW()-ROW($B$8),2))+1) -> 5 | D12: 店コード | L12: =VLOOKUP(D12,カラムID辞書!$C$4:$D$1266,2,FALSE) -> TENCD | T12: 5 | AB12: =IF(L12="DELDTE","","○") -> ○ | AE12: =IF(AB12="○",IF(AH12="timestamp","now()",IF(LEFT(AH12,9)="character","' '","0")),"") -> ' ' | AH12: =VLOOKUP(D12,カラムID辞書!C:H,3,FALSE) -> character varying | AM12: =VLOOKUP(D12,カラムID辞書!C:H,4,FALSE) -> 4 | AO12: =VLOOKUP(D12,カラムID辞書!C:H,6,FALSE) -> 4 | AQ12: 売上、仕入伝票の店コード
B13: =IF($D13="","",MAX(OFFSET($B$8,0,0,ROW()-ROW($B$8),2))+1) -> 6 | D13: 商品コード１ | L13: =VLOOKUP(D13,カラムID辞書!$C$4:$D$1266,2,FALSE) -> SHOHINCD1 | T13: 6 | AB13: =IF(L13="DELDTE","","○") -> ○ | AE13: =IF(AB13="○",IF(AH13="timestamp","now()",IF(LEFT(AH13,9)="character","' '","0")),"") -> ' ' | AH13: =VLOOKUP(D13,カラムID辞書!C:H,3,FALSE) -> character varying | AM13: =VLOOKUP(D13,カラムID辞書!C:H,4,FALSE) -> 6 | AO13: =VLOOKUP(D13,カラムID辞書!C:H,6,FALSE) -> 6 | AQ13: 売上、仕入伝票の商品コード１ | BR13: 品番
B14: =IF($D14="","",MAX(OFFSET($B$8,0,0,ROW()-ROW($B$8),2))+1) -> 7 | D14: 商品コード２ | L14: =VLOOKUP(D14,カラムID辞書!$C$4:$D$1266,2,FALSE) -> SHOHINCD2 | T14: 7 | AB14: =IF(L14="DELDTE","","○") -> ○ | AE14: =IF(AB14="○",IF(AH14="timestamp","now()",IF(LEFT(AH14,9)="character","' '","0")),"") -> ' ' | AH14: =VLOOKUP(D14,カラムID辞書!C:H,3,FALSE) -> character varying | AM14: =VLOOKUP(D14,カラムID辞書!C:H,4,FALSE) -> 6 | AO14: =VLOOKUP(D14,カラムID辞書!C:H,6,FALSE) -> 6 | AQ14: 売上、仕入伝票の商品コード２ | BR14: （未設定）
B15: =IF($D15="","",MAX(OFFSET($B$8,0,0,ROW()-ROW($B$8),2))+1) -> 8 | D15: 商品コード３ | L15: =VLOOKUP(D15,カラムID辞書!$C$4:$D$1266,2,FALSE) -> SHOHINCD3 | T15: 8 | AB15: =IF(L15="DELDTE","","○") -> ○ | AE15: =IF(AB15="○",IF(AH15="timestamp","now()",IF(LEFT(AH15,9)="character","' '","0")),"") -> ' ' | AH15: =VLOOKUP(D15,カラムID辞書!C:H,3,FALSE) -> character varying | AM15: =VLOOKUP(D15,カラムID辞書!C:H,4,FALSE) -> 6 | AO15: =VLOOKUP(D15,カラムID辞書!C:H,6,FALSE) -> 6 | AQ15: 売上、仕入伝票の商品コード３ | BR15: （未設定）
B16: =IF($D16="","",MAX(OFFSET($B$8,0,0,ROW()-ROW($B$8),2))+1) -> 9 | D16: 商品コード４ | L16: =VLOOKUP(D16,カラムID辞書!$C$4:$D$1266,2,FALSE) -> SHOHINCD4 | T16: 9 | AB16: =IF(L16="DELDTE","","○") -> ○ | AE16: =IF(AB16="○",IF(AH16="timestamp","now()",IF(LEFT(AH16,9)="character","' '","0")),"") -> ' ' | AH16: =VLOOKUP(D16,カラムID辞書!C:H,3,FALSE) -> character varying | AM16: =VLOOKUP(D16,カラムID辞書!C:H,4,FALSE) -> 6 | AO16: =VLOOKUP(D16,カラムID辞書!C:H,6,FALSE) -> 6 | AQ16: 売上、仕入伝票の商品コード４ | BR16: （未設定）
B17: =IF($D17="","",MAX(OFFSET($B$8,0,0,ROW()-ROW($B$8),2))+1) -> 10 | D17: 商品コード５ | L17: =VLOOKUP(D17,カラムID辞書!$C$4:$D$1266,2,FALSE) -> SHOHINCD5 | T17: 10 | AB17: =IF(L17="DELDTE","","○") -> ○ | AE17: =IF(AB17="○",IF(AH17="timestamp","now()",IF(LEFT(AH17,9)="character","' '","0")),"") -> ' ' | AH17: =VLOOKUP(D17,カラムID辞書!C:H,3,FALSE) -> character varying | AM17: =VLOOKUP(D17,カラムID辞書!C:H,4,FALSE) -> 6 | AO17: =VLOOKUP(D17,カラムID辞書!C:H,6,FALSE) -> 6 | AQ17: 売上、仕入伝票の商品コード５ | BR17: （未設定）
B18: =IF($D18="","",MAX(OFFSET($B$8,0,0,ROW()-ROW($B$8),2))+1) -> 11 | D18: 細別コード１ | L18: =VLOOKUP(D18,カラムID辞書!$C$4:$D$1266,2,FALSE) -> SIBTCD1 | T18: 11 | AB18: =IF(L18="DELDTE","","○") -> ○ | AE18: =IF(AB18="○",IF(AH18="timestamp","now()",IF(LEFT(AH18,9)="character","' '","0")),"") -> ' ' | AH18: =VLOOKUP(D18,カラムID辞書!C:H,3,FALSE) -> character varying | AM18: =VLOOKUP(D18,カラムID辞書!C:H,4,FALSE) -> 10 | AO18: =VLOOKUP(D18,カラムID辞書!C:H,6,FALSE) -> 10 | AQ18: 売上、仕入伝票の細別コード１ | BR18: （未設定）
B19: =IF($D19="","",MAX(OFFSET($B$8,0,0,ROW()-ROW($B$8),2))+1) -> 12 | D19: 細別コード２ | L19: =VLOOKUP(D19,カラムID辞書!$C$4:$D$1266,2,FALSE) -> SIBTCD2 | T19: 12 | AB19: =IF(L19="DELDTE","","○") -> ○ | AE19: =IF(AB19="○",IF(AH19="timestamp","now()",IF(LEFT(AH19,9)="character","' '","0")),"") -> ' ' | AH19: =VLOOKUP(D19,カラムID辞書!C:H,3,FALSE) -> character varying | AM19: =VLOOKUP(D19,カラムID辞書!C:H,4,FALSE) -> 10 | AO19: =VLOOKUP(D19,カラムID辞書!C:H,6,FALSE) -> 10 | AQ19: 売上、仕入伝票の細別コード２ | BR19: （未設定）
B20: =IF($D20="","",MAX(OFFSET($B$8,0,0,ROW()-ROW($B$8),2))+1) -> 13 | D20: 単品コード１ | L20: =VLOOKUP(D20,カラムID辞書!$C$4:$D$1266,2,FALSE) -> TNPNCD1 | T20: 13 | AB20: =IF(L20="DELDTE","","○") -> ○ | AE20: =IF(AB20="○",IF(AH20="timestamp","now()",IF(LEFT(AH20,9)="character","' '","0")),"") -> ' ' | AH20: =VLOOKUP(D20,カラムID辞書!C:H,3,FALSE) -> character varying | AM20: =VLOOKUP(D20,カラムID辞書!C:H,4,FALSE) -> 13 | AO20: =VLOOKUP(D20,カラムID辞書!C:H,6,FALSE) -> 13 | AQ20: 売上、仕入伝票の単品コード１ | BR20: （未設定）
B21: =IF($D21="","",MAX(OFFSET($B$8,0,0,ROW()-ROW($B$8),2))+1) -> 14 | D21: 単品コード２ | L21: =VLOOKUP(D21,カラムID辞書!$C$4:$D$1266,2,FALSE) -> TNPNCD2 | T21: 14 | AB21: =IF(L21="DELDTE","","○") -> ○ | AE21: =IF(AB21="○",IF(AH21="timestamp","now()",IF(LEFT(AH21,9)="character","' '","0")),"") -> ' ' | AH21: =VLOOKUP(D21,カラムID辞書!C:H,3,FALSE) -> character varying | AM21: =VLOOKUP(D21,カラムID辞書!C:H,4,FALSE) -> 13 | AO21: =VLOOKUP(D21,カラムID辞書!C:H,6,FALSE) -> 13 | AQ21: 売上、仕入伝票の単品コード２ | BR21: （未設定）
B22: =IF($D22="","",MAX(OFFSET($B$8,0,0,ROW()-ROW($B$8),2))+1) -> 15 | D22: 仕入区分 | L22: =VLOOKUP(D22,カラムID辞書!$C$4:$D$1266,2,FALSE) -> SHIIREKBN | T22: 15 | AB22: =IF(L22="DELDTE","","○") -> ○ | AE22: =IF(AB22="○",IF(AH22="timestamp","now()",IF(LEFT(AH22,9)="character","' '","0")),"") -> ' ' | AH22: =VLOOKUP(D22,カラムID辞書!C:H,3,FALSE) -> character varying | AM22: =VLOOKUP(D22,カラムID辞書!C:H,4,FALSE) -> 2 | AO22: =VLOOKUP(D22,カラムID辞書!C:H,6,FALSE) -> 2 | AQ22: 01：直扱 / 04：売仕
B23: =IF($D23="","",MAX(OFFSET($B$8,0,0,ROW()-ROW($B$8),2))+1) -> 16 | D23: 原価管理区分 | L23: =VLOOKUP(D23,カラムID辞書!$C$4:$D$1266,2,FALSE) -> GNKKBN | T23: 16 | AB23: =IF(L23="DELDTE","","○") -> ○ | AE23: =IF(AB23="○",IF(AH23="timestamp","now()",IF(LEFT(AH23,9)="character","' '","0")),"") -> ' ' | AH23: =VLOOKUP(D23,カラムID辞書!C:H,3,FALSE) -> character varying | AM23: =VLOOKUP(D23,カラムID辞書!C:H,4,FALSE) -> 1 | AO23: =VLOOKUP(D23,カラムID辞書!C:H,6,FALSE) -> 1 | AQ23: 1：売価品 / 2：原価品
B24: =IF($D24="","",MAX(OFFSET($B$8,0,0,ROW()-ROW($B$8),2))+1) -> 17 | D24: ＤＳ区分 | L24: =VLOOKUP(D24,カラムID辞書!$C$4:$D$1266,2,FALSE) -> DSKBN | T24: 17 | AB24: =IF(L24="DELDTE","","○") -> ○ | AE24: =IF(AB24="○",IF(AH24="timestamp","now()",IF(LEFT(AH24,9)="character","' '","0")),"") -> ' ' | AH24: =VLOOKUP(D24,カラムID辞書!C:H,3,FALSE) -> character varying | AM24: =VLOOKUP(D24,カラムID辞書!C:H,4,FALSE) -> 1 | AO24: =VLOOKUP(D24,カラムID辞書!C:H,6,FALSE) -> 1 | AQ24: 0：プロパー / 1：セール
B25: =IF($D25="","",MAX(OFFSET($B$8,0,0,ROW()-ROW($B$8),2))+1) -> 18 | D25: 利益計算式区分 | L25: =VLOOKUP(D25,カラムID辞書!$C$4:$D$1266,2,FALSE) -> RIEKICMPKBN | T25: 18 | AB25: =IF(L25="DELDTE","","○") -> ○ | AE25: =IF(AB25="○",IF(AH25="timestamp","now()",IF(LEFT(AH25,9)="character","' '","0")),"") -> ' ' | AH25: =VLOOKUP(D25,カラムID辞書!C:H,3,FALSE) -> character varying | AM25: =VLOOKUP(D25,カラムID辞書!C:H,4,FALSE) -> 1 | AO25: =VLOOKUP(D25,カラムID辞書!C:H,6,FALSE) -> 1 | AQ25: 0：利益計算対象外 / 1：売価還元原価法 / 3：売仕原価計算 /7：原価品計算
B26: =IF($D26="","",MAX(OFFSET($B$8,0,0,ROW()-ROW($B$8),2))+1) -> 19 | D26: 年月 | L26: =VLOOKUP(D26,カラムID辞書!$C$4:$D$1266,2,FALSE) -> YM | AB26: =IF(L26="DELDTE","","○") -> ○ | AE26: =IF(AB26="○",IF(AH26="timestamp","now()",IF(LEFT(AH26,9)="character","' '","0")),"") -> 0 | AH26: =VLOOKUP(D26,カラムID辞書!C:H,3,FALSE) -> numeric | AM26: =VLOOKUP(D26,カラムID辞書!C:H,4,FALSE) -> 6 | AO26: =VLOOKUP(D26,カラムID辞書!C:H,6,FALSE) -> 6 | AQ26: 「年月日」に該当する年月
B27: =IF($D27="","",MAX(OFFSET($B$8,0,0,ROW()-ROW($B$8),2))+1) -> 20 | D27: 期 | L27: =VLOOKUP(D27,カラムID辞書!$C$4:$D$1266,2,FALSE) -> NENKI | AB27: =IF(L27="DELDTE","","○") -> ○ | AE27: =IF(AB27="○",IF(AH27="timestamp","now()",IF(LEFT(AH27,9)="character","' '","0")),"") -> 0 | AH27: =VLOOKUP(D27,カラムID辞書!C:H,3,FALSE) -> numeric | AM27: =VLOOKUP(D27,カラムID辞書!C:H,4,FALSE) -> 6 | AO27: =VLOOKUP(D27,カラムID辞書!C:H,6,FALSE) -> 6 | AQ27: 「年月日」に該当する期首月（YYYYMM）
B28: =IF($D28="","",MAX(OFFSET($B$8,0,0,ROW()-ROW($B$8),2))+1) -> 21 | D28: 年 | L28: =VLOOKUP(D28,カラムID辞書!$C$4:$D$1266,2,FALSE) -> NENDO | AB28: =IF(L28="DELDTE","","○") -> ○ | AE28: =IF(AB28="○",IF(AH28="timestamp","now()",IF(LEFT(AH28,9)="character","' '","0")),"") -> 0 | AH28: =VLOOKUP(D28,カラムID辞書!C:H,3,FALSE) -> numeric | AM28: =VLOOKUP(D28,カラムID辞書!C:H,4,FALSE) -> 6 | AO28: =VLOOKUP(D28,カラムID辞書!C:H,6,FALSE) -> 6 | AQ28: 「年月日」に該当する年度開始月（YYYYMM）
B29: =IF($D29="","",MAX(OFFSET($B$8,0,0,ROW()-ROW($B$8),2))+1) -> 22 | D29: 売上高原価 | L29: =VLOOKUP(D29,カラムID辞書!$C$4:$D$1266,2,FALSE) -> URIAGED_GNK | AB29: =IF(L29="DELDTE","","○") -> ○ | AE29: =IF(AB29="○",IF(AH29="timestamp","now()",IF(LEFT(AH29,9)="character","' '","0")),"") -> 0 | AH29: =VLOOKUP(D29,カラムID辞書!C:H,3,FALSE) -> numeric | AM29: =VLOOKUP(D29,カラムID辞書!C:H,4,FALSE) -> 13 | AO29: =VLOOKUP(D29,カラムID辞書!C:H,6,FALSE) -> 13 | AQ29: 別紙「商品勘定利益計算」参照
B30: =IF($D30="","",MAX(OFFSET($B$8,0,0,ROW()-ROW($B$8),2))+1) -> 23 | D30: 売上高売価 | L30: =VLOOKUP(D30,カラムID辞書!$C$4:$D$1266,2,FALSE) -> URIAGED_BIK | AB30: =IF(L30="DELDTE","","○") -> ○ | AE30: =IF(AB30="○",IF(AH30="timestamp","now()",IF(LEFT(AH30,9)="character","' '","0")),"") -> 0 | AH30: =VLOOKUP(D30,カラムID辞書!C:H,3,FALSE) -> numeric | AM30: =VLOOKUP(D30,カラムID辞書!C:H,4,FALSE) -> 13 | AO30: =VLOOKUP(D30,カラムID辞書!C:H,6,FALSE) -> 13 | AQ30: 売上伝票の売上高集計値（総売上高）
B31: =IF($D31="","",MAX(OFFSET($B$8,0,0,ROW()-ROW($B$8),2))+1) -> 24 | D31: 売上高分類１ | L31: =VLOOKUP(D31,カラムID辞書!$C$4:$D$1266,2,FALSE) -> URIAGED_BNRI1 | AB31: =IF(L31="DELDTE","","○") -> ○ | AE31: =IF(AB31="○",IF(AH31="timestamp","now()",IF(LEFT(AH31,9)="character","' '","0")),"") -> 0 | AH31: =VLOOKUP(D31,カラムID辞書!C:H,3,FALSE) -> numeric | AM31: =VLOOKUP(D31,カラムID辞書!C:H,4,FALSE) -> 13 | AO31: =VLOOKUP(D31,カラムID辞書!C:H,6,FALSE) -> 13 | AQ31: 売上伝票の売上高集計値（店頭・普通品）
B32: =IF($D32="","",MAX(OFFSET($B$8,0,0,ROW()-ROW($B$8),2))+1) -> 25 | D32: 売上高分類２ | L32: =VLOOKUP(D32,カラムID辞書!$C$4:$D$1266,2,FALSE) -> URIAGED_BNRI2 | AB32: =IF(L32="DELDTE","","○") -> ○ | AE32: =IF(AB32="○",IF(AH32="timestamp","now()",IF(LEFT(AH32,9)="character","' '","0")),"") -> 0 | AH32: =VLOOKUP(D32,カラムID辞書!C:H,3,FALSE) -> numeric | AM32: =VLOOKUP(D32,カラムID辞書!C:H,4,FALSE) -> 13 | AO32: =VLOOKUP(D32,カラムID辞書!C:H,6,FALSE) -> 13 | AQ32: 売上伝票の売上高集計値（店頭・催事）
B33: =IF($D33="","",MAX(OFFSET($B$8,0,0,ROW()-ROW($B$8),2))+1) -> 26 | D33: 売上高分類３ | L33: =VLOOKUP(D33,カラムID辞書!$C$4:$D$1266,2,FALSE) -> URIAGED_BNRI3 | AB33: =IF(L33="DELDTE","","○") -> ○ | AE33: =IF(AB33="○",IF(AH33="timestamp","now()",IF(LEFT(AH33,9)="character","' '","0")),"") -> 0 | AH33: =VLOOKUP(D33,カラムID辞書!C:H,3,FALSE) -> numeric | AM33: =VLOOKUP(D33,カラムID辞書!C:H,4,FALSE) -> 13 | AO33: =VLOOKUP(D33,カラムID辞書!C:H,6,FALSE) -> 13 | AQ33: 売上伝票の売上高集計値（店頭・店外）
B34: =IF($D34="","",MAX(OFFSET($B$8,0,0,ROW()-ROW($B$8),2))+1) -> 27 | D34: 売上高分類４ | L34: =VLOOKUP(D34,カラムID辞書!$C$4:$D$1266,2,FALSE) -> URIAGED_BNRI4 | AB34: =IF(L34="DELDTE","","○") -> ○ | AE34: =IF(AB34="○",IF(AH34="timestamp","now()",IF(LEFT(AH34,9)="character","' '","0")),"") -> 0 | AH34: =VLOOKUP(D34,カラムID辞書!C:H,3,FALSE) -> numeric | AM34: =VLOOKUP(D34,カラムID辞書!C:H,4,FALSE) -> 13 | AO34: =VLOOKUP(D34,カラムID辞書!C:H,6,FALSE) -> 13 | AQ34: 売上伝票の売上高集計値（店頭・ギフト）
B35: =IF($D35="","",MAX(OFFSET($B$8,0,0,ROW()-ROW($B$8),2))+1) -> 28 | D35: 売上高分類５ | L35: =VLOOKUP(D35,カラムID辞書!$C$4:$D$1266,2,FALSE) -> URIAGED_BNRI5 | AB35: =IF(L35="DELDTE","","○") -> ○ | AE35: =IF(AB35="○",IF(AH35="timestamp","now()",IF(LEFT(AH35,9)="character","' '","0")),"") -> 0 | AH35: =VLOOKUP(D35,カラムID辞書!C:H,3,FALSE) -> numeric | AM35: =VLOOKUP(D35,カラムID辞書!C:H,4,FALSE) -> 13 | AO35: =VLOOKUP(D35,カラムID辞書!C:H,6,FALSE) -> 13 | AQ35: 売上伝票の売上高集計値（店頭・ネット）
B36: =IF($D36="","",MAX(OFFSET($B$8,0,0,ROW()-ROW($B$8),2))+1) -> 29 | D36: 売上高分類６ | L36: =VLOOKUP(D36,カラムID辞書!$C$4:$D$1266,2,FALSE) -> URIAGED_BNRI6 | AB36: =IF(L36="DELDTE","","○") -> ○ | AE36: =IF(AB36="○",IF(AH36="timestamp","now()",IF(LEFT(AH36,9)="character","' '","0")),"") -> 0 | AH36: =VLOOKUP(D36,カラムID辞書!C:H,3,FALSE) -> numeric | AM36: =VLOOKUP(D36,カラムID辞書!C:H,4,FALSE) -> 13 | AO36: =VLOOKUP(D36,カラムID辞書!C:H,6,FALSE) -> 13 | AQ36: 売上伝票の売上高集計値（店頭・その他）
B37: =IF($D37="","",MAX(OFFSET($B$8,0,0,ROW()-ROW($B$8),2))+1) -> 30 | D37: 売上高分類７ | L37: =VLOOKUP(D37,カラムID辞書!$C$4:$D$1266,2,FALSE) -> URIAGED_BNRI7 | AB37: =IF(L37="DELDTE","","○") -> ○ | AE37: =IF(AB37="○",IF(AH37="timestamp","now()",IF(LEFT(AH37,9)="character","' '","0")),"") -> 0 | AH37: =VLOOKUP(D37,カラムID辞書!C:H,3,FALSE) -> numeric | AM37: =VLOOKUP(D37,カラムID辞書!C:H,4,FALSE) -> 13 | AO37: =VLOOKUP(D37,カラムID辞書!C:H,6,FALSE) -> 13 | AQ37: 売上伝票の売上高集計値（非店頭・店外）
... B39: =IF($D39="","",MAX(OFFSET($B$8,0,0,ROW()-ROW($B$8),2))+1) -> 32 | D39: 売上高分類９ | L39: =VLOOKUP(D39,カラムID辞書!$C$4:$D$1266,2,FALSE) -> URIAGED_BNRI9 | AB39: =IF(L39="DELDTE","","○") -> ○ | AE39: =IF(AB39="○",IF(AH39="timestamp","now()",IF(LEFT(AH39,9)="character","' '","0")),"") -> 0 | AH39: =VLOOKUP(D39,カラムID辞書!C:H,3,FALSE) -> numeric | AM39: =VLOOKUP(D39,カラムID辞書!C:H,4,FALSE) -> 13 | AO39: =VLOOKUP(D39,カラムID辞書!C:H,6,FALSE) -> 13 | AQ39: 売上伝票の売上高集計値（非店頭・その他）
B40: =IF($D40="","",MAX(OFFSET($B$8,0,0,ROW()-ROW($B$8),2))+1) -> 33 | D40: 売上高分類１０ | L40: =VLOOKUP(D40,カラムID辞書!$C$4:$D$1266,2,FALSE) -> URIAGED_BNRI10 | AB40: =IF(L40="DELDTE","","○") -> ○ | AE40: =IF(AB40="○",IF(AH40="timestamp","now()",IF(LEFT(AH40,9)="character","' '","0")),"") -> 0 | AH40: =VLOOKUP(D40,カラムID辞書!C:H,3,FALSE) -> numeric | AM40: =VLOOKUP(D40,カラムID辞書!C:H,4,FALSE) -> 13 | AO40: =VLOOKUP(D40,カラムID辞書!C:H,6,FALSE) -> 13 | BR40: （未設定：ZERO）
B41: =IF($D41="","",MAX(OFFSET($B$8,0,0,ROW()-ROW($B$8),2))+1) -> 34 | D41: 売上高数量 | L41: =VLOOKUP(D41,カラムID辞書!$C$4:$D$1266,2,FALSE) -> URIAGED_SU | AB41: =IF(L41="DELDTE","","○") -> ○ | AE41: =IF(AB41="○",IF(AH41="timestamp","now()",IF(LEFT(AH41,9)="character","' '","0")),"") -> 0 | AH41: =VLOOKUP(D41,カラムID辞書!C:H,3,FALSE) -> numeric | AM41: =VLOOKUP(D41,カラムID辞書!C:H,4,FALSE) -> 10 | AO41: =VLOOKUP(D41,カラムID辞書!C:H,6,FALSE) -> 10 | AQ41: 売上伝票の売上数量集計値
B42: =IF($D42="","",MAX(OFFSET($B$8,0,0,ROW()-ROW($B$8),2))+1) -> 35 | D42: 利益高 | L42: =VLOOKUP(D42,カラムID辞書!$C$4:$D$1266,2,FALSE) -> RIEKID | AB42: =IF(L42="DELDTE","","○") -> ○ | AE42: =IF(AB42="○",IF(AH42="timestamp","now()",IF(LEFT(AH42,9)="character","' '","0")),"") -> 0 | AH42: =VLOOKUP(D42,カラムID辞書!C:H,3,FALSE) -> numeric | AM42: =VLOOKUP(D42,カラムID辞書!C:H,4,FALSE) -> 13 | AO42: =VLOOKUP(D42,カラムID辞書!C:H,6,FALSE) -> 13 | AQ42: 別紙「商品勘定利益計算」参照 | BR42: 売益金
B43: =IF($D43="","",MAX(OFFSET($B$8,0,0,ROW()-ROW($B$8),2))+1) -> 36 | D43: 割引額 | L43: =VLOOKUP(D43,カラムID辞書!$C$4:$D$1266,2,FALSE) -> WARIBIKI_GAK | AB43: =IF(L43="DELDTE","","○") -> ○ | AE43: =IF(AB43="○",IF(AH43="timestamp","now()",IF(LEFT(AH43,9)="character","' '","0")),"") -> 0 | AH43: =VLOOKUP(D43,カラムID辞書!C:H,3,FALSE) -> numeric | AM43: =VLOOKUP(D43,カラムID辞書!C:H,4,FALSE) -> 13 | AO43: =VLOOKUP(D43,カラムID辞書!C:H,6,FALSE) -> 13 | AQ43: 売上伝票の割引額集計値
B44: =IF($D44="","",MAX(OFFSET($B$8,0,0,ROW()-ROW($B$8),2))+1) -> 37 | D44: 値引額 | L44: =VLOOKUP(D44,カラムID辞書!$C$4:$D$1266,2,FALSE) -> NEBIKI_GAK | AB44: =IF(L44="DELDTE","","○") -> ○ | AE44: =IF(AB44="○",IF(AH44="timestamp","now()",IF(LEFT(AH44,9)="character","' '","0")),"") -> 0 | AH44: =VLOOKUP(D44,カラムID辞書!C:H,3,FALSE) -> numeric | AM44: =VLOOKUP(D44,カラムID辞書!C:H,4,FALSE) -> 13 | AO44: =VLOOKUP(D44,カラムID辞書!C:H,6,FALSE) -> 13 | AQ44: 売上伝票の値引額集計値
B45: =IF($D45="","",MAX(OFFSET($B$8,0,0,ROW()-ROW($B$8),2))+1) -> 38 | D45: 客数１ | L45: =VLOOKUP(D45,カラムID辞書!$C$4:$D$1266,2,FALSE) -> KYAKU1_SU | AB45: =IF(L45="DELDTE","","○") -> ○ | AE45: =IF(AB45="○",IF(AH45="timestamp","now()",IF(LEFT(AH45,9)="character","' '","0")),"") -> 0 | AH45: =VLOOKUP(D45,カラムID辞書!C:H,3,FALSE) -> numeric | AM45: =VLOOKUP(D45,カラムID辞書!C:H,4,FALSE) -> 10,2 | AO45: =VLOOKUP(D45,カラムID辞書!C:H,6,FALSE) -> 10 | AQ45: 売上伝票の客数１集計値
B46: =IF($D46="","",MAX(OFFSET($B$8,0,0,ROW()-ROW($B$8),2))+1) -> 39 | D46: 客数２ | L46: =VLOOKUP(D46,カラムID辞書!$C$4:$D$1266,2,FALSE) -> KYAKU2_SU | AB46: =IF(L46="DELDTE","","○") -> ○ | AE46: =IF(AB46="○",IF(AH46="timestamp","now()",IF(LEFT(AH46,9)="character","' '","0")),"") -> 0 | AH46: =VLOOKUP(D46,カラムID辞書!C:H,3,FALSE) -> numeric | AM46: =VLOOKUP(D46,カラムID辞書!C:H,4,FALSE) -> 10,2 | AO46: =VLOOKUP(D46,カラムID辞書!C:H,6,FALSE) -> 10 | AQ46: 売上伝票の客数２集計値
B47: =IF($D47="","",MAX(OFFSET($B$8,0,0,ROW()-ROW($B$8),2))+1) -> 40 | D47: 客数３ | L47: =VLOOKUP(D47,カラムID辞書!$C$4:$D$1266,2,FALSE) -> KYAKU3_SU | AB47: =IF(L47="DELDTE","","○") -> ○ | AE47: =IF(AB47="○",IF(AH47="timestamp","now()",IF(LEFT(AH47,9)="character","' '","0")),"") -> 0 | AH47: =VLOOKUP(D47,カラムID辞書!C:H,3,FALSE) -> numeric | AM47: =VLOOKUP(D47,カラムID辞書!C:H,4,FALSE) -> 10,2 | AO47: =VLOOKUP(D47,カラムID辞書!C:H,6,FALSE) -> 10 | AQ47: 売上伝票の客数３集計値 | BR47: （未設定：ZERO）
B48: =IF($D48="","",MAX(OFFSET($B$8,0,0,ROW()-ROW($B$8),2))+1) -> 41 | D48: 純仕入高原価 | L48: =VLOOKUP(D48,カラムID辞書!$C$4:$D$1266,2,FALSE) -> JNSHIIRED_GNK | AB48: =IF(L48="DELDTE","","○") -> ○ | AE48: =IF(AB48="○",IF(AH48="timestamp","now()",IF(LEFT(AH48,9)="character","' '","0")),"") -> 0 | AH48: =VLOOKUP(D48,カラムID辞書!C:H,3,FALSE) -> numeric | AM48: =VLOOKUP(D48,カラムID辞書!C:H,4,FALSE) -> 13 | AO48: =VLOOKUP(D48,カラムID辞書!C:H,6,FALSE) -> 13 | AQ48: 別紙「商品勘定利益計算」参照
B49: =IF($D49="","",MAX(OFFSET($B$8,0,0,ROW()-ROW($B$8),2))+1) -> 42 | D49: 純仕入高売価 | L49: =VLOOKUP(D49,カラムID辞書!$C$4:$D$1266,2,FALSE) -> JNSHIIRED_BIK | AB49: =IF(L49="DELDTE","","○") -> ○ | AE49: =IF(AB49="○",IF(AH49="timestamp","now()",IF(LEFT(AH49,9)="character","' '","0")),"") -> 0 | AH49: =VLOOKUP(D49,カラムID辞書!C:H,3,FALSE) -> numeric | AM49: =VLOOKUP(D49,カラムID辞書!C:H,4,FALSE) -> 13 | AO49: =VLOOKUP(D49,カラムID辞書!C:H,6,FALSE) -> 13 | AQ49: 別紙「商品勘定利益計算」参照
B50: =IF($D50="","",MAX(OFFSET($B$8,0,0,ROW()-ROW($B$8),2))+1) -> 43 | D50: 純仕入高数量 | L50: =VLOOKUP(D50,カラムID辞書!$C$4:$D$1266,2,FALSE) -> JNSHIIRED_SU | AB50: =IF(L50="DELDTE","","○") -> ○ | AE50: =IF(AB50="○",IF(AH50="timestamp","now()",IF(LEFT(AH50,9)="character","' '","0")),"") -> 0 | AH50: =VLOOKUP(D50,カラムID辞書!C:H,3,FALSE) -> numeric | AM50: =VLOOKUP(D50,カラムID辞書!C:H,4,FALSE) -> 10 | AO50: =VLOOKUP(D50,カラムID辞書!C:H,6,FALSE) -> 10 | AQ50: 別紙「商品勘定利益計算」参照
B51: =IF($D51="","",MAX(OFFSET($B$8,0,0,ROW()-ROW($B$8),2))+1) -> 44 | D51: 仕入高原価 | L51: =VLOOKUP(D51,カラムID辞書!$C$4:$D$1266,2,FALSE) -> SHIIRED_GNK | AB51: =IF(L51="DELDTE","","○") -> ○ | AE51: =IF(AB51="○",IF(AH51="timestamp","now()",IF(LEFT(AH51,9)="character","' '","0")),"") -> 0 | AH51: =VLOOKUP(D51,カラムID辞書!C:H,3,FALSE) -> numeric | AM51: =VLOOKUP(D51,カラムID辞書!C:H,4,FALSE) -> 13 | AO51: =VLOOKUP(D51,カラムID辞書!C:H,6,FALSE) -> 13 | AQ51: 仕入伝票の原価集計値
B52: =IF($D52="","",MAX(OFFSET($B$8,0,0,ROW()-ROW($B$8),2))+1) -> 45 | D52: 仕入高売価 | L52: =VLOOKUP(D52,カラムID辞書!$C$4:$D$1266,2,FALSE) -> SHIIRED_BIK | AB52: =IF(L52="DELDTE","","○") -> ○ | AE52: =IF(AB52="○",IF(AH52="timestamp","now()",IF(LEFT(AH52,9)="character","' '","0")),"") -> 0 | AH52: =VLOOKUP(D52,カラムID辞書!C:H,3,FALSE) -> numeric | AM52: =VLOOKUP(D52,カラムID辞書!C:H,4,FALSE) -> 13 | AO52: =VLOOKUP(D52,カラムID辞書!C:H,6,FALSE) -> 13 | AQ52: 仕入伝票の売価集計値
B53: =IF($D53="","",MAX(OFFSET($B$8,0,0,ROW()-ROW($B$8),2))+1) -> 46 | D53: 仕入高数量 | L53: =VLOOKUP(D53,カラムID辞書!$C$4:$D$1266,2,FALSE) -> SHIIRED_SU | AB53: =IF(L53="DELDTE","","○") -> ○ | AE53: =IF(AB53="○",IF(AH53="timestamp","now()",IF(LEFT(AH53,9)="character","' '","0")),"") -> 0 | AH53: =VLOOKUP(D53,カラムID辞書!C:H,3,FALSE) -> numeric | AM53: =VLOOKUP(D53,カラムID辞書!C:H,4,FALSE) -> 10 | AO53: =VLOOKUP(D53,カラムID辞書!C:H,6,FALSE) -> 10 | AQ53: 仕入伝票の数量集計値
B54: =IF($D54="","",MAX(OFFSET($B$8,0,0,ROW()-ROW($B$8),2))+1) -> 47 | D54: 付帯仕入高原価 | L54: =VLOOKUP(D54,カラムID辞書!$C$4:$D$1266,2,FALSE) -> FUTAISHIIRED_GNK | AB54: =IF(L54="DELDTE","","○") -> ○ | AE54: =IF(AB54="○",IF(AH54="timestamp","now()",IF(LEFT(AH54,9)="character","' '","0")),"") -> 0 | AH54: =VLOOKUP(D54,カラムID辞書!C:H,3,FALSE) -> numeric | AM54: =VLOOKUP(D54,カラムID辞書!C:H,4,FALSE) -> 13 | AO54: =VLOOKUP(D54,カラムID辞書!C:H,6,FALSE) -> 13 | BR54: （未設定：ZERO）
B55: =IF($D55="","",MAX(OFFSET($B$8,0,0,ROW()-ROW($B$8),2))+1) -> 48 | D55: 返品高原価 | L55: =VLOOKUP(D55,カラムID辞書!$C$4:$D$1266,2,FALSE) -> HENPND_GNK | AB55: =IF(L55="DELDTE","","○") -> ○ | AE55: =IF(AB55="○",IF(AH55="timestamp","now()",IF(LEFT(AH55,9)="character","' '","0")),"") -> 0 | AH55: =VLOOKUP(D55,カラムID辞書!C:H,3,FALSE) -> numeric | AM55: =VLOOKUP(D55,カラムID辞書!C:H,4,FALSE) -> 13 | AO55: =VLOOKUP(D55,カラムID辞書!C:H,6,FALSE) -> 13 | AQ55: 返品伝票の原価集計値
B56: =IF($D56="","",MAX(OFFSET($B$8,0,0,ROW()-ROW($B$8),2))+1) -> 49 | D56: 返品高売価 | L56: =VLOOKUP(D56,カラムID辞書!$C$4:$D$1266,2,FALSE) -> HENPND_BIK | AB56: =IF(L56="DELDTE","","○") -> ○ | AE56: =IF(AB56="○",IF(AH56="timestamp","now()",IF(LEFT(AH56,9)="character","' '","0")),"") -> 0 | AH56: =VLOOKUP(D56,カラムID辞書!C:H,3,FALSE) -> numeric | AM56: =VLOOKUP(D56,カラムID辞書!C:H,4,FALSE) -> 13 | AO56: =VLOOKUP(D56,カラムID辞書!C:H,6,FALSE) -> 13 | AQ56: 返品伝票の売価集計値
B57: =IF($D57="","",MAX(OFFSET($B$8,0,0,ROW()-ROW($B$8),2))+1) -> 50 | D57: 返品高数量 | L57: =VLOOKUP(D57,カラムID辞書!$C$4:$D$1266,2,FALSE) -> HENPND_SU | AB57: =IF(L57="DELDTE","","○") -> ○ | AE57: =IF(AB57="○",IF(AH57="timestamp","now()",IF(LEFT(AH57,9)="character","' '","0")),"") -> 0 | AH57: =VLOOKUP(D57,カラムID辞書!C:H,3,FALSE) -> numeric | AM57: =VLOOKUP(D57,カラムID辞書!C:H,4,FALSE) -> 10 | AO57: =VLOOKUP(D57,カラムID辞書!C:H,6,FALSE) -> 10 | AQ57: 返品伝票の数量集計値
B58: =IF($D58="","",MAX(OFFSET($B$8,0,0,ROW()-ROW($B$8),2))+1) -> 51 | D58: 付帯返品高原価 | L58: =VLOOKUP(D58,カラムID辞書!$C$4:$D$1266,2,FALSE) -> FUTAIHENPND_GNK | AB58: =IF(L58="DELDTE","","○") -> ○ | AE58: =IF(AB58="○",IF(AH58="timestamp","now()",IF(LEFT(AH58,9)="character","' '","0")),"") -> 0 | AH58: =VLOOKUP(D58,カラムID辞書!C:H,3,FALSE) -> numeric | AM58: =VLOOKUP(D58,カラムID辞書!C:H,4,FALSE) -> 13 | AO58: =VLOOKUP(D58,カラムID辞書!C:H,6,FALSE) -> 13 | BR58: （未設定：ZERO）
B59: =IF($D59="","",MAX(OFFSET($B$8,0,0,ROW()-ROW($B$8),2))+1) -> 52 | D59: 価格訂正仕入高原価 | L59: =VLOOKUP(D59,カラムID辞書!$C$4:$D$1266,2,FALSE) -> TEISEISHIIRED_GNK | AB59: =IF(L59="DELDTE","","○") -> ○ | AE59: =IF(AB59="○",IF(AH59="timestamp","now()",IF(LEFT(AH59,9)="character","' '","0")),"") -> 0 | AH59: =VLOOKUP(D59,カラムID辞書!C:H,3,FALSE) -> numeric | AM59: =VLOOKUP(D59,カラムID辞書!C:H,4,FALSE) -> 13 | AO59: =VLOOKUP(D59,カラムID辞書!C:H,6,FALSE) -> 13 | AQ59: 価格変更による再仕入伝票の原価集計値
B60: =IF($D60="","",MAX(OFFSET($B$8,0,0,ROW()-ROW($B$8),2))+1) -> 53 | D60: 価格訂正仕入高売価 | L60: =VLOOKUP(D60,カラムID辞書!$C$4:$D$1266,2,FALSE) -> TEISEISHIIRED_BIK | AB60: =IF(L60="DELDTE","","○") -> ○ | AE60: =IF(AB60="○",IF(AH60="timestamp","now()",IF(LEFT(AH60,9)="character","' '","0")),"") -> 0 | AH60: =VLOOKUP(D60,カラムID辞書!C:H,3,FALSE) -> numeric | AM60: =VLOOKUP(D60,カラムID辞書!C:H,4,FALSE) -> 13 | AO60: =VLOOKUP(D60,カラムID辞書!C:H,6,FALSE) -> 13 | AQ60: 価格変更による再仕入伝票の売価集計値
B61: =IF($D61="","",MAX(OFFSET($B$8,0,0,ROW()-ROW($B$8),2))+1) -> 54 | D61: 価格訂正仕入高数量 | L61: =VLOOKUP(D61,カラムID辞書!$C$4:$D$1266,2,FALSE) -> TEISEISHIIRED_SU | AB61: =IF(L61="DELDTE","","○") -> ○ | AE61: =IF(AB61="○",IF(AH61="timestamp","now()",IF(LEFT(AH61,9)="character","' '","0")),"") -> 0 | AH61: =VLOOKUP(D61,カラムID辞書!C:H,3,FALSE) -> numeric | AM61: =VLOOKUP(D61,カラムID辞書!C:H,4,FALSE) -> 10 | AO61: =VLOOKUP(D61,カラムID辞書!C:H,6,FALSE) -> 10 | AQ61: 価格変更による再仕入伝票の数量集計値
B62: =IF($D62="","",MAX(OFFSET($B$8,0,0,ROW()-ROW($B$8),2))+1) -> 55 | D62: 価格訂正返品高原価 | L62: =VLOOKUP(D62,カラムID辞書!$C$4:$D$1266,2,FALSE) -> TEISEIHENPIND_GNK | AB62: =IF(L62="DELDTE","","○") -> ○ | AE62: =IF(AB62="○",IF(AH62="timestamp","now()",IF(LEFT(AH62,9)="character","' '","0")),"") -> 0 | AH62: =VLOOKUP(D62,カラムID辞書!C:H,3,FALSE) -> numeric | AM62: =VLOOKUP(D62,カラムID辞書!C:H,4,FALSE) -> 13 | AO62: =VLOOKUP(D62,カラムID辞書!C:H,6,FALSE) -> 13 | AQ62: 価格変更による返品伝票の原価集計値
B63: =IF($D63="","",MAX(OFFSET($B$8,0,0,ROW()-ROW($B$8),2))+1) -> 56 | D63: 価格訂正返品高売価 | L63: =VLOOKUP(D63,カラムID辞書!$C$4:$D$1266,2,FALSE) -> TEISEIHENPIND_BIK | AB63: =IF(L63="DELDTE","","○") -> ○ | AE63: =IF(AB63="○",IF(AH63="timestamp","now()",IF(LEFT(AH63,9)="character","' '","0")),"") -> 0 | AH63: =VLOOKUP(D63,カラムID辞書!C:H,3,FALSE) -> numeric | AM63: =VLOOKUP(D63,カラムID辞書!C:H,4,FALSE) -> 13 | AO63: =VLOOKUP(D63,カラムID辞書!C:H,6,FALSE) -> 13 | AQ63: 価格変更による返品伝票の売価集計値
B64: =IF($D64="","",MAX(OFFSET($B$8,0,0,ROW()-ROW($B$8),2))+1) -> 57 | D64: 価格訂正返品高数量 | L64: =VLOOKUP(D64,カラムID辞書!$C$4:$D$1266,2,FALSE) -> TEISEIHENPIND_SU | AB64: =IF(L64="DELDTE","","○") -> ○ | AE64: =IF(AB64="○",IF(AH64="timestamp","now()",IF(LEFT(AH64,9)="character","' '","0")),"") -> 0 | AH64: =VLOOKUP(D64,カラムID辞書!C:H,3,FALSE) -> numeric | AM64: =VLOOKUP(D64,カラムID辞書!C:H,4,FALSE) -> 10 | AO64: =VLOOKUP(D64,カラムID辞書!C:H,6,FALSE) -> 10 | AQ64: 価格変更による返品伝票の数量集計値
B65: =IF($D65="","",MAX(OFFSET($B$8,0,0,ROW()-ROW($B$8),2))+1) -> 58 | D65: 自社値上高売価 | L65: =VLOOKUP(D65,カラムID辞書!$C$4:$D$1266,2,FALSE) -> JISHANEAGED_BIK | AB65: =IF(L65="DELDTE","","○") -> ○ | AE65: =IF(AB65="○",IF(AH65="timestamp","now()",IF(LEFT(AH65,9)="character","' '","0")),"") -> 0 | AH65: =VLOOKUP(D65,カラムID辞書!C:H,3,FALSE) -> numeric | AM65: =VLOOKUP(D65,カラムID辞書!C:H,4,FALSE) -> 13 | AO65: =VLOOKUP(D65,カラムID辞書!C:H,6,FALSE) -> 13 | AQ65: 値上伝票の売価集計値
B66: =IF($D66="","",MAX(OFFSET($B$8,0,0,ROW()-ROW($B$8),2))+1) -> 59 | D66: 自社値下高売価 | L66: =VLOOKUP(D66,カラムID辞書!$C$4:$D$1266,2,FALSE) -> JISHANESAGED_BIK | AB66: =IF(L66="DELDTE","","○") -> ○ | AE66: =IF(AB66="○",IF(AH66="timestamp","now()",IF(LEFT(AH66,9)="character","' '","0")),"") -> 0 | AH66: =VLOOKUP(D66,カラムID辞書!C:H,3,FALSE) -> numeric | AM66: =VLOOKUP(D66,カラムID辞書!C:H,4,FALSE) -> 13 | AO66: =VLOOKUP(D66,カラムID辞書!C:H,6,FALSE) -> 13 | AQ66: 値下伝票の売価集計値
B67: =IF($D67="","",MAX(OFFSET($B$8,0,0,ROW()-ROW($B$8),2))+1) -> 60 | D67: 値上高原価１ | L67: =VLOOKUP(D67,カラムID辞書!$C$4:$D$1266,2,FALSE) -> NEAGED1_GNK | AB67: =IF(L67="DELDTE","","○") -> ○ | AE67: =IF(AB67="○",IF(AH67="timestamp","now()",IF(LEFT(AH67,9)="character","' '","0")),"") -> 0 | AH67: =VLOOKUP(D67,カラムID辞書!C:H,3,FALSE) -> numeric | AM67: =VLOOKUP(D67,カラムID辞書!C:H,4,FALSE) -> 13 | AO67: =VLOOKUP(D67,カラムID辞書!C:H,6,FALSE) -> 13 | BR67: （未設定：ZERO）
B68: =IF($D68="","",MAX(OFFSET($B$8,0,0,ROW()-ROW($B$8),2))+1) -> 61 | D68: 値上高売価１ | L68: =VLOOKUP(D68,カラムID辞書!$C$4:$D$1266,2,FALSE) -> NEAGED1_BIK | AB68: =IF(L68="DELDTE","","○") -> ○ | AE68: =IF(AB68="○",IF(AH68="timestamp","now()",IF(LEFT(AH68,9)="character","' '","0")),"") -> 0 | AH68: =VLOOKUP(D68,カラムID辞書!C:H,3,FALSE) -> numeric | AM68: =VLOOKUP(D68,カラムID辞書!C:H,4,FALSE) -> 13 | AO68: =VLOOKUP(D68,カラムID辞書!C:H,6,FALSE) -> 13 | BR68: （未設定：ZERO）
B69: =IF($D69="","",MAX(OFFSET($B$8,0,0,ROW()-ROW($B$8),2))+1) -> 62 | D69: 値下高原価１ | L69: =VLOOKUP(D69,カラムID辞書!$C$4:$D$1266,2,FALSE) -> NESAGED1_GNK | AB69: =IF(L69="DELDTE","","○") -> ○ | AE69: =IF(AB69="○",IF(AH69="timestamp","now()",IF(LEFT(AH69,9)="character","' '","0")),"") -> 0 | AH69: =VLOOKUP(D69,カラムID辞書!C:H,3,FALSE) -> numeric | AM69: =VLOOKUP(D69,カラムID辞書!C:H,4,FALSE) -> 13 | AO69: =VLOOKUP(D69,カラムID辞書!C:H,6,FALSE) -> 13 | AQ69: 破損伝票の数量集計値
B70: =IF($D70="","",MAX(OFFSET($B$8,0,0,ROW()-ROW($B$8),2))+1) -> 63 | D70: 値下高売価１ | L70: =VLOOKUP(D70,カラムID辞書!$C$4:$D$1266,2,FALSE) -> NESAGED1_BIK | AB70: =IF(L70="DELDTE","","○") -> ○ | AE70: =IF(AB70="○",IF(AH70="timestamp","now()",IF(LEFT(AH70,9)="character","' '","0")),"") -> 0 | AH70: =VLOOKUP(D70,カラムID辞書!C:H,3,FALSE) -> numeric | AM70: =VLOOKUP(D70,カラムID辞書!C:H,4,FALSE) -> 13 | AO70: =VLOOKUP(D70,カラムID辞書!C:H,6,FALSE) -> 13 | AQ70: 破損伝票の売価集計値
B71: =IF($D71="","",MAX(OFFSET($B$8,0,0,ROW()-ROW($B$8),2))+1) -> 64 | D71: 値上高原価２ | L71: =VLOOKUP(D71,カラムID辞書!$C$4:$D$1266,2,FALSE) -> NEAGED2_GNK | AB71: =IF(L71="DELDTE","","○") -> ○ | AE71: =IF(AB71="○",IF(AH71="timestamp","now()",IF(LEFT(AH71,9)="character","' '","0")),"") -> 0 | AH71: =VLOOKUP(D71,カラムID辞書!C:H,3,FALSE) -> numeric | AM71: =VLOOKUP(D71,カラムID辞書!C:H,4,FALSE) -> 13 | AO71: =VLOOKUP(D71,カラムID辞書!C:H,6,FALSE) -> 13 | BR71: （未設定：ZERO）
B72: =IF($D72="","",MAX(OFFSET($B$8,0,0,ROW()-ROW($B$8),2))+1) -> 65 | D72: 値上高売価２ | L72: =VLOOKUP(D72,カラムID辞書!$C$4:$D$1266,2,FALSE) -> NEAGED2_BIK | AB72: =IF(L72="DELDTE","","○") -> ○ | AE72: =IF(AB72="○",IF(AH72="timestamp","now()",IF(LEFT(AH72,9)="character","' '","0")),"") -> 0 | AH72: =VLOOKUP(D72,カラムID辞書!C:H,3,FALSE) -> numeric | AM72: =VLOOKUP(D72,カラムID辞書!C:H,4,FALSE) -> 13 | AO72: =VLOOKUP(D72,カラムID辞書!C:H,6,FALSE) -> 13 | BR72: （未設定：ZERO）
B73: =IF($D73="","",MAX(OFFSET($B$8,0,0,ROW()-ROW($B$8),2))+1) -> 66 | D73: 値下高原価２ | L73: =VLOOKUP(D73,カラムID辞書!$C$4:$D$1266,2,FALSE) -> NESAGED2_GNK | AB73: =IF(L73="DELDTE","","○") -> ○ | AE73: =IF(AB73="○",IF(AH73="timestamp","now()",IF(LEFT(AH73,9)="character","' '","0")),"") -> 0 | AH73: =VLOOKUP(D73,カラムID辞書!C:H,3,FALSE) -> numeric | AM73: =VLOOKUP(D73,カラムID辞書!C:H,4,FALSE) -> 13 | AO73: =VLOOKUP(D73,カラムID辞書!C:H,6,FALSE) -> 13 | BR73: （未設定：ZERO）
B74: =IF($D74="","",MAX(OFFSET($B$8,0,0,ROW()-ROW($B$8),2))+1) -> 67 | D74: 値下高売価２ | L74: =VLOOKUP(D74,カラムID辞書!$C$4:$D$1266,2,FALSE) -> NESAGED2_BIK | AB74: =IF(L74="DELDTE","","○") -> ○ | AE74: =IF(AB74="○",IF(AH74="timestamp","now()",IF(LEFT(AH74,9)="character","' '","0")),"") -> 0 | AH74: =VLOOKUP(D74,カラムID辞書!C:H,3,FALSE) -> numeric | AM74: =VLOOKUP(D74,カラムID辞書!C:H,4,FALSE) -> 13 | AO74: =VLOOKUP(D74,カラムID辞書!C:H,6,FALSE) -> 13 | BR74: （未設定：ZERO）
B75: =IF($D75="","",MAX(OFFSET($B$8,0,0,ROW()-ROW($B$8),2))+1) -> 68 | D75: 店間振替高原価（払出） | L75: =VLOOKUP(D75,カラムID辞書!$C$4:$D$1266,2,FALSE) -> TNKANFURI_O_GNK | AB75: =IF(L75="DELDTE","","○") -> ○ | AE75: =IF(AB75="○",IF(AH75="timestamp","now()",IF(LEFT(AH75,9)="character","' '","0")),"") -> 0 | AH75: =VLOOKUP(D75,カラムID辞書!C:H,3,FALSE) -> numeric | AM75: =VLOOKUP(D75,カラムID辞書!C:H,4,FALSE) -> 13 | AO75: =VLOOKUP(D75,カラムID辞書!C:H,6,FALSE) -> 13 | AQ75: 店間振替伝票（払出）の原価集計値
B76: =IF($D76="","",MAX(OFFSET($B$8,0,0,ROW()-ROW($B$8),2))+1) -> 69 | D76: 店間振替高売価（払出） | L76: =VLOOKUP(D76,カラムID辞書!$C$4:$D$1266,2,FALSE) -> TNKANFURI_O_BIK | AB76: =IF(L76="DELDTE","","○") -> ○ | AE76: =IF(AB76="○",IF(AH76="timestamp","now()",IF(LEFT(AH76,9)="character","' '","0")),"") -> 0 | AH76: =VLOOKUP(D76,カラムID辞書!C:H,3,FALSE) -> numeric | AM76: =VLOOKUP(D76,カラムID辞書!C:H,4,FALSE) -> 13 | AO76: =VLOOKUP(D76,カラムID辞書!C:H,6,FALSE) -> 13 | AQ76: 店間振替伝票（払出）の売価集計値
B77: =IF($D77="","",MAX(OFFSET($B$8,0,0,ROW()-ROW($B$8),2))+1) -> 70 | D77: 店間振替高数量（払出） | L77: =VLOOKUP(D77,カラムID辞書!$C$4:$D$1266,2,FALSE) -> TNKANFURI_O_SU | AB77: =IF(L77="DELDTE","","○") -> ○ | AE77: =IF(AB77="○",IF(AH77="timestamp","now()",IF(LEFT(AH77,9)="character","' '","0")),"") -> 0 | AH77: =VLOOKUP(D77,カラムID辞書!C:H,3,FALSE) -> numeric | AM77: =VLOOKUP(D77,カラムID辞書!C:H,4,FALSE) -> 10 | AO77: =VLOOKUP(D77,カラムID辞書!C:H,6,FALSE) -> 10 | AQ77: 店間振替伝票（払出）の数量集計値
B78: =IF($D78="","",MAX(OFFSET($B$8,0,0,ROW()-ROW($B$8),2))+1) -> 71 | D78: 店間振替高原価（受入） | L78: =VLOOKUP(D78,カラムID辞書!$C$4:$D$1266,2,FALSE) -> TNKANFURI_I_GNK | AB78: =IF(L78="DELDTE","","○") -> ○ | AE78: =IF(AB78="○",IF(AH78="timestamp","now()",IF(LEFT(AH78,9)="character","' '","0")),"") -> 0 | AH78: =VLOOKUP(D78,カラムID辞書!C:H,3,FALSE) -> numeric | AM78: =VLOOKUP(D78,カラムID辞書!C:H,4,FALSE) -> 13 | AO78: =VLOOKUP(D78,カラムID辞書!C:H,6,FALSE) -> 13 | AQ78: 店間振替伝票（受入）の原価集計値
B79: =IF($D79="","",MAX(OFFSET($B$8,0,0,ROW()-ROW($B$8),2))+1) -> 72 | D79: 店間振替高売価（受入） | L79: =VLOOKUP(D79,カラムID辞書!$C$4:$D$1266,2,FALSE) -> TNKANFURI_I_BIK | AB79: =IF(L79="DELDTE","","○") -> ○ | AE79: =IF(AB79="○",IF(AH79="timestamp","now()",IF(LEFT(AH79,9)="character","' '","0")),"") -> 0 | AH79: =VLOOKUP(D79,カラムID辞書!C:H,3,FALSE) -> numeric | AM79: =VLOOKUP(D79,カラムID辞書!C:H,4,FALSE) -> 13 | AO79: =VLOOKUP(D79,カラムID辞書!C:H,6,FALSE) -> 13 | AQ79: 店間振替伝票（受入）の売価集計値
B80: =IF($D80="","",MAX(OFFSET($B$8,0,0,ROW()-ROW($B$8),2))+1) -> 73 | D80: 店間振替高数量（受入） | L80: =VLOOKUP(D80,カラムID辞書!$C$4:$D$1266,2,FALSE) -> TNKANFURI_I_SU | AB80: =IF(L80="DELDTE","","○") -> ○ | AE80: =IF(AB80="○",IF(AH80="timestamp","now()",IF(LEFT(AH80,9)="character","' '","0")),"") -> 0 | AH80: =VLOOKUP(D80,カラムID辞書!C:H,3,FALSE) -> numeric | AM80: =VLOOKUP(D80,カラムID辞書!C:H,4,FALSE) -> 10 | AO80: =VLOOKUP(D80,カラムID辞書!C:H,6,FALSE) -> 10 | AQ80: 店間振替伝票（受入）の数量集計値
B81: =IF($D81="","",MAX(OFFSET($B$8,0,0,ROW()-ROW($B$8),2))+1) -> 74 | D81: 店内振替高原価（払出） | L81: =VLOOKUP(D81,カラムID辞書!$C$4:$D$1266,2,FALSE) -> TNNAIFURI_O_GNK | AB81: =IF(L81="DELDTE","","○") -> ○ | AE81: =IF(AB81="○",IF(AH81="timestamp","now()",IF(LEFT(AH81,9)="character","' '","0")),"") -> 0 | AH81: =VLOOKUP(D81,カラムID辞書!C:H,3,FALSE) -> numeric | AM81: =VLOOKUP(D81,カラムID辞書!C:H,4,FALSE) -> 13 | AO81: =VLOOKUP(D81,カラムID辞書!C:H,6,FALSE) -> 13 | AQ81: 品番振替伝票（払出）の原価集計値
B82: =IF($D82="","",MAX(OFFSET($B$8,0,0,ROW()-ROW($B$8),2))+1) -> 75 | D82: 店内振替高売価（払出） | L82: =VLOOKUP(D82,カラムID辞書!$C$4:$D$1266,2,FALSE) -> TNNAIFURI_O_BIK | AB82: =IF(L82="DELDTE","","○") -> ○ | AE82: =IF(AB82="○",IF(AH82="timestamp","now()",IF(LEFT(AH82,9)="character","' '","0")),"") -> 0 | AH82: =VLOOKUP(D82,カラムID辞書!C:H,3,FALSE) -> numeric | AM82: =VLOOKUP(D82,カラムID辞書!C:H,4,FALSE) -> 13 | AO82: =VLOOKUP(D82,カラムID辞書!C:H,6,FALSE) -> 13 | AQ82: 品番振替伝票（払出）の売価集計値
B83: =IF($D83="","",MAX(OFFSET($B$8,0,0,ROW()-ROW($B$8),2))+1) -> 76 | D83: 店内振替高数量（払出） | L83: =VLOOKUP(D83,カラムID辞書!$C$4:$D$1266,2,FALSE) -> TNNAIFURI_O_SU | AB83: =IF(L83="DELDTE","","○") -> ○ | AE83: =IF(AB83="○",IF(AH83="timestamp","now()",IF(LEFT(AH83,9)="character","' '","0")),"") -> 0 | AH83: =VLOOKUP(D83,カラムID辞書!C:H,3,FALSE) -> numeric | AM83: =VLOOKUP(D83,カラムID辞書!C:H,4,FALSE) -> 10 | AO83: =VLOOKUP(D83,カラムID辞書!C:H,6,FALSE) -> 10 | AQ83: 品番振替伝票（払出）の数量集計値
B84: =IF($D84="","",MAX(OFFSET($B$8,0,0,ROW()-ROW($B$8),2))+1) -> 77 | D84: 店内振替高原価（受入） | L84: =VLOOKUP(D84,カラムID辞書!$C$4:$D$1266,2,FALSE) -> TNNAIFURI_I_GNK | AB84: =IF(L84="DELDTE","","○") -> ○ | AE84: =IF(AB84="○",IF(AH84="timestamp","now()",IF(LEFT(AH84,9)="character","' '","0")),"") -> 0 | AH84: =VLOOKUP(D84,カラムID辞書!C:H,3,FALSE) -> numeric | AM84: =VLOOKUP(D84,カラムID辞書!C:H,4,FALSE) -> 13 | AO84: =VLOOKUP(D84,カラムID辞書!C:H,6,FALSE) -> 13 | AQ84: 品番振替伝票（受入）の原価集計値
B85: =IF($D85="","",MAX(OFFSET($B$8,0,0,ROW()-ROW($B$8),2))+1) -> 78 | D85: 店内振替高売価（受入） | L85: =VLOOKUP(D85,カラムID辞書!$C$4:$D$1266,2,FALSE) -> TNNAIFURI_I_BIK | AB85: =IF(L85="DELDTE","","○") -> ○ | AE85: =IF(AB85="○",IF(AH85="timestamp","now()",IF(LEFT(AH85,9)="character","' '","0")),"") -> 0 | AH85: =VLOOKUP(D85,カラムID辞書!C:H,3,FALSE) -> numeric | AM85: =VLOOKUP(D85,カラムID辞書!C:H,4,FALSE) -> 13 | AO85: =VLOOKUP(D85,カラムID辞書!C:H,6,FALSE) -> 13 | AQ85: 品番振替伝票（受入）の売価集計値
B86: =IF($D86="","",MAX(OFFSET($B$8,0,0,ROW()-ROW($B$8),2))+1) -> 79 | D86: 店内振替高数量（受入） | L86: =VLOOKUP(D86,カラムID辞書!$C$4:$D$1266,2,FALSE) -> TNNAIFURI_I_SU | AB86: =IF(L86="DELDTE","","○") -> ○ | AE86: =IF(AB86="○",IF(AH86="timestamp","now()",IF(LEFT(AH86,9)="character","' '","0")),"") -> 0 | AH86: =VLOOKUP(D86,カラムID辞書!C:H,3,FALSE) -> numeric | AM86: =VLOOKUP(D86,カラムID辞書!C:H,4,FALSE) -> 10 | AO86: =VLOOKUP(D86,カラムID辞書!C:H,6,FALSE) -> 10 | AQ86: 品番振替伝票（受入）の数量集計値
B87: =IF($D87="","",MAX(OFFSET($B$8,0,0,ROW()-ROW($B$8),2))+1) -> 80 | D87: 商品振替高原価（払出） | L87: =VLOOKUP(D87,カラムID辞書!$C$4:$D$1266,2,FALSE) -> SHOHNFURI_O_GNK | AB87: =IF(L87="DELDTE","","○") -> ○ | AE87: =IF(AB87="○",IF(AH87="timestamp","now()",IF(LEFT(AH87,9)="character","' '","0")),"") -> 0 | AH87: =VLOOKUP(D87,カラムID辞書!C:H,3,FALSE) -> numeric | AM87: =VLOOKUP(D87,カラムID辞書!C:H,4,FALSE) -> 13 | AO87: =VLOOKUP(D87,カラムID辞書!C:H,6,FALSE) -> 13 | BR87: （未設定：ZERO）
B88: =IF($D88="","",MAX(OFFSET($B$8,0,0,ROW()-ROW($B$8),2))+1) -> 81 | D88: 商品振替高売価（払出） | L88: =VLOOKUP(D88,カラムID辞書!$C$4:$D$1266,2,FALSE) -> SHOHNFURI_O_BIK | AB88: =IF(L88="DELDTE","","○") -> ○ | AE88: =IF(AB88="○",IF(AH88="timestamp","now()",IF(LEFT(AH88,9)="character","' '","0")),"") -> 0 | AH88: =VLOOKUP(D88,カラムID辞書!C:H,3,FALSE) -> numeric | AM88: =VLOOKUP(D88,カラムID辞書!C:H,4,FALSE) -> 13 | AO88: =VLOOKUP(D88,カラムID辞書!C:H,6,FALSE) -> 13 | BR88: （未設定：ZERO）
B89: =IF($D89="","",MAX(OFFSET($B$8,0,0,ROW()-ROW($B$8),2))+1) -> 82 | D89: 商品振替高数量（払出） | L89: =VLOOKUP(D89,カラムID辞書!$C$4:$D$1266,2,FALSE) -> SHOHNFURI_O_SU | AB89: =IF(L89="DELDTE","","○") -> ○ | AE89: =IF(AB89="○",IF(AH89="timestamp","now()",IF(LEFT(AH89,9)="character","' '","0")),"") -> 0 | AH89: =VLOOKUP(D89,カラムID辞書!C:H,3,FALSE) -> numeric | AM89: =VLOOKUP(D89,カラムID辞書!C:H,4,FALSE) -> 10 | AO89: =VLOOKUP(D89,カラムID辞書!C:H,6,FALSE) -> 10 | BR89: （未設定：ZERO）
B90: =IF($D90="","",MAX(OFFSET($B$8,0,0,ROW()-ROW($B$8),2))+1) -> 83 | D90: 商品振替高原価（受入） | L90: =VLOOKUP(D90,カラムID辞書!$C$4:$D$1266,2,FALSE) -> SHOHNFURI_I_GNK | AB90: =IF(L90="DELDTE","","○") -> ○ | AE90: =IF(AB90="○",IF(AH90="timestamp","now()",IF(LEFT(AH90,9)="character","' '","0")),"") -> 0 | AH90: =VLOOKUP(D90,カラムID辞書!C:H,3,FALSE) -> numeric | AM90: =VLOOKUP(D90,カラムID辞書!C:H,4,FALSE) -> 13 | AO90: =VLOOKUP(D90,カラムID辞書!C:H,6,FALSE) -> 13 | BR90: （未設定：ZERO）
B91: =IF($D91="","",MAX(OFFSET($B$8,0,0,ROW()-ROW($B$8),2))+1) -> 84 | D91: 商品振替高売価（受入） | L91: =VLOOKUP(D91,カラムID辞書!$C$4:$D$1266,2,FALSE) -> SHOHNFURI_I_BIK | AB91: =IF(L91="DELDTE","","○") -> ○ | AE91: =IF(AB91="○",IF(AH91="timestamp","now()",IF(LEFT(AH91,9)="character","' '","0")),"") -> 0 | AH91: =VLOOKUP(D91,カラムID辞書!C:H,3,FALSE) -> numeric | AM91: =VLOOKUP(D91,カラムID辞書!C:H,4,FALSE) -> 13 | AO91: =VLOOKUP(D91,カラムID辞書!C:H,6,FALSE) -> 13 | BR91: （未設定：ZERO）
B92: =IF($D92="","",MAX(OFFSET($B$8,0,0,ROW()-ROW($B$8),2))+1) -> 85 | D92: 商品振替高数量（受入） | L92: =VLOOKUP(D92,カラムID辞書!$C$4:$D$1266,2,FALSE) -> SHOHNFURI_I_SU | AB92: =IF(L92="DELDTE","","○") -> ○ | AE92: =IF(AB92="○",IF(AH92="timestamp","now()",IF(LEFT(AH92,9)="character","' '","0")),"") -> 0 | AH92: =VLOOKUP(D92,カラムID辞書!C:H,3,FALSE) -> numeric | AM92: =VLOOKUP(D92,カラムID辞書!C:H,4,FALSE) -> 10 | AO92: =VLOOKUP(D92,カラムID辞書!C:H,6,FALSE) -> 10 | BR92: （未設定：ZERO）
B93: =IF($D93="","",MAX(OFFSET($B$8,0,0,ROW()-ROW($B$8),2))+1) -> 86 | D93: リベート | L93: =VLOOKUP(D93,カラムID辞書!$C$4:$D$1266,2,FALSE) -> REBATE | AB93: =IF(L93="DELDTE","","○") -> ○ | AE93: =IF(AB93="○",IF(AH93="timestamp","now()",IF(LEFT(AH93,9)="character","' '","0")),"") -> 0 | AH93: =VLOOKUP(D93,カラムID辞書!C:H,3,FALSE) -> numeric | AM93: =VLOOKUP(D93,カラムID辞書!C:H,4,FALSE) -> 13 | AO93: =VLOOKUP(D93,カラムID辞書!C:H,6,FALSE) -> 13 | BR93: （未設定：ZERO）
B94: =IF($D94="","",MAX(OFFSET($B$8,0,0,ROW()-ROW($B$8),2))+1) -> 87 | D94: リベート返金 | L94: =VLOOKUP(D94,カラムID辞書!$C$4:$D$1266,2,FALSE) -> REBATE_HENKIN | AB94: =IF(L94="DELDTE","","○") -> ○ | AE94: =IF(AB94="○",IF(AH94="timestamp","now()",IF(LEFT(AH94,9)="character","' '","0")),"") -> 0 | AH94: =VLOOKUP(D94,カラムID辞書!C:H,3,FALSE) -> numeric | AM94: =VLOOKUP(D94,カラムID辞書!C:H,4,FALSE) -> 13 | AO94: =VLOOKUP(D94,カラムID辞書!C:H,6,FALSE) -> 13 | BR94: （未設定：ZERO）
B95: =IF($D95="","",MAX(OFFSET($B$8,0,0,ROW()-ROW($B$8),2))+1) -> 88 | D95: 予備原価１ | L95: =VLOOKUP(D95,カラムID辞書!$C$4:$D$1266,2,FALSE) -> RSV_GNK1 | AB95: =IF(L95="DELDTE","","○") -> ○ | AE95: =IF(AB95="○",IF(AH95="timestamp","now()",IF(LEFT(AH95,9)="character","' '","0")),"") -> 0 | AH95: =VLOOKUP(D95,カラムID辞書!C:H,3,FALSE) -> numeric | AM95: =VLOOKUP(D95,カラムID辞書!C:H,4,FALSE) -> 13 | AO95: =VLOOKUP(D95,カラムID辞書!C:H,6,FALSE) -> 13 | BR95: （未設定：ZERO）
B96: =IF($D96="","",MAX(OFFSET($B$8,0,0,ROW()-ROW($B$8),2))+1) -> 89 | D96: 予備売価１ | L96: =VLOOKUP(D96,カラムID辞書!$C$4:$D$1266,2,FALSE) -> RSV_BIK1 | AB96: =IF(L96="DELDTE","","○") -> ○ | AE96: =IF(AB96="○",IF(AH96="timestamp","now()",IF(LEFT(AH96,9)="character","' '","0")),"") -> 0 | AH96: =VLOOKUP(D96,カラムID辞書!C:H,3,FALSE) -> numeric | AM96: =VLOOKUP(D96,カラムID辞書!C:H,4,FALSE) -> 13 | AO96: =VLOOKUP(D96,カラムID辞書!C:H,6,FALSE) -> 13 | BR96: （未設定：ZERO）
B97: =IF($D97="","",MAX(OFFSET($B$8,0,0,ROW()-ROW($B$8),2))+1) -> 90 | D97: 予備数量１ | L97: =VLOOKUP(D97,カラムID辞書!$C$4:$D$1266,2,FALSE) -> RSV_SU1 | AB97: =IF(L97="DELDTE","","○") -> ○ | AE97: =IF(AB97="○",IF(AH97="timestamp","now()",IF(LEFT(AH97,9)="character","' '","0")),"") -> 0 | AH97: =VLOOKUP(D97,カラムID辞書!C:H,3,FALSE) -> numeric | AM97: =VLOOKUP(D97,カラムID辞書!C:H,4,FALSE) -> 10 | AO97: =VLOOKUP(D97,カラムID辞書!C:H,6,FALSE) -> 10 | BR97: （未設定：ZERO）
B98: =IF($D98="","",MAX(OFFSET($B$8,0,0,ROW()-ROW($B$8),2))+1) -> 91 | D98: 予備原価２ | L98: =VLOOKUP(D98,カラムID辞書!$C$4:$D$1266,2,FALSE) -> RSV_GNK2 | AB98: =IF(L98="DELDTE","","○") -> ○ | AE98: =IF(AB98="○",IF(AH98="timestamp","now()",IF(LEFT(AH98,9)="character","' '","0")),"") -> 0 | AH98: =VLOOKUP(D98,カラムID辞書!C:H,3,FALSE) -> numeric | AM98: =VLOOKUP(D98,カラムID辞書!C:H,4,FALSE) -> 13 | AO98: =VLOOKUP(D98,カラムID辞書!C:H,6,FALSE) -> 13 | BR98: （未設定：ZERO）
... B124: =IF($D124="","",MAX(OFFSET($B$8,0,0,ROW()-ROW($B$8),2))+1) -> 117 | D124: 予備数量１０ | L124: =VLOOKUP(D124,カラムID辞書!$C$4:$D$1266,2,FALSE) -> RSV_SU10 | AB124: =IF(L124="DELDTE","","○") -> ○ | AE124: =IF(AB124="○",IF(AH124="timestamp","now()",IF(LEFT(AH124,9)="character","' '","0")),"") -> 0 | AH124: =VLOOKUP(D124,カラムID辞書!C:H,3,FALSE) -> numeric | AM124: =VLOOKUP(D124,カラムID辞書!C:H,4,FALSE) -> 10 | AO124: =VLOOKUP(D124,カラムID辞書!C:H,6,FALSE) -> 10 | BR124: （未設定：ZERO）
B125: =IF($D125="","",MAX(OFFSET($B$8,0,0,ROW()-ROW($B$8),2))+1) -> 118 | D125: 前日末在高原価 | L125: =VLOOKUP(D125,カラムID辞書!$C$4:$D$1266,2,FALSE) -> ZENJTZAID_GNK | AB125: =IF(L125="DELDTE","","○") -> ○ | AE125: =IF(AB125="○",IF(AH125="timestamp","now()",IF(LEFT(AH125,9)="character","' '","0")),"") -> 0 | AH125: =VLOOKUP(D125,カラムID辞書!C:H,3,FALSE) -> numeric | AM125: =VLOOKUP(D125,カラムID辞書!C:H,4,FALSE) -> 13 | AO125: =VLOOKUP(D125,カラムID辞書!C:H,6,FALSE) -> 13 | AQ125: 別紙「商品勘定利益計算」参照
B126: =IF($D126="","",MAX(OFFSET($B$8,0,0,ROW()-ROW($B$8),2))+1) -> 119 | D126: 前日末在高売価 | L126: =VLOOKUP(D126,カラムID辞書!$C$4:$D$1266,2,FALSE) -> ZENJTZAID_BIK | AB126: =IF(L126="DELDTE","","○") -> ○ | AE126: =IF(AB126="○",IF(AH126="timestamp","now()",IF(LEFT(AH126,9)="character","' '","0")),"") -> 0 | AH126: =VLOOKUP(D126,カラムID辞書!C:H,3,FALSE) -> numeric | AM126: =VLOOKUP(D126,カラムID辞書!C:H,4,FALSE) -> 13 | AO126: =VLOOKUP(D126,カラムID辞書!C:H,6,FALSE) -> 13 | AQ126: 別紙「商品勘定利益計算」参照
B127: =IF($D127="","",MAX(OFFSET($B$8,0,0,ROW()-ROW($B$8),2))+1) -> 120 | D127: 前日末在高数量 | L127: =VLOOKUP(D127,カラムID辞書!$C$4:$D$1266,2,FALSE) -> ZENJTZAID_SU | AB127: =IF(L127="DELDTE","","○") -> ○ | AE127: =IF(AB127="○",IF(AH127="timestamp","now()",IF(LEFT(AH127,9)="character","' '","0")),"") -> 0 | AH127: =VLOOKUP(D127,カラムID辞書!C:H,3,FALSE) -> numeric | AM127: =VLOOKUP(D127,カラムID辞書!C:H,4,FALSE) -> 10 | AO127: =VLOOKUP(D127,カラムID辞書!C:H,6,FALSE) -> 10 | AQ127: 別紙「商品勘定利益計算」参照
B128: =IF($D128="","",MAX(OFFSET($B$8,0,0,ROW()-ROW($B$8),2))+1) -> 121 | D128: 月初在高原価 | L128: =VLOOKUP(D128,カラムID辞書!$C$4:$D$1266,2,FALSE) -> GESSHOZAID_GNK | AB128: =IF(L128="DELDTE","","○") -> ○ | AE128: =IF(AB128="○",IF(AH128="timestamp","now()",IF(LEFT(AH128,9)="character","' '","0")),"") -> 0 | AH128: =VLOOKUP(D128,カラムID辞書!C:H,3,FALSE) -> numeric | AM128: =VLOOKUP(D128,カラムID辞書!C:H,4,FALSE) -> 13 | AO128: =VLOOKUP(D128,カラムID辞書!C:H,6,FALSE) -> 13 | AQ128: 別紙「商品勘定利益計算」参照
B129: =IF($D129="","",MAX(OFFSET($B$8,0,0,ROW()-ROW($B$8),2))+1) -> 122 | D129: 月初在高売価 | L129: =VLOOKUP(D129,カラムID辞書!$C$4:$D$1266,2,FALSE) -> GESSHOZAID_BIK | AB129: =IF(L129="DELDTE","","○") -> ○ | AE129: =IF(AB129="○",IF(AH129="timestamp","now()",IF(LEFT(AH129,9)="character","' '","0")),"") -> 0 | AH129: =VLOOKUP(D129,カラムID辞書!C:H,3,FALSE) -> numeric | AM129: =VLOOKUP(D129,カラムID辞書!C:H,4,FALSE) -> 13 | AO129: =VLOOKUP(D129,カラムID辞書!C:H,6,FALSE) -> 13 | AQ129: 別紙「商品勘定利益計算」参照
...

Sheet 売価還元単位別月別実績
B2: ユーザインタフェース 設計書 | J2: サブシステム分類 | O2: ドキュメント ID | T2: ドキュメント名 | BK2: 更新者 | BN2: 最終更新日 | BR2: 履歴 | BT2: 作成者 | BW2: 作成日
J3: 商品勘定 | O3: 2.04 | T3: テーブル定義 | BR3: 第1版 | BT3: 富士通 | BW3: 42917
B5: 概念データ名／ID | J5: 売価還元単位別月別実績テーブル | U5: ／ | V5: LBT02_BAIKAN_M | AD5: OID | AK5: 最大レコード長 | AR5: =ROUNDUP((27+ROUNDUP((MAX(B:B)-COUNTIF(AB:AB,"○"))/8,0)+IF(AF5="",0,4))/8,0)*8+SUM(AO8:AO1043) -> 1900 | AU5: Byte | AW5: 用途 | BB5: 商品勘定実績を月単位で管理する。
B7: 項番 | D7: 項目論理名称 | L7: 項目物理名称 | T7: PKey | V7: IDX1 | X7: IDX2 | Z7: IDX3 | AB7: NOTNULL | AE7: DEFAULT | AH7: Type | AM7: 桁数 | AO7: Byte | AQ7: 項目説明 | BR7: 備考
B8: 1 | D8: 年月 | L8: =VLOOKUP(D8,カラムID辞書!$C$4:$D$1266,2,FALSE) -> YM | T8: 1 | AB8: =IF(L8="DELDTE","","○") -> ○ | AE8: =IF(AB8="○",IF(AH8="timestamp","now()",IF(LEFT(AH8,9)="character","' '","0")),"") -> 0 | AH8: =VLOOKUP(D8,カラムID辞書!C:H,3,FALSE) -> numeric | AM8: =VLOOKUP(D8,カラムID辞書!C:H,4,FALSE) -> 6 | AO8: =VLOOKUP(D8,カラムID辞書!C:H,6,FALSE) -> 6 | AQ8: 伝票計上月
B9: =IF($D9="","",MAX(OFFSET($B$8,0,0,ROW()-ROW($B$8),2))+1) -> 2 | D9: システムグループコード | L9: =VLOOKUP(D9,カラムID辞書!$C$4:$D$1266,2,FALSE) -> SYSGRPCD | T9: 2 | AB9: =IF(L9="DELDTE","","○") -> ○ | AE9: =IF(AB9="○",IF(AH9="timestamp","now()",IF(LEFT(AH9,9)="character","' '","0")),"") -> ' ' | AH9: =VLOOKUP(D9,カラムID辞書!C:H,3,FALSE) -> character varying | AM9: =VLOOKUP(D9,カラムID辞書!C:H,4,FALSE) -> 4 | AO9: =VLOOKUP(D9,カラムID辞書!C:H,6,FALSE) -> 4 | AQ9: ユーザ分類コード | BR9: "0010"固定
B10: =IF($D10="","",MAX(OFFSET($B$8,0,0,ROW()-ROW($B$8),2))+1) -> 3 | D10: 企業グループコード | L10: =VLOOKUP(D10,カラムID辞書!$C$4:$D$1266,2,FALSE) -> KGYGRPCD | T10: 3 | AB10: =IF(L10="DELDTE","","○") -> ○ | AE10: =IF(AB10="○",IF(AH10="timestamp","now()",IF(LEFT(AH10,9)="character","' '","0")),"") -> ' ' | AH10: =VLOOKUP(D10,カラムID辞書!C:H,3,FALSE) -> character varying | AM10: =VLOOKUP(D10,カラムID辞書!C:H,4,FALSE) -> 3 | AO10: =VLOOKUP(D10,カラムID辞書!C:H,6,FALSE) -> 3 | AQ10: 売上、仕入伝票の企業グループコード
B11: =IF($D11="","",MAX(OFFSET($B$8,0,0,ROW()-ROW($B$8),2))+1) -> 4 | D11: 店コード | L11: =VLOOKUP(D11,カラムID辞書!$C$4:$D$1266,2,FALSE) -> TENCD | T11: 4 | AB11: =IF(L11="DELDTE","","○") -> ○ | AE11: =IF(AB11="○",IF(AH11="timestamp","now()",IF(LEFT(AH11,9)="character","' '","0")),"") -> ' ' | AH11: =VLOOKUP(D11,カラムID辞書!C:H,3,FALSE) -> character varying | AM11: =VLOOKUP(D11,カラムID辞書!C:H,4,FALSE) -> 4 | AO11: =VLOOKUP(D11,カラムID辞書!C:H,6,FALSE) -> 4 | AQ11: 売上、仕入伝票の店コード
B12: =IF($D12="","",MAX(OFFSET($B$8,0,0,ROW()-ROW($B$8),2))+1) -> 5 | D12: 商品コード１ | L12: =VLOOKUP(D12,カラムID辞書!$C$4:$D$1266,2,FALSE) -> SHOHINCD1 | T12: 5 | AB12: =IF(L12="DELDTE","","○") -> ○ | AE12: =IF(AB12="○",IF(AH12="timestamp","now()",IF(LEFT(AH12,9)="character","' '","0")),"") -> ' ' | AH12: =VLOOKUP(D12,カラムID辞書!C:H,3,FALSE) -> character varying | AM12: =VLOOKUP(D12,カラムID辞書!C:H,4,FALSE) -> 6 | AO12: =VLOOKUP(D12,カラムID辞書!C:H,6,FALSE) -> 6 | AQ12: 売上、仕入伝票の商品コード１ | BR12: 品番
B13: =IF($D13="","",MAX(OFFSET($B$8,0,0,ROW()-ROW($B$8),2))+1) -> 6 | D13: 商品コード２ | L13: =VLOOKUP(D13,カラムID辞書!$C$4:$D$1266,2,FALSE) -> SHOHINCD2 | T13: 6 | AB13: =IF(L13="DELDTE","","○") -> ○ | AE13: =IF(AB13="○",IF(AH13="timestamp","now()",IF(LEFT(AH13,9)="character","' '","0")),"") -> ' ' | AH13: =VLOOKUP(D13,カラムID辞書!C:H,3,FALSE) -> character varying | AM13: =VLOOKUP(D13,カラムID辞書!C:H,4,FALSE) -> 6 | AO13: =VLOOKUP(D13,カラムID辞書!C:H,6,FALSE) -> 6 | AQ13: 売上、仕入伝票の商品コード２ | BR13: （未設定）
B14: =IF($D14="","",MAX(OFFSET($B$8,0,0,ROW()-ROW($B$8),2))+1) -> 7 | D14: 商品コード３ | L14: =VLOOKUP(D14,カラムID辞書!$C$4:$D$1266,2,FALSE) -> SHOHINCD3 | T14: 7 | AB14: =IF(L14="DELDTE","","○") -> ○ | AE14: =IF(AB14="○",IF(AH14="timestamp","now()",IF(LEFT(AH14,9)="character","' '","0")),"") -> ' ' | AH14: =VLOOKUP(D14,カラムID辞書!C:H,3,FALSE) -> character varying | AM14: =VLOOKUP(D14,カラムID辞書!C:H,4,FALSE) -> 6 | AO14: =VLOOKUP(D14,カラムID辞書!C:H,6,FALSE) -> 6 | AQ14: 売上、仕入伝票の商品コード３ | BR14: （未設定）
B15: =IF($D15="","",MAX(OFFSET($B$8,0,0,ROW()-ROW($B$8),2))+1) -> 8 | D15: 商品コード４ | L15: =VLOOKUP(D15,カラムID辞書!$C$4:$D$1266,2,FALSE) -> SHOHINCD4 | T15: 8 | AB15: =IF(L15="DELDTE","","○") -> ○ | AE15: =IF(AB15="○",IF(AH15="timestamp","now()",IF(LEFT(AH15,9)="character","' '","0")),"") -> ' ' | AH15: =VLOOKUP(D15,カラムID辞書!C:H,3,FALSE) -> character varying | AM15: =VLOOKUP(D15,カラムID辞書!C:H,4,FALSE) -> 6 | AO15: =VLOOKUP(D15,カラムID辞書!C:H,6,FALSE) -> 6 | AQ15: 売上、仕入伝票の商品コード４ | BR15: （未設定）
B16: =IF($D16="","",MAX(OFFSET($B$8,0,0,ROW()-ROW($B$8),2))+1) -> 9 | D16: 商品コード５ | L16: =VLOOKUP(D16,カラムID辞書!$C$4:$D$1266,2,FALSE) -> SHOHINCD5 | T16: 9 | AB16: =IF(L16="DELDTE","","○") -> ○ | AE16: =IF(AB16="○",IF(AH16="timestamp","now()",IF(LEFT(AH16,9)="character","' '","0")),"") -> ' ' | AH16: =VLOOKUP(D16,カラムID辞書!C:H,3,FALSE) -> character varying | AM16: =VLOOKUP(D16,カラムID辞書!C:H,4,FALSE) -> 6 | AO16: =VLOOKUP(D16,カラムID辞書!C:H,6,FALSE) -> 6 | AQ16: 売上、仕入伝票の商品コード５ | BR16: （未設定）
B17: =IF($D17="","",MAX(OFFSET($B$8,0,0,ROW()-ROW($B$8),2))+1) -> 10 | D17: 細別コード１ | L17: =VLOOKUP(D17,カラムID辞書!$C$4:$D$1266,2,FALSE) -> SIBTCD1 | T17: 10 | AB17: =IF(L17="DELDTE","","○") -> ○ | AE17: =IF(AB17="○",IF(AH17="timestamp","now()",IF(LEFT(AH17,9)="character","' '","0")),"") -> ' ' | AH17: =VLOOKUP(D17,カラムID辞書!C:H,3,FALSE) -> character varying | AM17: =VLOOKUP(D17,カラムID辞書!C:H,4,FALSE) -> 10 | AO17: =VLOOKUP(D17,カラムID辞書!C:H,6,FALSE) -> 10 | AQ17: 売上、仕入伝票の細別コード１ | BR17: （未設定）
B18: =IF($D18="","",MAX(OFFSET($B$8,0,0,ROW()-ROW($B$8),2))+1) -> 11 | D18: 細別コード２ | L18: =VLOOKUP(D18,カラムID辞書!$C$4:$D$1266,2,FALSE) -> SIBTCD2 | T18: 11 | AB18: =IF(L18="DELDTE","","○") -> ○ | AE18: =IF(AB18="○",IF(AH18="timestamp","now()",IF(LEFT(AH18,9)="character","' '","0")),"") -> ' ' | AH18: =VLOOKUP(D18,カラムID辞書!C:H,3,FALSE) -> character varying | AM18: =VLOOKUP(D18,カラムID辞書!C:H,4,FALSE) -> 10 | AO18: =VLOOKUP(D18,カラムID辞書!C:H,6,FALSE) -> 10 | AQ18: 売上、仕入伝票の細別コード２ | BR18: （未設定）
B19: =IF($D19="","",MAX(OFFSET($B$8,0,0,ROW()-ROW($B$8),2))+1) -> 12 | D19: 単品コード１ | L19: =VLOOKUP(D19,カラムID辞書!$C$4:$D$1266,2,FALSE) -> TNPNCD1 | T19: 12 | AB19: =IF(L19="DELDTE","","○") -> ○ | AE19: =IF(AB19="○",IF(AH19="timestamp","now()",IF(LEFT(AH19,9)="character","' '","0")),"") -> ' ' | AH19: =VLOOKUP(D19,カラムID辞書!C:H,3,FALSE) -> character varying | AM19: =VLOOKUP(D19,カラムID辞書!C:H,4,FALSE) -> 13 | AO19: =VLOOKUP(D19,カラムID辞書!C:H,6,FALSE) -> 13 | AQ19: 売上、仕入伝票の単品コード１ | BR19: （未設定）
B20: =IF($D20="","",MAX(OFFSET($B$8,0,0,ROW()-ROW($B$8),2))+1) -> 13 | D20: 単品コード２ | L20: =VLOOKUP(D20,カラムID辞書!$C$4:$D$1266,2,FALSE) -> TNPNCD2 | T20: 13 | AB20: =IF(L20="DELDTE","","○") -> ○ | AE20: =IF(AB20="○",IF(AH20="timestamp","now()",IF(LEFT(AH20,9)="character","' '","0")),"") -> ' ' | AH20: =VLOOKUP(D20,カラムID辞書!C:H,3,FALSE) -> character varying | AM20: =VLOOKUP(D20,カラムID辞書!C:H,4,FALSE) -> 13 | AO20: =VLOOKUP(D20,カラムID辞書!C:H,6,FALSE) -> 13 | AQ20: 売上、仕入伝票の単品コード２ | BR20: （未設定）
B21: =IF($D21="","",MAX(OFFSET($B$8,0,0,ROW()-ROW($B$8),2))+1) -> 14 | D21: 仕入区分 | L21: =VLOOKUP(D21,カラムID辞書!$C$4:$D$1266,2,FALSE) -> SHIIREKBN | T21: 14 | AB21: =IF(L21="DELDTE","","○") -> ○ | AE21: =IF(AB21="○",IF(AH21="timestamp","now()",IF(LEFT(AH21,9)="character","' '","0")),"") -> ' ' | AH21: =VLOOKUP(D21,カラムID辞書!C:H,3,FALSE) -> character varying | AM21: =VLOOKUP(D21,カラムID辞書!C:H,4,FALSE) -> 2 | AO21: =VLOOKUP(D21,カラムID辞書!C:H,6,FALSE) -> 2 | AQ21: 01：直扱 / 04：売仕
B22: =IF($D22="","",MAX(OFFSET($B$8,0,0,ROW()-ROW($B$8),2))+1) -> 15 | D22: 原価管理区分 | L22: =VLOOKUP(D22,カラムID辞書!$C$4:$D$1266,2,FALSE) -> GNKKBN | T22: 15 | AB22: =IF(L22="DELDTE","","○") -> ○ | AE22: =IF(AB22="○",IF(AH22="timestamp","now()",IF(LEFT(AH22,9)="character","' '","0")),"") -> ' ' | AH22: =VLOOKUP(D22,カラムID辞書!C:H,3,FALSE) -> character varying | AM22: =VLOOKUP(D22,カラムID辞書!C:H,4,FALSE) -> 1 | AO22: =VLOOKUP(D22,カラムID辞書!C:H,6,FALSE) -> 1 | AQ22: 1：売価品 / 2：原価品
B23: =IF($D23="","",MAX(OFFSET($B$8,0,0,ROW()-ROW($B$8),2))+1) -> 16 | D23: ＤＳ区分 | L23: =VLOOKUP(D23,カラムID辞書!$C$4:$D$1266,2,FALSE) -> DSKBN | T23: 16 | AB23: =IF(L23="DELDTE","","○") -> ○ | AE23: =IF(AB23="○",IF(AH23="timestamp","now()",IF(LEFT(AH23,9)="character","' '","0")),"") -> ' ' | AH23: =VLOOKUP(D23,カラムID辞書!C:H,3,FALSE) -> character varying | AM23: =VLOOKUP(D23,カラムID辞書!C:H,4,FALSE) -> 1 | AO23: =VLOOKUP(D23,カラムID辞書!C:H,6,FALSE) -> 1 | AQ23: 0：プロパー / 1：セール
B24: =IF($D24="","",MAX(OFFSET($B$8,0,0,ROW()-ROW($B$8),2))+1) -> 17 | D24: 利益計算式区分 | L24: =VLOOKUP(D24,カラムID辞書!$C$4:$D$1266,2,FALSE) -> RIEKICMPKBN | T24: 17 | AB24: =IF(L24="DELDTE","","○") -> ○ | AE24: =IF(AB24="○",IF(AH24="timestamp","now()",IF(LEFT(AH24,9)="character","' '","0")),"") -> ' ' | AH24: =VLOOKUP(D24,カラムID辞書!C:H,3,FALSE) -> character varying | AM24: =VLOOKUP(D24,カラムID辞書!C:H,4,FALSE) -> 1 | AO24: =VLOOKUP(D24,カラムID辞書!C:H,6,FALSE) -> 1 | AQ24: 0：利益計算対象外 / 1：売価還元原価法 / 3：売仕原価計算 /7：原価品計算
B25: =IF($D25="","",MAX(OFFSET($B$8,0,0,ROW()-ROW($B$8),2))+1) -> 18 | D25: 期 | L25: =VLOOKUP(D25,カラムID辞書!$C$4:$D$1266,2,FALSE) -> NENKI | AB25: =IF(L25="DELDTE","","○") -> ○ | AE25: =IF(AB25="○",IF(AH25="timestamp","now()",IF(LEFT(AH25,9)="character","' '","0")),"") -> 0 | AH25: =VLOOKUP(D25,カラムID辞書!C:H,3,FALSE) -> numeric | AM25: =VLOOKUP(D25,カラムID辞書!C:H,4,FALSE) -> 6 | AO25: =VLOOKUP(D25,カラムID辞書!C:H,6,FALSE) -> 6 | AQ25: 「年月」に該当する期首月（YYYYMM）
B26: =IF($D26="","",MAX(OFFSET($B$8,0,0,ROW()-ROW($B$8),2))+1) -> 19 | D26: 年 | L26: =VLOOKUP(D26,カラムID辞書!$C$4:$D$1266,2,FALSE) -> NENDO | AB26: =IF(L26="DELDTE","","○") -> ○ | AE26: =IF(AB26="○",IF(AH26="timestamp","now()",IF(LEFT(AH26,9)="character","' '","0")),"") -> 0 | AH26: =VLOOKUP(D26,カラムID辞書!C:H,3,FALSE) -> numeric | AM26: =VLOOKUP(D26,カラムID辞書!C:H,4,FALSE) -> 6 | AO26: =VLOOKUP(D26,カラムID辞書!C:H,6,FALSE) -> 6 | AQ26: 「年月」に該当する年度開始月（YYYYMM）
B27: =IF($D27="","",MAX(OFFSET($B$8,0,0,ROW()-ROW($B$8),2))+1) -> 20 | D27: 売上高原価 | L27: =VLOOKUP(D27,カラムID辞書!$C$4:$D$1266,2,FALSE) -> URIAGED_GNK | AB27: =IF(L27="DELDTE","","○") -> ○ | AE27: =IF(AB27="○",IF(AH27="timestamp","now()",IF(LEFT(AH27,9)="character","' '","0")),"") -> 0 | AH27: =VLOOKUP(D27,カラムID辞書!C:H,3,FALSE) -> numeric | AM27: =VLOOKUP(D27,カラムID辞書!C:H,4,FALSE) -> 13 | AO27: =VLOOKUP(D27,カラムID辞書!C:H,6,FALSE) -> 13 | AQ27: 別紙「商品勘定利益計算」参照
B28: =IF($D28="","",MAX(OFFSET($B$8,0,0,ROW()-ROW($B$8),2))+1) -> 21 | D28: 売上高売価 | L28: =VLOOKUP(D28,カラムID辞書!$C$4:$D$1266,2,FALSE) -> URIAGED_BIK | AB28: =IF(L28="DELDTE","","○") -> ○ | AE28: =IF(AB28="○",IF(AH28="timestamp","now()",IF(LEFT(AH28,9)="character","' '","0")),"") -> 0 | AH28: =VLOOKUP(D28,カラムID辞書!C:H,3,FALSE) -> numeric | AM28: =VLOOKUP(D28,カラムID辞書!C:H,4,FALSE) -> 13 | AO28: =VLOOKUP(D28,カラムID辞書!C:H,6,FALSE) -> 13 | AQ28: 売上伝票の売上高集計値（総売上高）
B29: =IF($D29="","",MAX(OFFSET($B$8,0,0,ROW()-ROW($B$8),2))+1) -> 22 | D29: 売上高分類１ | L29: =VLOOKUP(D29,カラムID辞書!$C$4:$D$1266,2,FALSE) -> URIAGED_BNRI1 | AB29: =IF(L29="DELDTE","","○") -> ○ | AE29: =IF(AB29="○",IF(AH29="timestamp","now()",IF(LEFT(AH29,9)="character","' '","0")),"") -> 0 | AH29: =VLOOKUP(D29,カラムID辞書!C:H,3,FALSE) -> numeric | AM29: =VLOOKUP(D29,カラムID辞書!C:H,4,FALSE) -> 13 | AO29: =VLOOKUP(D29,カラムID辞書!C:H,6,FALSE) -> 13 | AQ29: 売上伝票の売上高集計値（店頭・普通品）
B30: =IF($D30="","",MAX(OFFSET($B$8,0,0,ROW()-ROW($B$8),2))+1) -> 23 | D30: 売上高分類２ | L30: =VLOOKUP(D30,カラムID辞書!$C$4:$D$1266,2,FALSE) -> URIAGED_BNRI2 | AB30: =IF(L30="DELDTE","","○") -> ○ | AE30: =IF(AB30="○",IF(AH30="timestamp","now()",IF(LEFT(AH30,9)="character","' '","0")),"") -> 0 | AH30: =VLOOKUP(D30,カラムID辞書!C:H,3,FALSE) -> numeric | AM30: =VLOOKUP(D30,カラムID辞書!C:H,4,FALSE) -> 13 | AO30: =VLOOKUP(D30,カラムID辞書!C:H,6,FALSE) -> 13 | AQ30: 売上伝票の売上高集計値（店頭・催事）
B31: =IF($D31="","",MAX(OFFSET($B$8,0,0,ROW()-ROW($B$8),2))+1) -> 24 | D31: 売上高分類３ | L31: =VLOOKUP(D31,カラムID辞書!$C$4:$D$1266,2,FALSE) -> URIAGED_BNRI3 | AB31: =IF(L31="DELDTE","","○") -> ○ | AE31: =IF(AB31="○",IF(AH31="timestamp","now()",IF(LEFT(AH31,9)="character","' '","0")),"") -> 0 | AH31: =VLOOKUP(D31,カラムID辞書!C:H,3,FALSE) -> numeric | AM31: =VLOOKUP(D31,カラムID辞書!C:H,4,FALSE) -> 13 | AO31: =VLOOKUP(D31,カラムID辞書!C:H,6,FALSE) -> 13 | AQ31: 売上伝票の売上高集計値（店頭・店外）
B32: =IF($D32="","",MAX(OFFSET($B$8,0,0,ROW()-ROW($B$8),2))+1) -> 25 | D32: 売上高分類４ | L32: =VLOOKUP(D32,カラムID辞書!$C$4:$D$1266,2,FALSE) -> URIAGED_BNRI4 | AB32: =IF(L32="DELDTE","","○") -> ○ | AE32: =IF(AB32="○",IF(AH32="timestamp","now()",IF(LEFT(AH32,9)="character","' '","0")),"") -> 0 | AH32: =VLOOKUP(D32,カラムID辞書!C:H,3,FALSE) -> numeric | AM32: =VLOOKUP(D32,カラムID辞書!C:H,4,FALSE) -> 13 | AO32: =VLOOKUP(D32,カラムID辞書!C:H,6,FALSE) -> 13 | AQ32: 売上伝票の売上高集計値（店頭・ギフト）
B33: =IF($D33="","",MAX(OFFSET($B$8,0,0,ROW()-ROW($B$8),2))+1) -> 26 | D33: 売上高分類５ | L33: =VLOOKUP(D33,カラムID辞書!$C$4:$D$1266,2,FALSE) -> URIAGED_BNRI5 | AB33: =IF(L33="DELDTE","","○") -> ○ | AE33: =IF(AB33="○",IF(AH33="timestamp","now()",IF(LEFT(AH33,9)="character","' '","0")),"") -> 0 | AH33: =VLOOKUP(D33,カラムID辞書!C:H,3,FALSE) -> numeric | AM33: =VLOOKUP(D33,カラムID辞書!C:H,4,FALSE) -> 13 | AO33: =VLOOKUP(D33,カラムID辞書!C:H,6,FALSE) -> 13 | AQ33: 売上伝票の売上高集計値（店頭・ネット）
B34: =IF($D34="","",MAX(OFFSET($B$8,0,0,ROW()-ROW($B$8),2))+1) -> 27 | D34: 売上高分類６ | L34: =VLOOKUP(D34,カラムID辞書!$C$4:$D$1266,2,FALSE) -> URIAGED_BNRI6 | AB34: =IF(L34="DELDTE","","○") -> ○ | AE34: =IF(AB34="○",IF(AH34="timestamp","now()",IF(LEFT(AH34,9)="character","' '","0")),"") -> 0 | AH34: =VLOOKUP(D34,カラムID辞書!C:H,3,FALSE) -> numeric | AM34: =VLOOKUP(D34,カラムID辞書!C:H,4,FALSE) -> 13 | AO34: =VLOOKUP(D34,カラムID辞書!C:H,6,FALSE) -> 13 | AQ34: 売上伝票の売上高集計値（店頭・その他）
B35: =IF($D35="","",MAX(OFFSET($B$8,0,0,ROW()-ROW($B$8),2))+1) -> 28 | D35: 売上高分類７ | L35: =VLOOKUP(D35,カラムID辞書!$C$4:$D$1266,2,FALSE) -> URIAGED_BNRI7 | AB35: =IF(L35="DELDTE","","○") -> ○ | AE35: =IF(AB35="○",IF(AH35="timestamp","now()",IF(LEFT(AH35,9)="character","' '","0")),"") -> 0 | AH35: =VLOOKUP(D35,カラムID辞書!C:H,3,FALSE) -> numeric | AM35: =VLOOKUP(D35,カラムID辞書!C:H,4,FALSE) -> 13 | AO35: =VLOOKUP(D35,カラムID辞書!C:H,6,FALSE) -> 13 | AQ35: 売上伝票の売上高集計値（非店頭・店外）
B36: =IF($D36="","",MAX(OFFSET($B$8,0,0,ROW()-ROW($B$8),2))+1) -> 29 | D36: 売上高分類８ | L36: =VLOOKUP(D36,カラムID辞書!$C$4:$D$1266,2,FALSE) -> URIAGED_BNRI8 | AB36: =IF(L36="DELDTE","","○") -> ○ | AE36: =IF(AB36="○",IF(AH36="timestamp","now()",IF(LEFT(AH36,9)="character","' '","0")),"") -> 0 | AH36: =VLOOKUP(D36,カラムID辞書!C:H,3,FALSE) -> numeric | AM36: =VLOOKUP(D36,カラムID辞書!C:H,4,FALSE) -> 13 | AO36: =VLOOKUP(D36,カラムID辞書!C:H,6,FALSE) -> 13 | AQ36: 売上伝票の売上高集計値（非店頭・ギフト）
B37: =IF($D37="","",MAX(OFFSET($B$8,0,0,ROW()-ROW($B$8),2))+1) -> 30 | D37: 売上高分類９ | L37: =VLOOKUP(D37,カラムID辞書!$C$4:$D$1266,2,FALSE) -> URIAGED_BNRI9 | AB37: =IF(L37="DELDTE","","○") -> ○ | AE37: =IF(AB37="○",IF(AH37="timestamp","now()",IF(LEFT(AH37,9)="character","' '","0")),"") -> 0 | AH37: =VLOOKUP(D37,カラムID辞書!C:H,3,FALSE) -> numeric | AM37: =VLOOKUP(D37,カラムID辞書!C:H,4,FALSE) -> 13 | AO37: =VLOOKUP(D37,カラムID辞書!C:H,6,FALSE) -> 13 | AQ37: 売上伝票の売上高集計値（非店頭・その他）
B38: =IF($D38="","",MAX(OFFSET($B$8,0,0,ROW()-ROW($B$8),2))+1) -> 31 | D38: 売上高分類１０ | L38: =VLOOKUP(D38,カラムID辞書!$C$4:$D$1266,2,FALSE) -> URIAGED_BNRI10 | AB38: =IF(L38="DELDTE","","○") -> ○ | AE38: =IF(AB38="○",IF(AH38="timestamp","now()",IF(LEFT(AH38,9)="character","' '","0")),"") -> 0 | AH38: =VLOOKUP(D38,カラムID辞書!C:H,3,FALSE) -> numeric | AM38: =VLOOKUP(D38,カラムID辞書!C:H,4,FALSE) -> 13 | AO38: =VLOOKUP(D38,カラムID辞書!C:H,6,FALSE) -> 13 | BR38: （未設定：ZERO）
B39: =IF($D39="","",MAX(OFFSET($B$8,0,0,ROW()-ROW($B$8),2))+1) -> 32 | D39: 売上高数量 | L39: =VLOOKUP(D39,カラムID辞書!$C$4:$D$1266,2,FALSE) -> URIAGED_SU | AB39: =IF(L39="DELDTE","","○") -> ○ | AE39: =IF(AB39="○",IF(AH39="timestamp","now()",IF(LEFT(AH39,9)="character","' '","0")),"") -> 0 | AH39: =VLOOKUP(D39,カラムID辞書!C:H,3,FALSE) -> numeric | AM39: =VLOOKUP(D39,カラムID辞書!C:H,4,FALSE) -> 10 | AO39: =VLOOKUP(D39,カラムID辞書!C:H,6,FALSE) -> 10 | AQ39: 売上伝票の売上数量集計値
B40: =IF($D40="","",MAX(OFFSET($B$8,0,0,ROW()-ROW($B$8),2))+1) -> 33 | D40: 利益高 | L40: =VLOOKUP(D40,カラムID辞書!$C$4:$D$1266,2,FALSE) -> RIEKID | AB40: =IF(L40="DELDTE","","○") -> ○ | AE40: =IF(AB40="○",IF(AH40="timestamp","now()",IF(LEFT(AH40,9)="character","' '","0")),"") -> 0 | AH40: =VLOOKUP(D40,カラムID辞書!C:H,3,FALSE) -> numeric | AM40: =VLOOKUP(D40,カラムID辞書!C:H,4,FALSE) -> 13 | AO40: =VLOOKUP(D40,カラムID辞書!C:H,6,FALSE) -> 13 | AQ40: 別紙「商品勘定利益計算」参照 | BR40: 売益金
B41: =IF($D41="","",MAX(OFFSET($B$8,0,0,ROW()-ROW($B$8),2))+1) -> 34 | D41: 割引額 | L41: =VLOOKUP(D41,カラムID辞書!$C$4:$D$1266,2,FALSE) -> WARIBIKI_GAK | AB41: =IF(L41="DELDTE","","○") -> ○ | AE41: =IF(AB41="○",IF(AH41="timestamp","now()",IF(LEFT(AH41,9)="character","' '","0")),"") -> 0 | AH41: =VLOOKUP(D41,カラムID辞書!C:H,3,FALSE) -> numeric | AM41: =VLOOKUP(D41,カラムID辞書!C:H,4,FALSE) -> 13 | AO41: =VLOOKUP(D41,カラムID辞書!C:H,6,FALSE) -> 13 | AQ41: 売上伝票の割引額集計値
B42: =IF($D42="","",MAX(OFFSET($B$8,0,0,ROW()-ROW($B$8),2))+1) -> 35 | D42: 値引額 | L42: =VLOOKUP(D42,カラムID辞書!$C$4:$D$1266,2,FALSE) -> NEBIKI_GAK | AB42: =IF(L42="DELDTE","","○") -> ○ | AE42: =IF(AB42="○",IF(AH42="timestamp","now()",IF(LEFT(AH42,9)="character","' '","0")),"") -> 0 | AH42: =VLOOKUP(D42,カラムID辞書!C:H,3,FALSE) -> numeric | AM42: =VLOOKUP(D42,カラムID辞書!C:H,4,FALSE) -> 13 | AO42: =VLOOKUP(D42,カラムID辞書!C:H,6,FALSE) -> 13 | AQ42: 売上伝票の値引額集計値
B43: =IF($D43="","",MAX(OFFSET($B$8,0,0,ROW()-ROW($B$8),2))+1) -> 36 | D43: 客数１ | L43: =VLOOKUP(D43,カラムID辞書!$C$4:$D$1266,2,FALSE) -> KYAKU1_SU | AB43: =IF(L43="DELDTE","","○") -> ○ | AE43: =IF(AB43="○",IF(AH43="timestamp","now()",IF(LEFT(AH43,9)="character","' '","0")),"") -> 0 | AH43: =VLOOKUP(D43,カラムID辞書!C:H,3,FALSE) -> numeric | AM43: =VLOOKUP(D43,カラムID辞書!C:H,4,FALSE) -> 10,2 | AO43: =VLOOKUP(D43,カラムID辞書!C:H,6,FALSE) -> 10 | AQ43: 売上伝票の客数１集計値
B44: =IF($D44="","",MAX(OFFSET($B$8,0,0,ROW()-ROW($B$8),2))+1) -> 37 | D44: 客数２ | L44: =VLOOKUP(D44,カラムID辞書!$C$4:$D$1266,2,FALSE) -> KYAKU2_SU | AB44: =IF(L44="DELDTE","","○") -> ○ | AE44: =IF(AB44="○",IF(AH44="timestamp","now()",IF(LEFT(AH44,9)="character","' '","0")),"") -> 0 | AH44: =VLOOKUP(D44,カラムID辞書!C:H,3,FALSE) -> numeric | AM44: =VLOOKUP(D44,カラムID辞書!C:H,4,FALSE) -> 10,2 | AO44: =VLOOKUP(D44,カラムID辞書!C:H,6,FALSE) -> 10 | AQ44: 売上伝票の客数２集計値
B45: =IF($D45="","",MAX(OFFSET($B$8,0,0,ROW()-ROW($B$8),2))+1) -> 38 | D45: 客数３ | L45: =VLOOKUP(D45,カラムID辞書!$C$4:$D$1266,2,FALSE) -> KYAKU3_SU | AB45: =IF(L45="DELDTE","","○") -> ○ | AE45: =IF(AB45="○",IF(AH45="timestamp","now()",IF(LEFT(AH45,9)="character","' '","0")),"") -> 0 | AH45: =VLOOKUP(D45,カラムID辞書!C:H,3,FALSE) -> numeric | AM45: =VLOOKUP(D45,カラムID辞書!C:H,4,FALSE) -> 10,2 | AO45: =VLOOKUP(D45,カラムID辞書!C:H,6,FALSE) -> 10 | AQ45: 売上伝票の客数３集計値 | BR45: （未設定：ZERO）
B46: =IF($D46="","",MAX(OFFSET($B$8,0,0,ROW()-ROW($B$8),2))+1) -> 39 | D46: 純仕入高原価 | L46: =VLOOKUP(D46,カラムID辞書!$C$4:$D$1266,2,FALSE) -> JNSHIIRED_GNK | AB46: =IF(L46="DELDTE","","○") -> ○ | AE46: =IF(AB46="○",IF(AH46="timestamp","now()",IF(LEFT(AH46,9)="character","' '","0")),"") -> 0 | AH46: =VLOOKUP(D46,カラムID辞書!C:H,3,FALSE) -> numeric | AM46: =VLOOKUP(D46,カラムID辞書!C:H,4,FALSE) -> 13 | AO46: =VLOOKUP(D46,カラムID辞書!C:H,6,FALSE) -> 13 | AQ46: 別紙「商品勘定利益計算」参照
B47: =IF($D47="","",MAX(OFFSET($B$8,0,0,ROW()-ROW($B$8),2))+1) -> 40 | D47: 純仕入高売価 | L47: =VLOOKUP(D47,カラムID辞書!$C$4:$D$1266,2,FALSE) -> JNSHIIRED_BIK | AB47: =IF(L47="DELDTE","","○") -> ○ | AE47: =IF(AB47="○",IF(AH47="timestamp","now()",IF(LEFT(AH47,9)="character","' '","0")),"") -> 0 | AH47: =VLOOKUP(D47,カラムID辞書!C:H,3,FALSE) -> numeric | AM47: =VLOOKUP(D47,カラムID辞書!C:H,4,FALSE) -> 13 | AO47: =VLOOKUP(D47,カラムID辞書!C:H,6,FALSE) -> 13 | AQ47: 別紙「商品勘定利益計算」参照
B48: =IF($D48="","",MAX(OFFSET($B$8,0,0,ROW()-ROW($B$8),2))+1) -> 41 | D48: 純仕入高数量 | L48: =VLOOKUP(D48,カラムID辞書!$C$4:$D$1266,2,FALSE) -> JNSHIIRED_SU | AB48: =IF(L48="DELDTE","","○") -> ○ | AE48: =IF(AB48="○",IF(AH48="timestamp","now()",IF(LEFT(AH48,9)="character","' '","0")),"") -> 0 | AH48: =VLOOKUP(D48,カラムID辞書!C:H,3,FALSE) -> numeric | AM48: =VLOOKUP(D48,カラムID辞書!C:H,4,FALSE) -> 10 | AO48: =VLOOKUP(D48,カラムID辞書!C:H,6,FALSE) -> 10 | AQ48: 別紙「商品勘定利益計算」参照
B49: =IF($D49="","",MAX(OFFSET($B$8,0,0,ROW()-ROW($B$8),2))+1) -> 42 | D49: 仕入高原価 | L49: =VLOOKUP(D49,カラムID辞書!$C$4:$D$1266,2,FALSE) -> SHIIRED_GNK | AB49: =IF(L49="DELDTE","","○") -> ○ | AE49: =IF(AB49="○",IF(AH49="timestamp","now()",IF(LEFT(AH49,9)="character","' '","0")),"") -> 0 | AH49: =VLOOKUP(D49,カラムID辞書!C:H,3,FALSE) -> numeric | AM49: =VLOOKUP(D49,カラムID辞書!C:H,4,FALSE) -> 13 | AO49: =VLOOKUP(D49,カラムID辞書!C:H,6,FALSE) -> 13 | AQ49: 仕入伝票の原価集計値
B50: =IF($D50="","",MAX(OFFSET($B$8,0,0,ROW()-ROW($B$8),2))+1) -> 43 | D50: 仕入高売価 | L50: =VLOOKUP(D50,カラムID辞書!$C$4:$D$1266,2,FALSE) -> SHIIRED_BIK | AB50: =IF(L50="DELDTE","","○") -> ○ | AE50: =IF(AB50="○",IF(AH50="timestamp","now()",IF(LEFT(AH50,9)="character","' '","0")),"") -> 0 | AH50: =VLOOKUP(D50,カラムID辞書!C:H,3,FALSE) -> numeric | AM50: =VLOOKUP(D50,カラムID辞書!C:H,4,FALSE) -> 13 | AO50: =VLOOKUP(D50,カラムID辞書!C:H,6,FALSE) -> 13 | AQ50: 仕入伝票の売価集計値
B51: =IF($D51="","",MAX(OFFSET($B$8,0,0,ROW()-ROW($B$8),2))+1) -> 44 | D51: 仕入高数量 | L51: =VLOOKUP(D51,カラムID辞書!$C$4:$D$1266,2,FALSE) -> SHIIRED_SU | AB51: =IF(L51="DELDTE","","○") -> ○ | AE51: =IF(AB51="○",IF(AH51="timestamp","now()",IF(LEFT(AH51,9)="character","' '","0")),"") -> 0 | AH51: =VLOOKUP(D51,カラムID辞書!C:H,3,FALSE) -> numeric | AM51: =VLOOKUP(D51,カラムID辞書!C:H,4,FALSE) -> 10 | AO51: =VLOOKUP(D51,カラムID辞書!C:H,6,FALSE) -> 10 | AQ51: 仕入伝票の数量集計値
B52: =IF($D52="","",MAX(OFFSET($B$8,0,0,ROW()-ROW($B$8),2))+1) -> 45 | D52: 付帯仕入高原価 | L52: =VLOOKUP(D52,カラムID辞書!$C$4:$D$1266,2,FALSE) -> FUTAISHIIRED_GNK | AB52: =IF(L52="DELDTE","","○") -> ○ | AE52: =IF(AB52="○",IF(AH52="timestamp","now()",IF(LEFT(AH52,9)="character","' '","0")),"") -> 0 | AH52: =VLOOKUP(D52,カラムID辞書!C:H,3,FALSE) -> numeric | AM52: =VLOOKUP(D52,カラムID辞書!C:H,4,FALSE) -> 13 | AO52: =VLOOKUP(D52,カラムID辞書!C:H,6,FALSE) -> 13 | BR52: （未設定：ZERO）
B53: =IF($D53="","",MAX(OFFSET($B$8,0,0,ROW()-ROW($B$8),2))+1) -> 46 | D53: 返品高原価 | L53: =VLOOKUP(D53,カラムID辞書!$C$4:$D$1266,2,FALSE) -> HENPND_GNK | AB53: =IF(L53="DELDTE","","○") -> ○ | AE53: =IF(AB53="○",IF(AH53="timestamp","now()",IF(LEFT(AH53,9)="character","' '","0")),"") -> 0 | AH53: =VLOOKUP(D53,カラムID辞書!C:H,3,FALSE) -> numeric | AM53: =VLOOKUP(D53,カラムID辞書!C:H,4,FALSE) -> 13 | AO53: =VLOOKUP(D53,カラムID辞書!C:H,6,FALSE) -> 13 | AQ53: 返品伝票の原価集計値
B54: =IF($D54="","",MAX(OFFSET($B$8,0,0,ROW()-ROW($B$8),2))+1) -> 47 | D54: 返品高売価 | L54: =VLOOKUP(D54,カラムID辞書!$C$4:$D$1266,2,FALSE) -> HENPND_BIK | AB54: =IF(L54="DELDTE","","○") -> ○ | AE54: =IF(AB54="○",IF(AH54="timestamp","now()",IF(LEFT(AH54,9)="character","' '","0")),"") -> 0 | AH54: =VLOOKUP(D54,カラムID辞書!C:H,3,FALSE) -> numeric | AM54: =VLOOKUP(D54,カラムID辞書!C:H,4,FALSE) -> 13 | AO54: =VLOOKUP(D54,カラムID辞書!C:H,6,FALSE) -> 13 | AQ54: 返品伝票の売価集計値
B55: =IF($D55="","",MAX(OFFSET($B$8,0,0,ROW()-ROW($B$8),2))+1) -> 48 | D55: 返品高数量 | L55: =VLOOKUP(D55,カラムID辞書!$C$4:$D$1266,2,FALSE) -> HENPND_SU | AB55: =IF(L55="DELDTE","","○") -> ○ | AE55: =IF(AB55="○",IF(AH55="timestamp","now()",IF(LEFT(AH55,9)="character","' '","0")),"") -> 0 | AH55: =VLOOKUP(D55,カラムID辞書!C:H,3,FALSE) -> numeric | AM55: =VLOOKUP(D55,カラムID辞書!C:H,4,FALSE) -> 10 | AO55: =VLOOKUP(D55,カラムID辞書!C:H,6,FALSE) -> 10 | AQ55: 返品伝票の数量集計値
B56: =IF($D56="","",MAX(OFFSET($B$8,0,0,ROW()-ROW($B$8),2))+1) -> 49 | D56: 付帯返品高原価 | L56: =VLOOKUP(D56,カラムID辞書!$C$4:$D$1266,2,FALSE) -> FUTAIHENPND_GNK | AB56: =IF(L56="DELDTE","","○") -> ○ | AE56: =IF(AB56="○",IF(AH56="timestamp","now()",IF(LEFT(AH56,9)="character","' '","0")),"") -> 0 | AH56: =VLOOKUP(D56,カラムID辞書!C:H,3,FALSE) -> numeric | AM56: =VLOOKUP(D56,カラムID辞書!C:H,4,FALSE) -> 13 | AO56: =VLOOKUP(D56,カラムID辞書!C:H,6,FALSE) -> 13 | BR56: （未設定：ZERO）
B57: =IF($D57="","",MAX(OFFSET($B$8,0,0,ROW()-ROW($B$8),2))+1) -> 50 | D57: 価格訂正仕入高原価 | L57: =VLOOKUP(D57,カラムID辞書!$C$4:$D$1266,2,FALSE) -> TEISEISHIIRED_GNK | AB57: =IF(L57="DELDTE","","○") -> ○ | AE57: =IF(AB57="○",IF(AH57="timestamp","now()",IF(LEFT(AH57,9)="character","' '","0")),"") -> 0 | AH57: =VLOOKUP(D57,カラムID辞書!C:H,3,FALSE) -> numeric | AM57: =VLOOKUP(D57,カラムID辞書!C:H,4,FALSE) -> 13 | AO57: =VLOOKUP(D57,カラムID辞書!C:H,6,FALSE) -> 13 | AQ57: 価格変更による再仕入伝票の原価集計値
B58: =IF($D58="","",MAX(OFFSET($B$8,0,0,ROW()-ROW($B$8),2))+1) -> 51 | D58: 価格訂正仕入高売価 | L58: =VLOOKUP(D58,カラムID辞書!$C$4:$D$1266,2,FALSE) -> TEISEISHIIRED_BIK | AB58: =IF(L58="DELDTE","","○") -> ○ | AE58: =IF(AB58="○",IF(AH58="timestamp","now()",IF(LEFT(AH58,9)="character","' '","0")),"") -> 0 | AH58: =VLOOKUP(D58,カラムID辞書!C:H,3,FALSE) -> numeric | AM58: =VLOOKUP(D58,カラムID辞書!C:H,4,FALSE) -> 13 | AO58: =VLOOKUP(D58,カラムID辞書!C:H,6,FALSE) -> 13 | AQ58: 価格変更による再仕入伝票の売価集計値
B59: =IF($D59="","",MAX(OFFSET($B$8,0,0,ROW()-ROW($B$8),2))+1) -> 52 | D59: 価格訂正仕入高数量 | L59: =VLOOKUP(D59,カラムID辞書!$C$4:$D$1266,2,FALSE) -> TEISEISHIIRED_SU | AB59: =IF(L59="DELDTE","","○") -> ○ | AE59: =IF(AB59="○",IF(AH59="timestamp","now()",IF(LEFT(AH59,9)="character","' '","0")),"") -> 0 | AH59: =VLOOKUP(D59,カラムID辞書!C:H,3,FALSE) -> numeric | AM59: =VLOOKUP(D59,カラムID辞書!C:H,4,FALSE) -> 10 | AO59: =VLOOKUP(D59,カラムID辞書!C:H,6,FALSE) -> 10 | AQ59: 価格変更による再仕入伝票の数量集計値
B60: =IF($D60="","",MAX(OFFSET($B$8,0,0,ROW()-ROW($B$8),2))+1) -> 53 | D60: 価格訂正返品高原価 | L60: =VLOOKUP(D60,カラムID辞書!$C$4:$D$1266,2,FALSE) -> TEISEIHENPIND_GNK | AB60: =IF(L60="DELDTE","","○") -> ○ | AE60: =IF(AB60="○",IF(AH60="timestamp","now()",IF(LEFT(AH60,9)="character","' '","0")),"") -> 0 | AH60: =VLOOKUP(D60,カラムID辞書!C:H,3,FALSE) -> numeric | AM60: =VLOOKUP(D60,カラムID辞書!C:H,4,FALSE) -> 13 | AO60: =VLOOKUP(D60,カラムID辞書!C:H,6,FALSE) -> 13 | AQ60: 価格変更による返品伝票の原価集計値
B61: =IF($D61="","",MAX(OFFSET($B$8,0,0,ROW()-ROW($B$8),2))+1) -> 54 | D61: 価格訂正返品高売価 | L61: =VLOOKUP(D61,カラムID辞書!$C$4:$D$1266,2,FALSE) -> TEISEIHENPIND_BIK | AB61: =IF(L61="DELDTE","","○") -> ○ | AE61: =IF(AB61="○",IF(AH61="timestamp","now()",IF(LEFT(AH61,9)="character","' '","0")),"") -> 0 | AH61: =VLOOKUP(D61,カラムID辞書!C:H,3,FALSE) -> numeric | AM61: =VLOOKUP(D61,カラムID辞書!C:H,4,FALSE) -> 13 | AO61: =VLOOKUP(D61,カラムID辞書!C:H,6,FALSE) -> 13 | AQ61: 価格変更による返品伝票の売価集計値
B62: =IF($D62="","",MAX(OFFSET($B$8,0,0,ROW()-ROW($B$8),2))+1) -> 55 | D62: 価格訂正返品高数量 | L62: =VLOOKUP(D62,カラムID辞書!$C$4:$D$1266,2,FALSE) -> TEISEIHENPIND_SU | AB62: =IF(L62="DELDTE","","○") -> ○ | AE62: =IF(AB62="○",IF(AH62="timestamp","now()",IF(LEFT(AH62,9)="character","' '","0")),"") -> 0 | AH62: =VLOOKUP(D62,カラムID辞書!C:H,3,FALSE) -> numeric | AM62: =VLOOKUP(D62,カラムID辞書!C:H,4,FALSE) -> 10 | AO62: =VLOOKUP(D62,カラムID辞書!C:H,6,FALSE) -> 10 | AQ62: 価格変更による返品伝票の数量集計値
B63: =IF($D63="","",MAX(OFFSET($B$8,0,0,ROW()-ROW($B$8),2))+1) -> 56 | D63: 自社値上高売価 | L63: =VLOOKUP(D63,カラムID辞書!$C$4:$D$1266,2,FALSE) -> JISHANEAGED_BIK | AB63: =IF(L63="DELDTE","","○") -> ○ | AE63: =IF(AB63="○",IF(AH63="timestamp","now()",IF(LEFT(AH63,9)="character","' '","0")),"") -> 0 | AH63: =VLOOKUP(D63,カラムID辞書!C:H,3,FALSE) -> numeric | AM63: =VLOOKUP(D63,カラムID辞書!C:H,4,FALSE) -> 13 | AO63: =VLOOKUP(D63,カラムID辞書!C:H,6,FALSE) -> 13 | AQ63: 値上伝票の売価集計値
B64: =IF($D64="","",MAX(OFFSET($B$8,0,0,ROW()-ROW($B$8),2))+1) -> 57 | D64: 自社値下高売価 | L64: =VLOOKUP(D64,カラムID辞書!$C$4:$D$1266,2,FALSE) -> JISHANESAGED_BIK | AB64: =IF(L64="DELDTE","","○") -> ○ | AE64: =IF(AB64="○",IF(AH64="timestamp","now()",IF(LEFT(AH64,9)="character","' '","0")),"") -> 0 | AH64: =VLOOKUP(D64,カラムID辞書!C:H,3,FALSE) -> numeric | AM64: =VLOOKUP(D64,カラムID辞書!C:H,4,FALSE) -> 13 | AO64: =VLOOKUP(D64,カラムID辞書!C:H,6,FALSE) -> 13 | AQ64: 値下伝票の売価集計値
B65: =IF($D65="","",MAX(OFFSET($B$8,0,0,ROW()-ROW($B$8),2))+1) -> 58 | D65: 値上高原価１ | L65: =VLOOKUP(D65,カラムID辞書!$C$4:$D$1266,2,FALSE) -> NEAGED1_GNK | AB65: =IF(L65="DELDTE","","○") -> ○ | AE65: =IF(AB65="○",IF(AH65="timestamp","now()",IF(LEFT(AH65,9)="character","' '","0")),"") -> 0 | AH65: =VLOOKUP(D65,カラムID辞書!C:H,3,FALSE) -> numeric | AM65: =VLOOKUP(D65,カラムID辞書!C:H,4,FALSE) -> 13 | AO65: =VLOOKUP(D65,カラムID辞書!C:H,6,FALSE) -> 13 | BR65: （未設定：ZERO）
B66: =IF($D66="","",MAX(OFFSET($B$8,0,0,ROW()-ROW($B$8),2))+1) -> 59 | D66: 値上高売価１ | L66: =VLOOKUP(D66,カラムID辞書!$C$4:$D$1266,2,FALSE) -> NEAGED1_BIK | AB66: =IF(L66="DELDTE","","○") -> ○ | AE66: =IF(AB66="○",IF(AH66="timestamp","now()",IF(LEFT(AH66,9)="character","' '","0")),"") -> 0 | AH66: =VLOOKUP(D66,カラムID辞書!C:H,3,FALSE) -> numeric | AM66: =VLOOKUP(D66,カラムID辞書!C:H,4,FALSE) -> 13 | AO66: =VLOOKUP(D66,カラムID辞書!C:H,6,FALSE) -> 13 | BR66: （未設定：ZERO）
B67: =IF($D67="","",MAX(OFFSET($B$8,0,0,ROW()-ROW($B$8),2))+1) -> 60 | D67: 値下高原価１ | L67: =VLOOKUP(D67,カラムID辞書!$C$4:$D$1266,2,FALSE) -> NESAGED1_GNK | AB67: =IF(L67="DELDTE","","○") -> ○ | AE67: =IF(AB67="○",IF(AH67="timestamp","now()",IF(LEFT(AH67,9)="character","' '","0")),"") -> 0 | AH67: =VLOOKUP(D67,カラムID辞書!C:H,3,FALSE) -> numeric | AM67: =VLOOKUP(D67,カラムID辞書!C:H,4,FALSE) -> 13 | AO67: =VLOOKUP(D67,カラムID辞書!C:H,6,FALSE) -> 13 | AQ67: 破損伝票の数量集計値
B68: =IF($D68="","",MAX(OFFSET($B$8,0,0,ROW()-ROW($B$8),2))+1) -> 61 | D68: 値下高売価１ | L68: =VLOOKUP(D68,カラムID辞書!$C$4:$D$1266,2,FALSE) -> NESAGED1_BIK | AB68: =IF(L68="DELDTE","","○") -> ○ | AE68: =IF(AB68="○",IF(AH68="timestamp","now()",IF(LEFT(AH68,9)="character","' '","0")),"") -> 0 | AH68: =VLOOKUP(D68,カラムID辞書!C:H,3,FALSE) -> numeric | AM68: =VLOOKUP(D68,カラムID辞書!C:H,4,FALSE) -> 13 | AO68: =VLOOKUP(D68,カラムID辞書!C:H,6,FALSE) -> 13 | AQ68: 破損伝票の売価集計値
B69: =IF($D69="","",MAX(OFFSET($B$8,0,0,ROW()-ROW($B$8),2))+1) -> 62 | D69: 値上高原価２ | L69: =VLOOKUP(D69,カラムID辞書!$C$4:$D$1266,2,FALSE) -> NEAGED2_GNK | AB69: =IF(L69="DELDTE","","○") -> ○ | AE69: =IF(AB69="○",IF(AH69="timestamp","now()",IF(LEFT(AH69,9)="character","' '","0")),"") -> 0 | AH69: =VLOOKUP(D69,カラムID辞書!C:H,3,FALSE) -> numeric | AM69: =VLOOKUP(D69,カラムID辞書!C:H,4,FALSE) -> 13 | AO69: =VLOOKUP(D69,カラムID辞書!C:H,6,FALSE) -> 13 | BR69: （未設定：ZERO）
B70: =IF($D70="","",MAX(OFFSET($B$8,0,0,ROW()-ROW($B$8),2))+1) -> 63 | D70: 値上高売価２ | L70: =VLOOKUP(D70,カラムID辞書!$C$4:$D$1266,2,FALSE) -> NEAGED2_BIK | AB70: =IF(L70="DELDTE","","○") -> ○ | AE70: =IF(AB70="○",IF(AH70="timestamp","now()",IF(LEFT(AH70,9)="character","' '","0")),"") -> 0 | AH70: =VLOOKUP(D70,カラムID辞書!C:H,3,FALSE) -> numeric | AM70: =VLOOKUP(D70,カラムID辞書!C:H,4,FALSE) -> 13 | AO70: =VLOOKUP(D70,カラムID辞書!C:H,6,FALSE) -> 13 | BR70: （未設定：ZERO）
B71: =IF($D71="","",MAX(OFFSET($B$8,0,0,ROW()-ROW($B$8),2))+1) -> 64 | D71: 値下高原価２ | L71: =VLOOKUP(D71,カラムID辞書!$C$4:$D$1266,2,FALSE) -> NESAGED2_GNK | AB71: =IF(L71="DELDTE","","○") -> ○ | AE71: =IF(AB71="○",IF(AH71="timestamp","now()",IF(LEFT(AH71,9)="character","' '","0")),"") -> 0 | AH71: =VLOOKUP(D71,カラムID辞書!C:H,3,FALSE) -> numeric | AM71: =VLOOKUP(D71,カラムID辞書!C:H,4,FALSE) -> 13 | AO71: =VLOOKUP(D71,カラムID辞書!C:H,6,FALSE) -> 13 | BR71: （未設定：ZERO）
B72: =IF($D72="","",MAX(OFFSET($B$8,0,0,ROW()-ROW($B$8),2))+1) -> 65 | D72: 値下高売価２ | L72: =VLOOKUP(D72,カラムID辞書!$C$4:$D$1266,2,FALSE) -> NESAGED2_BIK | AB72: =IF(L72="DELDTE","","○") -> ○ | AE72: =IF(AB72="○",IF(AH72="timestamp","now()",IF(LEFT(AH72,9)="character","' '","0")),"") -> 0 | AH72: =VLOOKUP(D72,カラムID辞書!C:H,3,FALSE) -> numeric | AM72: =VLOOKUP(D72,カラムID辞書!C:H,4,FALSE) -> 13 | AO72: =VLOOKUP(D72,カラムID辞書!C:H,6,FALSE) -> 13 | BR72: （未設定：ZERO）
B73: =IF($D73="","",MAX(OFFSET($B$8,0,0,ROW()-ROW($B$8),2))+1) -> 66 | D73: 店間振替高原価（払出） | L73: =VLOOKUP(D73,カラムID辞書!$C$4:$D$1266,2,FALSE) -> TNKANFURI_O_GNK | AB73: =IF(L73="DELDTE","","○") -> ○ | AE73: =IF(AB73="○",IF(AH73="timestamp","now()",IF(LEFT(AH73,9)="character","' '","0")),"") -> 0 | AH73: =VLOOKUP(D73,カラムID辞書!C:H,3,FALSE) -> numeric | AM73: =VLOOKUP(D73,カラムID辞書!C:H,4,FALSE) -> 13 | AO73: =VLOOKUP(D73,カラムID辞書!C:H,6,FALSE) -> 13 | AQ73: 店間振替伝票（払出）の原価集計値
B74: =IF($D74="","",MAX(OFFSET($B$8,0,0,ROW()-ROW($B$8),2))+1) -> 67 | D74: 店間振替高売価（払出） | L74: =VLOOKUP(D74,カラムID辞書!$C$4:$D$1266,2,FALSE) -> TNKANFURI_O_BIK | AB74: =IF(L74="DELDTE","","○") -> ○ | AE74: =IF(AB74="○",IF(AH74="timestamp","now()",IF(LEFT(AH74,9)="character","' '","0")),"") -> 0 | AH74: =VLOOKUP(D74,カラムID辞書!C:H,3,FALSE) -> numeric | AM74: =VLOOKUP(D74,カラムID辞書!C:H,4,FALSE) -> 13 | AO74: =VLOOKUP(D74,カラムID辞書!C:H,6,FALSE) -> 13 | AQ74: 店間振替伝票（払出）の売価集計値
B75: =IF($D75="","",MAX(OFFSET($B$8,0,0,ROW()-ROW($B$8),2))+1) -> 68 | D75: 店間振替高数量（払出） | L75: =VLOOKUP(D75,カラムID辞書!$C$4:$D$1266,2,FALSE) -> TNKANFURI_O_SU | AB75: =IF(L75="DELDTE","","○") -> ○ | AE75: =IF(AB75="○",IF(AH75="timestamp","now()",IF(LEFT(AH75,9)="character","' '","0")),"") -> 0 | AH75: =VLOOKUP(D75,カラムID辞書!C:H,3,FALSE) -> numeric | AM75: =VLOOKUP(D75,カラムID辞書!C:H,4,FALSE) -> 10 | AO75: =VLOOKUP(D75,カラムID辞書!C:H,6,FALSE) -> 10 | AQ75: 店間振替伝票（払出）の数量集計値
B76: =IF($D76="","",MAX(OFFSET($B$8,0,0,ROW()-ROW($B$8),2))+1) -> 69 | D76: 店間振替高原価（受入） | L76: =VLOOKUP(D76,カラムID辞書!$C$4:$D$1266,2,FALSE) -> TNKANFURI_I_GNK | AB76: =IF(L76="DELDTE","","○") -> ○ | AE76: =IF(AB76="○",IF(AH76="timestamp","now()",IF(LEFT(AH76,9)="character","' '","0")),"") -> 0 | AH76: =VLOOKUP(D76,カラムID辞書!C:H,3,FALSE) -> numeric | AM76: =VLOOKUP(D76,カラムID辞書!C:H,4,FALSE) -> 13 | AO76: =VLOOKUP(D76,カラムID辞書!C:H,6,FALSE) -> 13 | AQ76: 店間振替伝票（受入）の原価集計値
B77: =IF($D77="","",MAX(OFFSET($B$8,0,0,ROW()-ROW($B$8),2))+1) -> 70 | D77: 店間振替高売価（受入） | L77: =VLOOKUP(D77,カラムID辞書!$C$4:$D$1266,2,FALSE) -> TNKANFURI_I_BIK | AB77: =IF(L77="DELDTE","","○") -> ○ | AE77: =IF(AB77="○",IF(AH77="timestamp","now()",IF(LEFT(AH77,9)="character","' '","0")),"") -> 0 | AH77: =VLOOKUP(D77,カラムID辞書!C:H,3,FALSE) -> numeric | AM77: =VLOOKUP(D77,カラムID辞書!C:H,4,FALSE) -> 13 | AO77: =VLOOKUP(D77,カラムID辞書!C:H,6,FALSE) -> 13 | AQ77: 店間振替伝票（受入）の売価集計値
B78: =IF($D78="","",MAX(OFFSET($B$8,0,0,ROW()-ROW($B$8),2))+1) -> 71 | D78: 店間振替高数量（受入） | L78: =VLOOKUP(D78,カラムID辞書!$C$4:$D$1266,2,FALSE) -> TNKANFURI_I_SU | AB78: =IF(L78="DELDTE","","○") -> ○ | AE78: =IF(AB78="○",IF(AH78="timestamp","now()",IF(LEFT(AH78,9)="character","' '","0")),"") -> 0 | AH78: =VLOOKUP(D78,カラムID辞書!C:H,3,FALSE) -> numeric | AM78: =VLOOKUP(D78,カラムID辞書!C:H,4,FALSE) -> 10 | AO78: =VLOOKUP(D78,カラムID辞書!C:H,6,FALSE) -> 10 | AQ78: 店間振替伝票（受入）の数量集計値
B79: =IF($D79="","",MAX(OFFSET($B$8,0,0,ROW()-ROW($B$8),2))+1) -> 72 | D79: 店内振替高原価（払出） | L79: =VLOOKUP(D79,カラムID辞書!$C$4:$D$1266,2,FALSE) -> TNNAIFURI_O_GNK | AB79: =IF(L79="DELDTE","","○") -> ○ | AE79: =IF(AB79="○",IF(AH79="timestamp","now()",IF(LEFT(AH79,9)="character","' '","0")),"") -> 0 | AH79: =VLOOKUP(D79,カラムID辞書!C:H,3,FALSE) -> numeric | AM79: =VLOOKUP(D79,カラムID辞書!C:H,4,FALSE) -> 13 | AO79: =VLOOKUP(D79,カラムID辞書!C:H,6,FALSE) -> 13 | AQ79: 品番振替伝票（払出）の原価集計値
B80: =IF($D80="","",MAX(OFFSET($B$8,0,0,ROW()-ROW($B$8),2))+1) -> 73 | D80: 店内振替高売価（払出） | L80: =VLOOKUP(D80,カラムID辞書!$C$4:$D$1266,2,FALSE) -> TNNAIFURI_O_BIK | AB80: =IF(L80="DELDTE","","○") -> ○ | AE80: =IF(AB80="○",IF(AH80="timestamp","now()",IF(LEFT(AH80,9)="character","' '","0")),"") -> 0 | AH80: =VLOOKUP(D80,カラムID辞書!C:H,3,FALSE) -> numeric | AM80: =VLOOKUP(D80,カラムID辞書!C:H,4,FALSE) -> 13 | AO80: =VLOOKUP(D80,カラムID辞書!C:H,6,FALSE) -> 13 | AQ80: 品番振替伝票（払出）の売価集計値
B81: =IF($D81="","",MAX(OFFSET($B$8,0,0,ROW()-ROW($B$8),2))+1) -> 74 | D81: 店内振替高数量（払出） | L81: =VLOOKUP(D81,カラムID辞書!$C$4:$D$1266,2,FALSE) -> TNNAIFURI_O_SU | AB81: =IF(L81="DELDTE","","○") -> ○ | AE81: =IF(AB81="○",IF(AH81="timestamp","now()",IF(LEFT(AH81,9)="character","' '","0")),"") -> 0 | AH81: =VLOOKUP(D81,カラムID辞書!C:H,3,FALSE) -> numeric | AM81: =VLOOKUP(D81,カラムID辞書!C:H,4,FALSE) -> 10 | AO81: =VLOOKUP(D81,カラムID辞書!C:H,6,FALSE) -> 10 | AQ81: 品番振替伝票（払出）の数量集計値
B82: =IF($D82="","",MAX(OFFSET($B$8,0,0,ROW()-ROW($B$8),2))+1) -> 75 | D82: 店内振替高原価（受入） | L82: =VLOOKUP(D82,カラムID辞書!$C$4:$D$1266,2,FALSE) -> TNNAIFURI_I_GNK | AB82: =IF(L82="DELDTE","","○") -> ○ | AE82: =IF(AB82="○",IF(AH82="timestamp","now()",IF(LEFT(AH82,9)="character","' '","0")),"") -> 0 | AH82: =VLOOKUP(D82,カラムID辞書!C:H,3,FALSE) -> numeric | AM82: =VLOOKUP(D82,カラムID辞書!C:H,4,FALSE) -> 13 | AO82: =VLOOKUP(D82,カラムID辞書!C:H,6,FALSE) -> 13 | AQ82: 品番振替伝票（受入）の原価集計値
B83: =IF($D83="","",MAX(OFFSET($B$8,0,0,ROW()-ROW($B$8),2))+1) -> 76 | D83: 店内振替高売価（受入） | L83: =VLOOKUP(D83,カラムID辞書!$C$4:$D$1266,2,FALSE) -> TNNAIFURI_I_BIK | AB83: =IF(L83="DELDTE","","○") -> ○ | AE83: =IF(AB83="○",IF(AH83="timestamp","now()",IF(LEFT(AH83,9)="character","' '","0")),"") -> 0 | AH83: =VLOOKUP(D83,カラムID辞書!C:H,3,FALSE) -> numeric | AM83: =VLOOKUP(D83,カラムID辞書!C:H,4,FALSE) -> 13 | AO83: =VLOOKUP(D83,カラムID辞書!C:H,6,FALSE) -> 13 | AQ83: 品番振替伝票（受入）の売価集計値
B84: =IF($D84="","",MAX(OFFSET($B$8,0,0,ROW()-ROW($B$8),2))+1) -> 77 | D84: 店内振替高数量（受入） | L84: =VLOOKUP(D84,カラムID辞書!$C$4:$D$1266,2,FALSE) -> TNNAIFURI_I_SU | AB84: =IF(L84="DELDTE","","○") -> ○ | AE84: =IF(AB84="○",IF(AH84="timestamp","now()",IF(LEFT(AH84,9)="character","' '","0")),"") -> 0 | AH84: =VLOOKUP(D84,カラムID辞書!C:H,3,FALSE) -> numeric | AM84: =VLOOKUP(D84,カラムID辞書!C:H,4,FALSE) -> 10 | AO84: =VLOOKUP(D84,カラムID辞書!C:H,6,FALSE) -> 10 | AQ84: 品番振替伝票（受入）の数量集計値
B85: =IF($D85="","",MAX(OFFSET($B$8,0,0,ROW()-ROW($B$8),2))+1) -> 78 | D85: 商品振替高原価（払出） | L85: =VLOOKUP(D85,カラムID辞書!$C$4:$D$1266,2,FALSE) -> SHOHNFURI_O_GNK | AB85: =IF(L85="DELDTE","","○") -> ○ | AE85: =IF(AB85="○",IF(AH85="timestamp","now()",IF(LEFT(AH85,9)="character","' '","0")),"") -> 0 | AH85: =VLOOKUP(D85,カラムID辞書!C:H,3,FALSE) -> numeric | AM85: =VLOOKUP(D85,カラムID辞書!C:H,4,FALSE) -> 13 | AO85: =VLOOKUP(D85,カラムID辞書!C:H,6,FALSE) -> 13 | BR85: （未設定：ZERO）
B86: =IF($D86="","",MAX(OFFSET($B$8,0,0,ROW()-ROW($B$8),2))+1) -> 79 | D86: 商品振替高売価（払出） | L86: =VLOOKUP(D86,カラムID辞書!$C$4:$D$1266,2,FALSE) -> SHOHNFURI_O_BIK | AB86: =IF(L86="DELDTE","","○") -> ○ | AE86: =IF(AB86="○",IF(AH86="timestamp","now()",IF(LEFT(AH86,9)="character","' '","0")),"") -> 0 | AH86: =VLOOKUP(D86,カラムID辞書!C:H,3,FALSE) -> numeric | AM86: =VLOOKUP(D86,カラムID辞書!C:H,4,FALSE) -> 13 | AO86: =VLOOKUP(D86,カラムID辞書!C:H,6,FALSE) -> 13 | BR86: （未設定：ZERO）
B87: =IF($D87="","",MAX(OFFSET($B$8,0,0,ROW()-ROW($B$8),2))+1) -> 80 | D87: 商品振替高数量（払出） | L87: =VLOOKUP(D87,カラムID辞書!$C$4:$D$1266,2,FALSE) -> SHOHNFURI_O_SU | AB87: =IF(L87="DELDTE","","○") -> ○ | AE87: =IF(AB87="○",IF(AH87="timestamp","now()",IF(LEFT(AH87,9)="character","' '","0")),"") -> 0 | AH87: =VLOOKUP(D87,カラムID辞書!C:H,3,FALSE) -> numeric | AM87: =VLOOKUP(D87,カラムID辞書!C:H,4,FALSE) -> 10 | AO87: =VLOOKUP(D87,カラムID辞書!C:H,6,FALSE) -> 10 | BR87: （未設定：ZERO）
B88: =IF($D88="","",MAX(OFFSET($B$8,0,0,ROW()-ROW($B$8),2))+1) -> 81 | D88: 商品振替高原価（受入） | L88: =VLOOKUP(D88,カラムID辞書!$C$4:$D$1266,2,FALSE) -> SHOHNFURI_I_GNK | AB88: =IF(L88="DELDTE","","○") -> ○ | AE88: =IF(AB88="○",IF(AH88="timestamp","now()",IF(LEFT(AH88,9)="character","' '","0")),"") -> 0 | AH88: =VLOOKUP(D88,カラムID辞書!C:H,3,FALSE) -> numeric | AM88: =VLOOKUP(D88,カラムID辞書!C:H,4,FALSE) -> 13 | AO88: =VLOOKUP(D88,カラムID辞書!C:H,6,FALSE) -> 13 | BR88: （未設定：ZERO）
B89: =IF($D89="","",MAX(OFFSET($B$8,0,0,ROW()-ROW($B$8),2))+1) -> 82 | D89: 商品振替高売価（受入） | L89: =VLOOKUP(D89,カラムID辞書!$C$4:$D$1266,2,FALSE) -> SHOHNFURI_I_BIK | AB89: =IF(L89="DELDTE","","○") -> ○ | AE89: =IF(AB89="○",IF(AH89="timestamp","now()",IF(LEFT(AH89,9)="character","' '","0")),"") -> 0 | AH89: =VLOOKUP(D89,カラムID辞書!C:H,3,FALSE) -> numeric | AM89: =VLOOKUP(D89,カラムID辞書!C:H,4,FALSE) -> 13 | AO89: =VLOOKUP(D89,カラムID辞書!C:H,6,FALSE) -> 13 | BR89: （未設定：ZERO）
B90: =IF($D90="","",MAX(OFFSET($B$8,0,0,ROW()-ROW($B$8),2))+1) -> 83 | D90: 商品振替高数量（受入） | L90: =VLOOKUP(D90,カラムID辞書!$C$4:$D$1266,2,FALSE) -> SHOHNFURI_I_SU | AB90: =IF(L90="DELDTE","","○") -> ○ | AE90: =IF(AB90="○",IF(AH90="timestamp","now()",IF(LEFT(AH90,9)="character","' '","0")),"") -> 0 | AH90: =VLOOKUP(D90,カラムID辞書!C:H,3,FALSE) -> numeric | AM90: =VLOOKUP(D90,カラムID辞書!C:H,4,FALSE) -> 10 | AO90: =VLOOKUP(D90,カラムID辞書!C:H,6,FALSE) -> 10 | BR90: （未設定：ZERO）
B91: =IF($D91="","",MAX(OFFSET($B$8,0,0,ROW()-ROW($B$8),2))+1) -> 84 | D91: リベート | L91: =VLOOKUP(D91,カラムID辞書!$C$4:$D$1266,2,FALSE) -> REBATE | AB91: =IF(L91="DELDTE","","○") -> ○ | AE91: =IF(AB91="○",IF(AH91="timestamp","now()",IF(LEFT(AH91,9)="character","' '","0")),"") -> 0 | AH91: =VLOOKUP(D91,カラムID辞書!C:H,3,FALSE) -> numeric | AM91: =VLOOKUP(D91,カラムID辞書!C:H,4,FALSE) -> 13 | AO91: =VLOOKUP(D91,カラムID辞書!C:H,6,FALSE) -> 13 | BR91: （未設定：ZERO）
B92: =IF($D92="","",MAX(OFFSET($B$8,0,0,ROW()-ROW($B$8),2))+1) -> 85 | D92: リベート返金 | L92: =VLOOKUP(D92,カラムID辞書!$C$4:$D$1266,2,FALSE) -> REBATE_HENKIN | AB92: =IF(L92="DELDTE","","○") -> ○ | AE92: =IF(AB92="○",IF(AH92="timestamp","now()",IF(LEFT(AH92,9)="character","' '","0")),"") -> 0 | AH92: =VLOOKUP(D92,カラムID辞書!C:H,3,FALSE) -> numeric | AM92: =VLOOKUP(D92,カラムID辞書!C:H,4,FALSE) -> 13 | AO92: =VLOOKUP(D92,カラムID辞書!C:H,6,FALSE) -> 13 | BR92: （未設定：ZERO）
B93: =IF($D93="","",MAX(OFFSET($B$8,0,0,ROW()-ROW($B$8),2))+1) -> 86 | D93: 予備原価１ | L93: =VLOOKUP(D93,カラムID辞書!$C$4:$D$1266,2,FALSE) -> RSV_GNK1 | AB93: =IF(L93="DELDTE","","○") -> ○ | AE93: =IF(AB93="○",IF(AH93="timestamp","now()",IF(LEFT(AH93,9)="character","' '","0")),"") -> 0 | AH93: =VLOOKUP(D93,カラムID辞書!C:H,3,FALSE) -> numeric | AM93: =VLOOKUP(D93,カラムID辞書!C:H,4,FALSE) -> 13 | AO93: =VLOOKUP(D93,カラムID辞書!C:H,6,FALSE) -> 13 | BR93: （未設定：ZERO）
B94: =IF($D94="","",MAX(OFFSET($B$8,0,0,ROW()-ROW($B$8),2))+1) -> 87 | D94: 予備売価１ | L94: =VLOOKUP(D94,カラムID辞書!$C$4:$D$1266,2,FALSE) -> RSV_BIK1 | AB94: =IF(L94="DELDTE","","○") -> ○ | AE94: =IF(AB94="○",IF(AH94="timestamp","now()",IF(LEFT(AH94,9)="character","' '","0")),"") -> 0 | AH94: =VLOOKUP(D94,カラムID辞書!C:H,3,FALSE) -> numeric | AM94: =VLOOKUP(D94,カラムID辞書!C:H,4,FALSE) -> 13 | AO94: =VLOOKUP(D94,カラムID辞書!C:H,6,FALSE) -> 13 | BR94: （未設定：ZERO）
B95: =IF($D95="","",MAX(OFFSET($B$8,0,0,ROW()-ROW($B$8),2))+1) -> 88 | D95: 予備数量１ | L95: =VLOOKUP(D95,カラムID辞書!$C$4:$D$1266,2,FALSE) -> RSV_SU1 | AB95: =IF(L95="DELDTE","","○") -> ○ | AE95: =IF(AB95="○",IF(AH95="timestamp","now()",IF(LEFT(AH95,9)="character","' '","0")),"") -> 0 | AH95: =VLOOKUP(D95,カラムID辞書!C:H,3,FALSE) -> numeric | AM95: =VLOOKUP(D95,カラムID辞書!C:H,4,FALSE) -> 10 | AO95: =VLOOKUP(D95,カラムID辞書!C:H,6,FALSE) -> 10 | BR95: （未設定：ZERO）
B96: =IF($D96="","",MAX(OFFSET($B$8,0,0,ROW()-ROW($B$8),2))+1) -> 89 | D96: 予備原価２ | L96: =VLOOKUP(D96,カラムID辞書!$C$4:$D$1266,2,FALSE) -> RSV_GNK2 | AB96: =IF(L96="DELDTE","","○") -> ○ | AE96: =IF(AB96="○",IF(AH96="timestamp","now()",IF(LEFT(AH96,9)="character","' '","0")),"") -> 0 | AH96: =VLOOKUP(D96,カラムID辞書!C:H,3,FALSE) -> numeric | AM96: =VLOOKUP(D96,カラムID辞書!C:H,4,FALSE) -> 13 | AO96: =VLOOKUP(D96,カラムID辞書!C:H,6,FALSE) -> 13 | BR96: （未設定：ZERO）
... B122: =IF($D122="","",MAX(OFFSET($B$8,0,0,ROW()-ROW($B$8),2))+1) -> 115 | D122: 予備数量１０ | L122: =VLOOKUP(D122,カラムID辞書!$C$4:$D$1266,2,FALSE) -> RSV_SU10 | AB122: =IF(L122="DELDTE","","○") -> ○ | AE122: =IF(AB122="○",IF(AH122="timestamp","now()",IF(LEFT(AH122,9)="character","' '","0")),"") -> 0 | AH122: =VLOOKUP(D122,カラムID辞書!C:H,3,FALSE) -> numeric | AM122: =VLOOKUP(D122,カラムID辞書!C:H,4,FALSE) -> 10 | AO122: =VLOOKUP(D122,カラムID辞書!C:H,6,FALSE) -> 10 | BR122: （未設定：ZERO）
B123: =IF($D123="","",MAX(OFFSET($B$8,0,0,ROW()-ROW($B$8),2))+1) -> 116 | D123: 月初在高原価 | L123: =VLOOKUP(D123,カラムID辞書!$C$4:$D$1266,2,FALSE) -> GESSHOZAID_GNK | AB123: =IF(L123="DELDTE","","○") -> ○ | AE123: =IF(AB123="○",IF(AH123="timestamp","now()",IF(LEFT(AH123,9)="character","' '","0")),"") -> 0 | AH123: =VLOOKUP(D123,カラムID辞書!C:H,3,FALSE) -> numeric | AM123: =VLOOKUP(D123,カラムID辞書!C:H,4,FALSE) -> 13 | AO123: =VLOOKUP(D123,カラムID辞書!C:H,6,FALSE) -> 13 | AQ123: 別紙「商品勘定利益計算」参照
B124: =IF($D124="","",MAX(OFFSET($B$8,0,0,ROW()-ROW($B$8),2))+1) -> 117 | D124: 月初在高売価 | L124: =VLOOKUP(D124,カラムID辞書!$C$4:$D$1266,2,FALSE) -> GESSHOZAID_BIK | AB124: =IF(L124="DELDTE","","○") -> ○ | AE124: =IF(AB124="○",IF(AH124="timestamp","now()",IF(LEFT(AH124,9)="character","' '","0")),"") -> 0 | AH124: =VLOOKUP(D124,カラムID辞書!C:H,3,FALSE) -> numeric | AM124: =VLOOKUP(D124,カラムID辞書!C:H,4,FALSE) -> 13 | AO124: =VLOOKUP(D124,カラムID辞書!C:H,6,FALSE) -> 13 | AQ124: 別紙「商品勘定利益計算」参照
B125: =IF($D125="","",MAX(OFFSET($B$8,0,0,ROW()-ROW($B$8),2))+1) -> 118 | D125: 月初在高数量 | L125: =VLOOKUP(D125,カラムID辞書!$C$4:$D$1266,2,FALSE) -> GESSHOZAID_SU | AB125: =IF(L125="DELDTE","","○") -> ○ | AE125: =IF(AB125="○",IF(AH125="timestamp","now()",IF(LEFT(AH125,9)="character","' '","0")),"") -> 0 | AH125: =VLOOKUP(D125,カラムID辞書!C:H,3,FALSE) -> numeric | AM125: =VLOOKUP(D125,カラムID辞書!C:H,4,FALSE) -> 10 | AO125: =VLOOKUP(D125,カラムID辞書!C:H,6,FALSE) -> 10 | AQ125: 別紙「商品勘定利益計算」参照
B126: =IF($D126="","",MAX(OFFSET($B$8,0,0,ROW()-ROW($B$8),2))+1) -> 119 | D126: 月央在高原価 | L126: =VLOOKUP(D126,カラムID辞書!$C$4:$D$1266,2,FALSE) -> GETSUOZAID_GNK | AB126: =IF(L126="DELDTE","","○") -> ○ | AE126: =IF(AB126="○",IF(AH126="timestamp","now()",IF(LEFT(AH126,9)="character","' '","0")),"") -> 0 | AH126: =VLOOKUP(D126,カラムID辞書!C:H,3,FALSE) -> numeric | AM126: =VLOOKUP(D126,カラムID辞書!C:H,4,FALSE) -> 13 | AO126: =VLOOKUP(D126,カラムID辞書!C:H,6,FALSE) -> 13 | AQ126: 別紙「商品勘定利益計算」参照
B127: =IF($D127="","",MAX(OFFSET($B$8,0,0,ROW()-ROW($B$8),2))+1) -> 120 | D127: 月央在高売価 | L127: =VLOOKUP(D127,カラムID辞書!$C$4:$D$1266,2,FALSE) -> GETSUOZAID_BIK | AB127: =IF(L127="DELDTE","","○") -> ○ | AE127: =IF(AB127="○",IF(AH127="timestamp","now()",IF(LEFT(AH127,9)="character","' '","0")),"") -> 0 | AH127: =VLOOKUP(D127,カラムID辞書!C:H,3,FALSE) -> numeric | AM127: =VLOOKUP(D127,カラムID辞書!C:H,4,FALSE) -> 13 | AO127: =VLOOKUP(D127,カラムID辞書!C:H,6,FALSE) -> 13 | AQ127: 別紙「商品勘定利益計算」参照
B128: =IF($D128="","",MAX(OFFSET($B$8,0,0,ROW()-ROW($B$8),2))+1) -> 121 | D128: 月央在高数量 | L128: =VLOOKUP(D128,カラムID辞書!$C$4:$D$1266,2,FALSE) -> GETSUOZAID_SU | AB128: =IF(L128="DELDTE","","○") -> ○ | AE128: =IF(AB128="○",IF(AH128="timestamp","now()",IF(LEFT(AH128,9)="character","' '","0")),"") -> 0 | AH128: =VLOOKUP(D128,カラムID辞書!C:H,3,FALSE) -> numeric | AM128: =VLOOKUP(D128,カラムID辞書!C:H,4,FALSE) -> 10 | AO128: =VLOOKUP(D128,カラムID辞書!C:H,6,FALSE) -> 10 | AQ128: 別紙「商品勘定利益計算」参照
...

Sheet 売価還元単位別期別実績
B2: ユーザインタフェース 設計書 | J2: サブシステム分類 | O2: ドキュメント ID | T2: ドキュメント名 | BK2: 更新者 | BN2: 最終更新日 | BR2: 履歴 | BT2: 作成者 | BW2: 作成日
J3: 商品勘定 | O3: 2.04 | T3: テーブル定義 | BR3: 第1版 | BT3: 富士通 | BW3: 42917
B5: 概念データ名／ID | J5: 売価還元単位別期別実績テーブル | U5: ／ | V5: LBT03_BAIKAN_K | AD5: OID | AK5: 最大レコード長 | AR5: =ROUNDUP((27+ROUNDUP((MAX(B:B)-COUNTIF(AB:AB,"○"))/8,0)+IF(AF5="",0,4))/8,0)*8+SUM(AO8:AO1034) -> 1828 | AU5: Byte | AW5: 用途 | BB5: 商品勘定実績を期単位で管理する。
B7: 項番 | D7: 項目論理名称 | L7: 項目物理名称 | T7: PKey | V7: IDX1 | X7: IDX2 | Z7: IDX3 | AB7: NOTNULL | AE7: DEFAULT | AH7: Type | AM7: 桁数 | AO7: Byte | AQ7: 項目説明 | BR7: 備考
B8: 1 | D8: 期 | L8: =VLOOKUP(D8,カラムID辞書!$C$4:$D$1266,2,FALSE) -> NENKI | T8: 1 | AB8: =IF(L8="DELDTE","","○") -> ○ | AE8: =IF(AB8="○",IF(AH8="timestamp","now()",IF(LEFT(AH8,9)="character","' '","0")),"") -> 0 | AH8: =VLOOKUP(D8,カラムID辞書!C:H,3,FALSE) -> numeric | AM8: =VLOOKUP(D8,カラムID辞書!C:H,4,FALSE) -> 6 | AO8: =VLOOKUP(D8,カラムID辞書!C:H,6,FALSE) -> 6 | AQ8: 伝票計上日に該当する期首月（YYYYMM）
B9: =IF($D9="","",MAX(OFFSET($B$8,0,0,ROW()-ROW($B$8),2))+1) -> 2 | D9: システムグループコード | L9: =VLOOKUP(D9,カラムID辞書!$C$4:$D$1266,2,FALSE) -> SYSGRPCD | T9: 2 | AB9: =IF(L9="DELDTE","","○") -> ○ | AE9: =IF(AB9="○",IF(AH9="timestamp","now()",IF(LEFT(AH9,9)="character","' '","0")),"") -> ' ' | AH9: =VLOOKUP(D9,カラムID辞書!C:H,3,FALSE) -> character varying | AM9: =VLOOKUP(D9,カラムID辞書!C:H,4,FALSE) -> 4 | AO9: =VLOOKUP(D9,カラムID辞書!C:H,6,FALSE) -> 4 | AQ9: ユーザ分類コード | BR9: "0010"固定
B10: =IF($D10="","",MAX(OFFSET($B$8,0,0,ROW()-ROW($B$8),2))+1) -> 3 | D10: 企業グループコード | L10: =VLOOKUP(D10,カラムID辞書!$C$4:$D$1266,2,FALSE) -> KGYGRPCD | T10: 3 | AB10: =IF(L10="DELDTE","","○") -> ○ | AE10: =IF(AB10="○",IF(AH10="timestamp","now()",IF(LEFT(AH10,9)="character","' '","0")),"") -> ' ' | AH10: =VLOOKUP(D10,カラムID辞書!C:H,3,FALSE) -> character varying | AM10: =VLOOKUP(D10,カラムID辞書!C:H,4,FALSE) -> 3 | AO10: =VLOOKUP(D10,カラムID辞書!C:H,6,FALSE) -> 3 | AQ10: 売上、仕入伝票の企業グループコード
B11: =IF($D11="","",MAX(OFFSET($B$8,0,0,ROW()-ROW($B$8),2))+1) -> 4 | D11: 店コード | L11: =VLOOKUP(D11,カラムID辞書!$C$4:$D$1266,2,FALSE) -> TENCD | T11: 4 | AB11: =IF(L11="DELDTE","","○") -> ○ | AE11: =IF(AB11="○",IF(AH11="timestamp","now()",IF(LEFT(AH11,9)="character","' '","0")),"") -> ' ' | AH11: =VLOOKUP(D11,カラムID辞書!C:H,3,FALSE) -> character varying | AM11: =VLOOKUP(D11,カラムID辞書!C:H,4,FALSE) -> 4 | AO11: =VLOOKUP(D11,カラムID辞書!C:H,6,FALSE) -> 4 | AQ11: 売上、仕入伝票の店コード
B12: =IF($D12="","",MAX(OFFSET($B$8,0,0,ROW()-ROW($B$8),2))+1) -> 5 | D12: 商品コード１ | L12: =VLOOKUP(D12,カラムID辞書!$C$4:$D$1266,2,FALSE) -> SHOHINCD1 | T12: 5 | AB12: =IF(L12="DELDTE","","○") -> ○ | AE12: =IF(AB12="○",IF(AH12="timestamp","now()",IF(LEFT(AH12,9)="character","' '","0")),"") -> ' ' | AH12: =VLOOKUP(D12,カラムID辞書!C:H,3,FALSE) -> character varying | AM12: =VLOOKUP(D12,カラムID辞書!C:H,4,FALSE) -> 6 | AO12: =VLOOKUP(D12,カラムID辞書!C:H,6,FALSE) -> 6 | AQ12: 売上、仕入伝票の商品コード１ | BR12: 品番
B13: =IF($D13="","",MAX(OFFSET($B$8,0,0,ROW()-ROW($B$8),2))+1) -> 6 | D13: 商品コード２ | L13: =VLOOKUP(D13,カラムID辞書!$C$4:$D$1266,2,FALSE) -> SHOHINCD2 | T13: 6 | AB13: =IF(L13="DELDTE","","○") -> ○ | AE13: =IF(AB13="○",IF(AH13="timestamp","now()",IF(LEFT(AH13,9)="character","' '","0")),"") -> ' ' | AH13: =VLOOKUP(D13,カラムID辞書!C:H,3,FALSE) -> character varying | AM13: =VLOOKUP(D13,カラムID辞書!C:H,4,FALSE) -> 6 | AO13: =VLOOKUP(D13,カラムID辞書!C:H,6,FALSE) -> 6 | AQ13: 売上、仕入伝票の商品コード２ | BR13: （未設定）
B14: =IF($D14="","",MAX(OFFSET($B$8,0,0,ROW()-ROW($B$8),2))+1) -> 7 | D14: 商品コード３ | L14: =VLOOKUP(D14,カラムID辞書!$C$4:$D$1266,2,FALSE) -> SHOHINCD3 | T14: 7 | AB14: =IF(L14="DELDTE","","○") -> ○ | AE14: =IF(AB14="○",IF(AH14="timestamp","now()",IF(LEFT(AH14,9)="character","' '","0")),"") -> ' ' | AH14: =VLOOKUP(D14,カラムID辞書!C:H,3,FALSE) -> character varying | AM14: =VLOOKUP(D14,カラムID辞書!C:H,4,FALSE) -> 6 | AO14: =VLOOKUP(D14,カラムID辞書!C:H,6,FALSE) -> 6 | AQ14: 売上、仕入伝票の商品コード３ | BR14: （未設定）
B15: =IF($D15="","",MAX(OFFSET($B$8,0,0,ROW()-ROW($B$8),2))+1) -> 8 | D15: 商品コード４ | L15: =VLOOKUP(D15,カラムID辞書!$C$4:$D$1266,2,FALSE) -> SHOHINCD4 | T15: 8 | AB15: =IF(L15="DELDTE","","○") -> ○ | AE15: =IF(AB15="○",IF(AH15="timestamp","now()",IF(LEFT(AH15,9)="character","' '","0")),"") -> ' ' | AH15: =VLOOKUP(D15,カラムID辞書!C:H,3,FALSE) -> character varying | AM15: =VLOOKUP(D15,カラムID辞書!C:H,4,FALSE) -> 6 | AO15: =VLOOKUP(D15,カラムID辞書!C:H,6,FALSE) -> 6 | AQ15: 売上、仕入伝票の商品コード４ | BR15: （未設定）
B16: =IF($D16="","",MAX(OFFSET($B$8,0,0,ROW()-ROW($B$8),2))+1) -> 9 | D16: 商品コード５ | L16: =VLOOKUP(D16,カラムID辞書!$C$4:$D$1266,2,FALSE) -> SHOHINCD5 | T16: 9 | AB16: =IF(L16="DELDTE","","○") -> ○ | AE16: =IF(AB16="○",IF(AH16="timestamp","now()",IF(LEFT(AH16,9)="character","' '","0")),"") -> ' ' | AH16: =VLOOKUP(D16,カラムID辞書!C:H,3,FALSE) -> character varying | AM16: =VLOOKUP(D16,カラムID辞書!C:H,4,FALSE) -> 6 | AO16: =VLOOKUP(D16,カラムID辞書!C:H,6,FALSE) -> 6 | AQ16: 売上、仕入伝票の商品コード５ | BR16: （未設定）
B17: =IF($D17="","",MAX(OFFSET($B$8,0,0,ROW()-ROW($B$8),2))+1) -> 10 | D17: 細別コード１ | L17: =VLOOKUP(D17,カラムID辞書!$C$4:$D$1266,2,FALSE) -> SIBTCD1 | T17: 10 | AB17: =IF(L17="DELDTE","","○") -> ○ | AE17: =IF(AB17="○",IF(AH17="timestamp","now()",IF(LEFT(AH17,9)="character","' '","0")),"") -> ' ' | AH17: =VLOOKUP(D17,カラムID辞書!C:H,3,FALSE) -> character varying | AM17: =VLOOKUP(D17,カラムID辞書!C:H,4,FALSE) -> 10 | AO17: =VLOOKUP(D17,カラムID辞書!C:H,6,FALSE) -> 10 | AQ17: 売上、仕入伝票の細別コード１ | BR17: （未設定）
B18: =IF($D18="","",MAX(OFFSET($B$8,0,0,ROW()-ROW($B$8),2))+1) -> 11 | D18: 細別コード２ | L18: =VLOOKUP(D18,カラムID辞書!$C$4:$D$1266,2,FALSE) -> SIBTCD2 | T18: 11 | AB18: =IF(L18="DELDTE","","○") -> ○ | AE18: =IF(AB18="○",IF(AH18="timestamp","now()",IF(LEFT(AH18,9)="character","' '","0")),"") -> ' ' | AH18: =VLOOKUP(D18,カラムID辞書!C:H,3,FALSE) -> character varying | AM18: =VLOOKUP(D18,カラムID辞書!C:H,4,FALSE) -> 10 | AO18: =VLOOKUP(D18,カラムID辞書!C:H,6,FALSE) -> 10 | AQ18: 売上、仕入伝票の細別コード２ | BR18: （未設定）
B19: =IF($D19="","",MAX(OFFSET($B$8,0,0,ROW()-ROW($B$8),2))+1) -> 12 | D19: 単品コード１ | L19: =VLOOKUP(D19,カラムID辞書!$C$4:$D$1266,2,FALSE) -> TNPNCD1 | T19: 12 | AB19: =IF(L19="DELDTE","","○") -> ○ | AE19: =IF(AB19="○",IF(AH19="timestamp","now()",IF(LEFT(AH19,9)="character","' '","0")),"") -> ' ' | AH19: =VLOOKUP(D19,カラムID辞書!C:H,3,FALSE) -> character varying | AM19: =VLOOKUP(D19,カラムID辞書!C:H,4,FALSE) -> 13 | AO19: =VLOOKUP(D19,カラムID辞書!C:H,6,FALSE) -> 13 | AQ19: 売上、仕入伝票の単品コード１ | BR19: （未設定）
B20: =IF($D20="","",MAX(OFFSET($B$8,0,0,ROW()-ROW($B$8),2))+1) -> 13 | D20: 単品コード２ | L20: =VLOOKUP(D20,カラムID辞書!$C$4:$D$1266,2,FALSE) -> TNPNCD2 | T20: 13 | AB20: =IF(L20="DELDTE","","○") -> ○ | AE20: =IF(AB20="○",IF(AH20="timestamp","now()",IF(LEFT(AH20,9)="character","' '","0")),"") -> ' ' | AH20: =VLOOKUP(D20,カラムID辞書!C:H,3,FALSE) -> character varying | AM20: =VLOOKUP(D20,カラムID辞書!C:H,4,FALSE) -> 13 | AO20: =VLOOKUP(D20,カラムID辞書!C:H,6,FALSE) -> 13 | AQ20: 売上、仕入伝票の単品コード２ | BR20: （未設定）
B21: =IF($D21="","",MAX(OFFSET($B$8,0,0,ROW()-ROW($B$8),2))+1) -> 14 | D21: 仕入区分 | L21: =VLOOKUP(D21,カラムID辞書!$C$4:$D$1266,2,FALSE) -> SHIIREKBN | T21: 14 | AB21: =IF(L21="DELDTE","","○") -> ○ | AE21: =IF(AB21="○",IF(AH21="timestamp","now()",IF(LEFT(AH21,9)="character","' '","0")),"") -> ' ' | AH21: =VLOOKUP(D21,カラムID辞書!C:H,3,FALSE) -> character varying | AM21: =VLOOKUP(D21,カラムID辞書!C:H,4,FALSE) -> 2 | AO21: =VLOOKUP(D21,カラムID辞書!C:H,6,FALSE) -> 2 | AQ21: 01：直扱 / 04：売仕
B22: =IF($D22="","",MAX(OFFSET($B$8,0,0,ROW()-ROW($B$8),2))+1) -> 15 | D22: 原価管理区分 | L22: =VLOOKUP(D22,カラムID辞書!$C$4:$D$1266,2,FALSE) -> GNKKBN | T22: 15 | AB22: =IF(L22="DELDTE","","○") -> ○ | AE22: =IF(AB22="○",IF(AH22="timestamp","now()",IF(LEFT(AH22,9)="character","' '","0")),"") -> ' ' | AH22: =VLOOKUP(D22,カラムID辞書!C:H,3,FALSE) -> character varying | AM22: =VLOOKUP(D22,カラムID辞書!C:H,4,FALSE) -> 1 | AO22: =VLOOKUP(D22,カラムID辞書!C:H,6,FALSE) -> 1 | AQ22: 1：売価品 / 2：原価品
B23: =IF($D23="","",MAX(OFFSET($B$8,0,0,ROW()-ROW($B$8),2))+1) -> 16 | D23: ＤＳ区分 | L23: =VLOOKUP(D23,カラムID辞書!$C$4:$D$1266,2,FALSE) -> DSKBN | T23: 16 | AB23: =IF(L23="DELDTE","","○") -> ○ | AE23: =IF(AB23="○",IF(AH23="timestamp","now()",IF(LEFT(AH23,9)="character","' '","0")),"") -> ' ' | AH23: =VLOOKUP(D23,カラムID辞書!C:H,3,FALSE) -> character varying | AM23: =VLOOKUP(D23,カラムID辞書!C:H,4,FALSE) -> 1 | AO23: =VLOOKUP(D23,カラムID辞書!C:H,6,FALSE) -> 1 | AQ23: 0：プロパー / 1：セール
B24: =IF($D24="","",MAX(OFFSET($B$8,0,0,ROW()-ROW($B$8),2))+1) -> 17 | D24: 利益計算式区分 | L24: =VLOOKUP(D24,カラムID辞書!$C$4:$D$1266,2,FALSE) -> RIEKICMPKBN | T24: 17 | AB24: =IF(L24="DELDTE","","○") -> ○ | AE24: =IF(AB24="○",IF(AH24="timestamp","now()",IF(LEFT(AH24,9)="character","' '","0")),"") -> ' ' | AH24: =VLOOKUP(D24,カラムID辞書!C:H,3,FALSE) -> character varying | AM24: =VLOOKUP(D24,カラムID辞書!C:H,4,FALSE) -> 1 | AO24: =VLOOKUP(D24,カラムID辞書!C:H,6,FALSE) -> 1 | AQ24: 0：利益計算対象外 / 1：売価還元原価法 / 3：売仕原価計算 /7：原価品計算
B25: =IF($D25="","",MAX(OFFSET($B$8,0,0,ROW()-ROW($B$8),2))+1) -> 18 | D25: 年 | L25: =VLOOKUP(D25,カラムID辞書!$C$4:$D$1266,2,FALSE) -> NENDO | AB25: =IF(L25="DELDTE","","○") -> ○ | AE25: =IF(AB25="○",IF(AH25="timestamp","now()",IF(LEFT(AH25,9)="character","' '","0")),"") -> 0 | AH25: =VLOOKUP(D25,カラムID辞書!C:H,3,FALSE) -> numeric | AM25: =VLOOKUP(D25,カラムID辞書!C:H,4,FALSE) -> 6 | AO25: =VLOOKUP(D25,カラムID辞書!C:H,6,FALSE) -> 6 | AQ25: 「期」に該当する年度開始月（YYYYMM）
B26: =IF($D26="","",MAX(OFFSET($B$8,0,0,ROW()-ROW($B$8),2))+1) -> 19 | D26: 売上高原価 | L26: =VLOOKUP(D26,カラムID辞書!$C$4:$D$1266,2,FALSE) -> URIAGED_GNK | AB26: =IF(L26="DELDTE","","○") -> ○ | AE26: =IF(AB26="○",IF(AH26="timestamp","now()",IF(LEFT(AH26,9)="character","' '","0")),"") -> 0 | AH26: =VLOOKUP(D26,カラムID辞書!C:H,3,FALSE) -> numeric | AM26: =VLOOKUP(D26,カラムID辞書!C:H,4,FALSE) -> 13 | AO26: =VLOOKUP(D26,カラムID辞書!C:H,6,FALSE) -> 13 | AQ26: 別紙「商品勘定利益計算」参照
B27: =IF($D27="","",MAX(OFFSET($B$8,0,0,ROW()-ROW($B$8),2))+1) -> 20 | D27: 売上高売価 | L27: =VLOOKUP(D27,カラムID辞書!$C$4:$D$1266,2,FALSE) -> URIAGED_BIK | AB27: =IF(L27="DELDTE","","○") -> ○ | AE27: =IF(AB27="○",IF(AH27="timestamp","now()",IF(LEFT(AH27,9)="character","' '","0")),"") -> 0 | AH27: =VLOOKUP(D27,カラムID辞書!C:H,3,FALSE) -> numeric | AM27: =VLOOKUP(D27,カラムID辞書!C:H,4,FALSE) -> 13 | AO27: =VLOOKUP(D27,カラムID辞書!C:H,6,FALSE) -> 13 | AQ27: 売上伝票の売上高集計値（総売上高）
B28: =IF($D28="","",MAX(OFFSET($B$8,0,0,ROW()-ROW($B$8),2))+1) -> 21 | D28: 売上高分類１ | L28: =VLOOKUP(D28,カラムID辞書!$C$4:$D$1266,2,FALSE) -> URIAGED_BNRI1 | AB28: =IF(L28="DELDTE","","○") -> ○ | AE28: =IF(AB28="○",IF(AH28="timestamp","now()",IF(LEFT(AH28,9)="character","' '","0")),"") -> 0 | AH28: =VLOOKUP(D28,カラムID辞書!C:H,3,FALSE) -> numeric | AM28: =VLOOKUP(D28,カラムID辞書!C:H,4,FALSE) -> 13 | AO28: =VLOOKUP(D28,カラムID辞書!C:H,6,FALSE) -> 13 | AQ28: 売上伝票の売上高集計値（店頭・普通品）
B29: =IF($D29="","",MAX(OFFSET($B$8,0,0,ROW()-ROW($B$8),2))+1) -> 22 | D29: 売上高分類２ | L29: =VLOOKUP(D29,カラムID辞書!$C$4:$D$1266,2,FALSE) -> URIAGED_BNRI2 | AB29: =IF(L29="DELDTE","","○") -> ○ | AE29: =IF(AB29="○",IF(AH29="timestamp","now()",IF(LEFT(AH29,9)="character","' '","0")),"") -> 0 | AH29: =VLOOKUP(D29,カラムID辞書!C:H,3,FALSE) -> numeric | AM29: =VLOOKUP(D29,カラムID辞書!C:H,4,FALSE) -> 13 | AO29: =VLOOKUP(D29,カラムID辞書!C:H,6,FALSE) -> 13 | AQ29: 売上伝票の売上高集計値（店頭・催事）
B30: =IF($D30="","",MAX(OFFSET($B$8,0,0,ROW()-ROW($B$8),2))+1) -> 23 | D30: 売上高分類３ | L30: =VLOOKUP(D30,カラムID辞書!$C$4:$D$1266,2,FALSE) -> URIAGED_BNRI3 | AB30: =IF(L30="DELDTE","","○") -> ○ | AE30: =IF(AB30="○",IF(AH30="timestamp","now()",IF(LEFT(AH30,9)="character","' '","0")),"") -> 0 | AH30: =VLOOKUP(D30,カラムID辞書!C:H,3,FALSE) -> numeric | AM30: =VLOOKUP(D30,カラムID辞書!C:H,4,FALSE) -> 13 | AO30: =VLOOKUP(D30,カラムID辞書!C:H,6,FALSE) -> 13 | AQ30: 売上伝票の売上高集計値（店頭・店外）
B31: =IF($D31="","",MAX(OFFSET($B$8,0,0,ROW()-ROW($B$8),2))+1) -> 24 | D31: 売上高分類４ | L31: =VLOOKUP(D31,カラムID辞書!$C$4:$D$1266,2,FALSE) -> URIAGED_BNRI4 | AB31: =IF(L31="DELDTE","","○") -> ○ | AE31: =IF(AB31="○",IF(AH31="timestamp","now()",IF(LEFT(AH31,9)="character","' '","0")),"") -> 0 | AH31: =VLOOKUP(D31,カラムID辞書!C:H,3,FALSE) -> numeric | AM31: =VLOOKUP(D31,カラムID辞書!C:H,4,FALSE) -> 13 | AO31: =VLOOKUP(D31,カラムID辞書!C:H,6,FALSE) -> 13 | AQ31: 売上伝票の売上高集計値（店頭・ギフト）
B32: =IF($D32="","",MAX(OFFSET($B$8,0,0,ROW()-ROW($B$8),2))+1) -> 25 | D32: 売上高分類５ | L32: =VLOOKUP(D32,カラムID辞書!$C$4:$D$1266,2,FALSE) -> URIAGED_BNRI5 | AB32: =IF(L32="DELDTE","","○") -> ○ | AE32: =IF(AB32="○",IF(AH32="timestamp","now()",IF(LEFT(AH32,9)="character","' '","0")),"") -> 0 | AH32: =VLOOKUP(D32,カラムID辞書!C:H,3,FALSE) -> numeric | AM32: =VLOOKUP(D32,カラムID辞書!C:H,4,FALSE) -> 13 | AO32: =VLOOKUP(D32,カラムID辞書!C:H,6,FALSE) -> 13 | AQ32: 売上伝票の売上高集計値（店頭・ネット）
B33: =IF($D33="","",MAX(OFFSET($B$8,0,0,ROW()-ROW($B$8),2))+1) -> 26 | D33: 売上高分類６ | L33: =VLOOKUP(D33,カラムID辞書!$C$4:$D$1266,2,FALSE) -> URIAGED_BNRI6 | AB33: =IF(L33="DELDTE","","○") -> ○ | AE33: =IF(AB33="○",IF(AH33="timestamp","now()",IF(LEFT(AH33,9)="character","' '","0")),"") -> 0 | AH33: =VLOOKUP(D33,カラムID辞書!C:H,3,FALSE) -> numeric | AM33: =VLOOKUP(D33,カラムID辞書!C:H,4,FALSE) -> 13 | AO33: =VLOOKUP(D33,カラムID辞書!C:H,6,FALSE) -> 13 | AQ33: 売上伝票の売上高集計値（店頭・その他）
B34: =IF($D34="","",MAX(OFFSET($B$8,0,0,ROW()-ROW($B$8),2))+1) -> 27 | D34: 売上高分類７ | L34: =VLOOKUP(D34,カラムID辞書!$C$4:$D$1266,2,FALSE) -> URIAGED_BNRI7 | AB34: =IF(L34="DELDTE","","○") -> ○ | AE34: =IF(AB34="○",IF(AH34="timestamp","now()",IF(LEFT(AH34,9)="character","' '","0")),"") -> 0 | AH34: =VLOOKUP(D34,カラムID辞書!C:H,3,FALSE) -> numeric | AM34: =VLOOKUP(D34,カラムID辞書!C:H,4,FALSE) -> 13 | AO34: =VLOOKUP(D34,カラムID辞書!C:H,6,FALSE) -> 13 | AQ34: 売上伝票の売上高集計値（非店頭・店外）
B35: =IF($D35="","",MAX(OFFSET($B$8,0,0,ROW()-ROW($B$8),2))+1) -> 28 | D35: 売上高分類８ | L35: =VLOOKUP(D35,カラムID辞書!$C$4:$D$1266,2,FALSE) -> URIAGED_BNRI8 | AB35: =IF(L35="DELDTE","","○") -> ○ | AE35: =IF(AB35="○",IF(AH35="timestamp","now()",IF(LEFT(AH35,9)="character","' '","0")),"") -> 0 | AH35: =VLOOKUP(D35,カラムID辞書!C:H,3,FALSE) -> numeric | AM35: =VLOOKUP(D35,カラムID辞書!C:H,4,FALSE) -> 13 | AO35: =VLOOKUP(D35,カラムID辞書!C:H,6,FALSE) -> 13 | AQ35: 売上伝票の売上高集計値（非店頭・ギフト）
B36: =IF($D36="","",MAX(OFFSET($B$8,0,0,ROW()-ROW($B$8),2))+1) -> 29 | D36: 売上高分類９ | L36: =VLOOKUP(D36,カラムID辞書!$C$4:$D$1266,2,FALSE) -> URIAGED_BNRI9 | AB36: =IF(L36="DELDTE","","○") -> ○ | AE36: =IF(AB36="○",IF(AH36="timestamp","now()",IF(LEFT(AH36,9)="character","' '","0")),"") -> 0 | AH36: =VLOOKUP(D36,カラムID辞書!C:H,3,FALSE) -> numeric | AM36: =VLOOKUP(D36,カラムID辞書!C:H,4,FALSE) -> 13 | AO36: =VLOOKUP(D36,カラムID辞書!C:H,6,FALSE) -> 13 | AQ36: 売上伝票の売上高集計値（非店頭・その他）
B37: =IF($D37="","",MAX(OFFSET($B$8,0,0,ROW()-ROW($B$8),2))+1) -> 30 | D37: 売上高分類１０ | L37: =VLOOKUP(D37,カラムID辞書!$C$4:$D$1266,2,FALSE) -> URIAGED_BNRI10 | AB37: =IF(L37="DELDTE","","○") -> ○ | AE37: =IF(AB37="○",IF(AH37="timestamp","now()",IF(LEFT(AH37,9)="character","' '","0")),"") -> 0 | AH37: =VLOOKUP(D37,カラムID辞書!C:H,3,FALSE) -> numeric | AM37: =VLOOKUP(D37,カラムID辞書!C:H,4,FALSE) -> 13 | AO37: =VLOOKUP(D37,カラムID辞書!C:H,6,FALSE) -> 13 | BR37: （未設定：ZERO）
B38: =IF($D38="","",MAX(OFFSET($B$8,0,0,ROW()-ROW($B$8),2))+1) -> 31 | D38: 売上高数量 | L38: =VLOOKUP(D38,カラムID辞書!$C$4:$D$1266,2,FALSE) -> URIAGED_SU | AB38: =IF(L38="DELDTE","","○") -> ○ | AE38: =IF(AB38="○",IF(AH38="timestamp","now()",IF(LEFT(AH38,9)="character","' '","0")),"") -> 0 | AH38: =VLOOKUP(D38,カラムID辞書!C:H,3,FALSE) -> numeric | AM38: =VLOOKUP(D38,カラムID辞書!C:H,4,FALSE) -> 10 | AO38: =VLOOKUP(D38,カラムID辞書!C:H,6,FALSE) -> 10 | AQ38: 売上伝票の売上数量集計値
B39: =IF($D39="","",MAX(OFFSET($B$8,0,0,ROW()-ROW($B$8),2))+1) -> 32 | D39: 利益高 | L39: =VLOOKUP(D39,カラムID辞書!$C$4:$D$1266,2,FALSE) -> RIEKID | AB39: =IF(L39="DELDTE","","○") -> ○ | AE39: =IF(AB39="○",IF(AH39="timestamp","now()",IF(LEFT(AH39,9)="character","' '","0")),"") -> 0 | AH39: =VLOOKUP(D39,カラムID辞書!C:H,3,FALSE) -> numeric | AM39: =VLOOKUP(D39,カラムID辞書!C:H,4,FALSE) -> 13 | AO39: =VLOOKUP(D39,カラムID辞書!C:H,6,FALSE) -> 13 | AQ39: 別紙「商品勘定利益計算」参照 | BR39: 売益金
B40: =IF($D40="","",MAX(OFFSET($B$8,0,0,ROW()-ROW($B$8),2))+1) -> 33 | D40: 割引額 | L40: =VLOOKUP(D40,カラムID辞書!$C$4:$D$1266,2,FALSE) -> WARIBIKI_GAK | AB40: =IF(L40="DELDTE","","○") -> ○ | AE40: =IF(AB40="○",IF(AH40="timestamp","now()",IF(LEFT(AH40,9)="character","' '","0")),"") -> 0 | AH40: =VLOOKUP(D40,カラムID辞書!C:H,3,FALSE) -> numeric | AM40: =VLOOKUP(D40,カラムID辞書!C:H,4,FALSE) -> 13 | AO40: =VLOOKUP(D40,カラムID辞書!C:H,6,FALSE) -> 13 | AQ40: 売上伝票の割引額集計値
B41: =IF($D41="","",MAX(OFFSET($B$8,0,0,ROW()-ROW($B$8),2))+1) -> 34 | D41: 値引額 | L41: =VLOOKUP(D41,カラムID辞書!$C$4:$D$1266,2,FALSE) -> NEBIKI_GAK | AB41: =IF(L41="DELDTE","","○") -> ○ | AE41: =IF(AB41="○",IF(AH41="timestamp","now()",IF(LEFT(AH41,9)="character","' '","0")),"") -> 0 | AH41: =VLOOKUP(D41,カラムID辞書!C:H,3,FALSE) -> numeric | AM41: =VLOOKUP(D41,カラムID辞書!C:H,4,FALSE) -> 13 | AO41: =VLOOKUP(D41,カラムID辞書!C:H,6,FALSE) -> 13 | AQ41: 売上伝票の値引額集計値
B42: =IF($D42="","",MAX(OFFSET($B$8,0,0,ROW()-ROW($B$8),2))+1) -> 35 | D42: 客数１ | L42: =VLOOKUP(D42,カラムID辞書!$C$4:$D$1266,2,FALSE) -> KYAKU1_SU | AB42: =IF(L42="DELDTE","","○") -> ○ | AE42: =IF(AB42="○",IF(AH42="timestamp","now()",IF(LEFT(AH42,9)="character","' '","0")),"") -> 0 | AH42: =VLOOKUP(D42,カラムID辞書!C:H,3,FALSE) -> numeric | AM42: =VLOOKUP(D42,カラムID辞書!C:H,4,FALSE) -> 10,2 | AO42: =VLOOKUP(D42,カラムID辞書!C:H,6,FALSE) -> 10 | AQ42: 売上伝票の客数１集計値
B43: =IF($D43="","",MAX(OFFSET($B$8,0,0,ROW()-ROW($B$8),2))+1) -> 36 | D43: 客数２ | L43: =VLOOKUP(D43,カラムID辞書!$C$4:$D$1266,2,FALSE) -> KYAKU2_SU | AB43: =IF(L43="DELDTE","","○") -> ○ | AE43: =IF(AB43="○",IF(AH43="timestamp","now()",IF(LEFT(AH43,9)="character","' '","0")),"") -> 0 | AH43: =VLOOKUP(D43,カラムID辞書!C:H,3,FALSE) -> numeric | AM43: =VLOOKUP(D43,カラムID辞書!C:H,4,FALSE) -> 10,2 | AO43: =VLOOKUP(D43,カラムID辞書!C:H,6,FALSE) -> 10 | AQ43: 売上伝票の客数２集計値
B44: =IF($D44="","",MAX(OFFSET($B$8,0,0,ROW()-ROW($B$8),2))+1) -> 37 | D44: 客数３ | L44: =VLOOKUP(D44,カラムID辞書!$C$4:$D$1266,2,FALSE) -> KYAKU3_SU | AB44: =IF(L44="DELDTE","","○") -> ○ | AE44: =IF(AB44="○",IF(AH44="timestamp","now()",IF(LEFT(AH44,9)="character","' '","0")),"") -> 0 | AH44: =VLOOKUP(D44,カラムID辞書!C:H,3,FALSE) -> numeric | AM44: =VLOOKUP(D44,カラムID辞書!C:H,4,FALSE) -> 10,2 | AO44: =VLOOKUP(D44,カラムID辞書!C:H,6,FALSE) -> 10 | AQ44: 売上伝票の客数３集計値 | BR44: （未設定：ZERO）
B45: =IF($D45="","",MAX(OFFSET($B$8,0,0,ROW()-ROW($B$8),2))+1) -> 38 | D45: 純仕入高原価 | L45: =VLOOKUP(D45,カラムID辞書!$C$4:$D$1266,2,FALSE) -> JNSHIIRED_GNK | AB45: =IF(L45="DELDTE","","○") -> ○ | AE45: =IF(AB45="○",IF(AH45="timestamp","now()",IF(LEFT(AH45,9)="character","' '","0")),"") -> 0 | AH45: =VLOOKUP(D45,カラムID辞書!C:H,3,FALSE) -> numeric | AM45: =VLOOKUP(D45,カラムID辞書!C:H,4,FALSE) -> 13 | AO45: =VLOOKUP(D45,カラムID辞書!C:H,6,FALSE) -> 13 | AQ45: 別紙「商品勘定利益計算」参照
B46: =IF($D46="","",MAX(OFFSET($B$8,0,0,ROW()-ROW($B$8),2))+1) -> 39 | D46: 純仕入高売価 | L46: =VLOOKUP(D46,カラムID辞書!$C$4:$D$1266,2,FALSE) -> JNSHIIRED_BIK | AB46: =IF(L46="DELDTE","","○") -> ○ | AE46: =IF(AB46="○",IF(AH46="timestamp","now()",IF(LEFT(AH46,9)="character","' '","0")),"") -> 0 | AH46: =VLOOKUP(D46,カラムID辞書!C:H,3,FALSE) -> numeric | AM46: =VLOOKUP(D46,カラムID辞書!C:H,4,FALSE) -> 13 | AO46: =VLOOKUP(D46,カラムID辞書!C:H,6,FALSE) -> 13 | AQ46: 別紙「商品勘定利益計算」参照
B47: =IF($D47="","",MAX(OFFSET($B$8,0,0,ROW()-ROW($B$8),2))+1) -> 40 | D47: 純仕入高数量 | L47: =VLOOKUP(D47,カラムID辞書!$C$4:$D$1266,2,FALSE) -> JNSHIIRED_SU | AB47: =IF(L47="DELDTE","","○") -> ○ | AE47: =IF(AB47="○",IF(AH47="timestamp","now()",IF(LEFT(AH47,9)="character","' '","0")),"") -> 0 | AH47: =VLOOKUP(D47,カラムID辞書!C:H,3,FALSE) -> numeric | AM47: =VLOOKUP(D47,カラムID辞書!C:H,4,FALSE) -> 10 | AO47: =VLOOKUP(D47,カラムID辞書!C:H,6,FALSE) -> 10 | AQ47: 別紙「商品勘定利益計算」参照
B48: =IF($D48="","",MAX(OFFSET($B$8,0,0,ROW()-ROW($B$8),2))+1) -> 41 | D48: 仕入高原価 | L48: =VLOOKUP(D48,カラムID辞書!$C$4:$D$1266,2,FALSE) -> SHIIRED_GNK | AB48: =IF(L48="DELDTE","","○") -> ○ | AE48: =IF(AB48="○",IF(AH48="timestamp","now()",IF(LEFT(AH48,9)="character","' '","0")),"") -> 0 | AH48: =VLOOKUP(D48,カラムID辞書!C:H,3,FALSE) -> numeric | AM48: =VLOOKUP(D48,カラムID辞書!C:H,4,FALSE) -> 13 | AO48: =VLOOKUP(D48,カラムID辞書!C:H,6,FALSE) -> 13 | AQ48: 仕入伝票の原価集計値
B49: =IF($D49="","",MAX(OFFSET($B$8,0,0,ROW()-ROW($B$8),2))+1) -> 42 | D49: 仕入高売価 | L49: =VLOOKUP(D49,カラムID辞書!$C$4:$D$1266,2,FALSE) -> SHIIRED_BIK | AB49: =IF(L49="DELDTE","","○") -> ○ | AE49: =IF(AB49="○",IF(AH49="timestamp","now()",IF(LEFT(AH49,9)="character","' '","0")),"") -> 0 | AH49: =VLOOKUP(D49,カラムID辞書!C:H,3,FALSE) -> numeric | AM49: =VLOOKUP(D49,カラムID辞書!C:H,4,FALSE) -> 13 | AO49: =VLOOKUP(D49,カラムID辞書!C:H,6,FALSE) -> 13 | AQ49: 仕入伝票の売価集計値
B50: =IF($D50="","",MAX(OFFSET($B$8,0,0,ROW()-ROW($B$8),2))+1) -> 43 | D50: 仕入高数量 | L50: =VLOOKUP(D50,カラムID辞書!$C$4:$D$1266,2,FALSE) -> SHIIRED_SU | AB50: =IF(L50="DELDTE","","○") -> ○ | AE50: =IF(AB50="○",IF(AH50="timestamp","now()",IF(LEFT(AH50,9)="character","' '","0")),"") -> 0 | AH50: =VLOOKUP(D50,カラムID辞書!C:H,3,FALSE) -> numeric | AM50: =VLOOKUP(D50,カラムID辞書!C:H,4,FALSE) -> 10 | AO50: =VLOOKUP(D50,カラムID辞書!C:H,6,FALSE) -> 10 | AQ50: 仕入伝票の数量集計値
B51: =IF($D51="","",MAX(OFFSET($B$8,0,0,ROW()-ROW($B$8),2))+1) -> 44 | D51: 付帯仕入高原価 | L51: =VLOOKUP(D51,カラムID辞書!$C$4:$D$1266,2,FALSE) -> FUTAISHIIRED_GNK | AB51: =IF(L51="DELDTE","","○") -> ○ | AE51: =IF(AB51="○",IF(AH51="timestamp","now()",IF(LEFT(AH51,9)="character","' '","0")),"") -> 0 | AH51: =VLOOKUP(D51,カラムID辞書!C:H,3,FALSE) -> numeric | AM51: =VLOOKUP(D51,カラムID辞書!C:H,4,FALSE) -> 13 | AO51: =VLOOKUP(D51,カラムID辞書!C:H,6,FALSE) -> 13 | BR51: （未設定：ZERO）
B52: =IF($D52="","",MAX(OFFSET($B$8,0,0,ROW()-ROW($B$8),2))+1) -> 45 | D52: 返品高原価 | L52: =VLOOKUP(D52,カラムID辞書!$C$4:$D$1266,2,FALSE) -> HENPND_GNK | AB52: =IF(L52="DELDTE","","○") -> ○ | AE52: =IF(AB52="○",IF(AH52="timestamp","now()",IF(LEFT(AH52,9)="character","' '","0")),"") -> 0 | AH52: =VLOOKUP(D52,カラムID辞書!C:H,3,FALSE) -> numeric | AM52: =VLOOKUP(D52,カラムID辞書!C:H,4,FALSE) -> 13 | AO52: =VLOOKUP(D52,カラムID辞書!C:H,6,FALSE) -> 13 | AQ52: 返品伝票の原価集計値
B53: =IF($D53="","",MAX(OFFSET($B$8,0,0,ROW()-ROW($B$8),2))+1) -> 46 | D53: 返品高売価 | L53: =VLOOKUP(D53,カラムID辞書!$C$4:$D$1266,2,FALSE) -> HENPND_BIK | AB53: =IF(L53="DELDTE","","○") -> ○ | AE53: =IF(AB53="○",IF(AH53="timestamp","now()",IF(LEFT(AH53,9)="character","' '","0")),"") -> 0 | AH53: =VLOOKUP(D53,カラムID辞書!C:H,3,FALSE) -> numeric | AM53: =VLOOKUP(D53,カラムID辞書!C:H,4,FALSE) -> 13 | AO53: =VLOOKUP(D53,カラムID辞書!C:H,6,FALSE) -> 13 | AQ53: 返品伝票の売価集計値
B54: =IF($D54="","",MAX(OFFSET($B$8,0,0,ROW()-ROW($B$8),2))+1) -> 47 | D54: 返品高数量 | L54: =VLOOKUP(D54,カラムID辞書!$C$4:$D$1266,2,FALSE) -> HENPND_SU | AB54: =IF(L54="DELDTE","","○") -> ○ | AE54: =IF(AB54="○",IF(AH54="timestamp","now()",IF(LEFT(AH54,9)="character","' '","0")),"") -> 0 | AH54: =VLOOKUP(D54,カラムID辞書!C:H,3,FALSE) -> numeric | AM54: =VLOOKUP(D54,カラムID辞書!C:H,4,FALSE) -> 10 | AO54: =VLOOKUP(D54,カラムID辞書!C:H,6,FALSE) -> 10 | AQ54: 返品伝票の数量集計値
B55: =IF($D55="","",MAX(OFFSET($B$8,0,0,ROW()-ROW($B$8),2))+1) -> 48 | D55: 付帯返品高原価 | L55: =VLOOKUP(D55,カラムID辞書!$C$4:$D$1266,2,FALSE) -> FUTAIHENPND_GNK | AB55: =IF(L55="DELDTE","","○") -> ○ | AE55: =IF(AB55="○",IF(AH55="timestamp","now()",IF(LEFT(AH55,9)="character","' '","0")),"") -> 0 | AH55: =VLOOKUP(D55,カラムID辞書!C:H,3,FALSE) -> numeric | AM55: =VLOOKUP(D55,カラムID辞書!C:H,4,FALSE) -> 13 | AO55: =VLOOKUP(D55,カラムID辞書!C:H,6,FALSE) -> 13 | BR55: （未設定：ZERO）
B56: =IF($D56="","",MAX(OFFSET($B$8,0,0,ROW()-ROW($B$8),2))+1) -> 49 | D56: 価格訂正仕入高原価 | L56: =VLOOKUP(D56,カラムID辞書!$C$4:$D$1266,2,FALSE) -> TEISEISHIIRED_GNK | AB56: =IF(L56="DELDTE","","○") -> ○ | AE56: =IF(AB56="○",IF(AH56="timestamp","now()",IF(LEFT(AH56,9)="character","' '","0")),"") -> 0 | AH56: =VLOOKUP(D56,カラムID辞書!C:H,3,FALSE) -> numeric | AM56: =VLOOKUP(D56,カラムID辞書!C:H,4,FALSE) -> 13 | AO56: =VLOOKUP(D56,カラムID辞書!C:H,6,FALSE) -> 13 | AQ56: 価格変更による再仕入伝票の原価集計値
B57: =IF($D57="","",MAX(OFFSET($B$8,0,0,ROW()-ROW($B$8),2))+1) -> 50 | D57: 価格訂正仕入高売価 | L57: =VLOOKUP(D57,カラムID辞書!$C$4:$D$1266,2,FALSE) -> TEISEISHIIRED_BIK | AB57: =IF(L57="DELDTE","","○") -> ○ | AE57: =IF(AB57="○",IF(AH57="timestamp","now()",IF(LEFT(AH57,9)="character","' '","0")),"") -> 0 | AH57: =VLOOKUP(D57,カラムID辞書!C:H,3,FALSE) -> numeric | AM57: =VLOOKUP(D57,カラムID辞書!C:H,4,FALSE) -> 13 | AO57: =VLOOKUP(D57,カラムID辞書!C:H,6,FALSE) -> 13 | AQ57: 価格変更による再仕入伝票の売価集計値
B58: =IF($D58="","",MAX(OFFSET($B$8,0,0,ROW()-ROW($B$8),2))+1) -> 51 | D58: 価格訂正仕入高数量 | L58: =VLOOKUP(D58,カラムID辞書!$C$4:$D$1266,2,FALSE) -> TEISEISHIIRED_SU | AB58: =IF(L58="DELDTE","","○") -> ○ | AE58: =IF(AB58="○",IF(AH58="timestamp","now()",IF(LEFT(AH58,9)="character","' '","0")),"") -> 0 | AH58: =VLOOKUP(D58,カラムID辞書!C:H,3,FALSE) -> numeric | AM58: =VLOOKUP(D58,カラムID辞書!C:H,4,FALSE) -> 10 | AO58: =VLOOKUP(D58,カラムID辞書!C:H,6,FALSE) -> 10 | AQ58: 価格変更による再仕入伝票の数量集計値
B59: =IF($D59="","",MAX(OFFSET($B$8,0,0,ROW()-ROW($B$8),2))+1) -> 52 | D59: 価格訂正返品高原価 | L59: =VLOOKUP(D59,カラムID辞書!$C$4:$D$1266,2,FALSE) -> TEISEIHENPIND_GNK | AB59: =IF(L59="DELDTE","","○") -> ○ | AE59: =IF(AB59="○",IF(AH59="timestamp","now()",IF(LEFT(AH59,9)="character","' '","0")),"") -> 0 | AH59: =VLOOKUP(D59,カラムID辞書!C:H,3,FALSE) -> numeric | AM59: =VLOOKUP(D59,カラムID辞書!C:H,4,FALSE) -> 13 | AO59: =VLOOKUP(D59,カラムID辞書!C:H,6,FALSE) -> 13 | AQ59: 価格変更による返品伝票の原価集計値
B60: =IF($D60="","",MAX(OFFSET($B$8,0,0,ROW()-ROW($B$8),2))+1) -> 53 | D60: 価格訂正返品高売価 | L60: =VLOOKUP(D60,カラムID辞書!$C$4:$D$1266,2,FALSE) -> TEISEIHENPIND_BIK | AB60: =IF(L60="DELDTE","","○") -> ○ | AE60: =IF(AB60="○",IF(AH60="timestamp","now()",IF(LEFT(AH60,9)="character","' '","0")),"") -> 0 | AH60: =VLOOKUP(D60,カラムID辞書!C:H,3,FALSE) -> numeric | AM60: =VLOOKUP(D60,カラムID辞書!C:H,4,FALSE) -> 13 | AO60: =VLOOKUP(D60,カラムID辞書!C:H,6,FALSE) -> 13 | AQ60: 価格変更による返品伝票の売価集計値
B61: =IF($D61="","",MAX(OFFSET($B$8,0,0,ROW()-ROW($B$8),2))+1) -> 54 | D61: 価格訂正返品高数量 | L61: =VLOOKUP(D61,カラムID辞書!$C$4:$D$1266,2,FALSE) -> TEISEIHENPIND_SU | AB61: =IF(L61="DELDTE","","○") -> ○ | AE61: =IF(AB61="○",IF(AH61="timestamp","now()",IF(LEFT(AH61,9)="character","' '","0")),"") -> 0 | AH61: =VLOOKUP(D61,カラムID辞書!C:H,3,FALSE) -> numeric | AM61: =VLOOKUP(D61,カラムID辞書!C:H,4,FALSE) -> 10 | AO61: =VLOOKUP(D61,カラムID辞書!C:H,6,FALSE) -> 10 | AQ61: 価格変更による返品伝票の数量集計値
B62: =IF($D62="","",MAX(OFFSET($B$8,0,0,ROW()-ROW($B$8),2))+1) -> 55 | D62: 自社値上高売価 | L62: =VLOOKUP(D62,カラムID辞書!$C$4:$D$1266,2,FALSE) -> JISHANEAGED_BIK | AB62: =IF(L62="DELDTE","","○") -> ○ | AE62: =IF(AB62="○",IF(AH62="timestamp","now()",IF(LEFT(AH62,9)="character","' '","0")),"") -> 0 | AH62: =VLOOKUP(D62,カラムID辞書!C:H,3,FALSE) -> numeric | AM62: =VLOOKUP(D62,カラムID辞書!C:H,4,FALSE) -> 13 | AO62: =VLOOKUP(D62,カラムID辞書!C:H,6,FALSE) -> 13 | AQ62: 値上伝票の売価集計値
B63: =IF($D63="","",MAX(OFFSET($B$8,0,0,ROW()-ROW($B$8),2))+1) -> 56 | D63: 自社値下高売価 | L63: =VLOOKUP(D63,カラムID辞書!$C$4:$D$1266,2,FALSE) -> JISHANESAGED_BIK | AB63: =IF(L63="DELDTE","","○") -> ○ | AE63: =IF(AB63="○",IF(AH63="timestamp","now()",IF(LEFT(AH63,9)="character","' '","0")),"") -> 0 | AH63: =VLOOKUP(D63,カラムID辞書!C:H,3,FALSE) -> numeric | AM63: =VLOOKUP(D63,カラムID辞書!C:H,4,FALSE) -> 13 | AO63: =VLOOKUP(D63,カラムID辞書!C:H,6,FALSE) -> 13 | AQ63: 値下伝票の売価集計値
B64: =IF($D64="","",MAX(OFFSET($B$8,0,0,ROW()-ROW($B$8),2))+1) -> 57 | D64: 値上高原価１ | L64: =VLOOKUP(D64,カラムID辞書!$C$4:$D$1266,2,FALSE) -> NEAGED1_GNK | AB64: =IF(L64="DELDTE","","○") -> ○ | AE64: =IF(AB64="○",IF(AH64="timestamp","now()",IF(LEFT(AH64,9)="character","' '","0")),"") -> 0 | AH64: =VLOOKUP(D64,カラムID辞書!C:H,3,FALSE) -> numeric | AM64: =VLOOKUP(D64,カラムID辞書!C:H,4,FALSE) -> 13 | AO64: =VLOOKUP(D64,カラムID辞書!C:H,6,FALSE) -> 13 | BR64: （未設定：ZERO）
B65: =IF($D65="","",MAX(OFFSET($B$8,0,0,ROW()-ROW($B$8),2))+1) -> 58 | D65: 値上高売価１ | L65: =VLOOKUP(D65,カラムID辞書!$C$4:$D$1266,2,FALSE) -> NEAGED1_BIK | AB65: =IF(L65="DELDTE","","○") -> ○ | AE65: =IF(AB65="○",IF(AH65="timestamp","now()",IF(LEFT(AH65,9)="character","' '","0")),"") -> 0 | AH65: =VLOOKUP(D65,カラムID辞書!C:H,3,FALSE) -> numeric | AM65: =VLOOKUP(D65,カラムID辞書!C:H,4,FALSE) -> 13 | AO65: =VLOOKUP(D65,カラムID辞書!C:H,6,FALSE) -> 13 | BR65: （未設定：ZERO）
B66: =IF($D66="","",MAX(OFFSET($B$8,0,0,ROW()-ROW($B$8),2))+1) -> 59 | D66: 値下高原価１ | L66: =VLOOKUP(D66,カラムID辞書!$C$4:$D$1266,2,FALSE) -> NESAGED1_GNK | AB66: =IF(L66="DELDTE","","○") -> ○ | AE66: =IF(AB66="○",IF(AH66="timestamp","now()",IF(LEFT(AH66,9)="character","' '","0")),"") -> 0 | AH66: =VLOOKUP(D66,カラムID辞書!C:H,3,FALSE) -> numeric | AM66: =VLOOKUP(D66,カラムID辞書!C:H,4,FALSE) -> 13 | AO66: =VLOOKUP(D66,カラムID辞書!C:H,6,FALSE) -> 13 | AQ66: 破損伝票の数量集計値
B67: =IF($D67="","",MAX(OFFSET($B$8,0,0,ROW()-ROW($B$8),2))+1) -> 60 | D67: 値下高売価１ | L67: =VLOOKUP(D67,カラムID辞書!$C$4:$D$1266,2,FALSE) -> NESAGED1_BIK | AB67: =IF(L67="DELDTE","","○") -> ○ | AE67: =IF(AB67="○",IF(AH67="timestamp","now()",IF(LEFT(AH67,9)="character","' '","0")),"") -> 0 | AH67: =VLOOKUP(D67,カラムID辞書!C:H,3,FALSE) -> numeric | AM67: =VLOOKUP(D67,カラムID辞書!C:H,4,FALSE) -> 13 | AO67: =VLOOKUP(D67,カラムID辞書!C:H,6,FALSE) -> 13 | AQ67: 破損伝票の売価集計値
B68: =IF($D68="","",MAX(OFFSET($B$8,0,0,ROW()-ROW($B$8),2))+1) -> 61 | D68: 値上高原価２ | L68: =VLOOKUP(D68,カラムID辞書!$C$4:$D$1266,2,FALSE) -> NEAGED2_GNK | AB68: =IF(L68="DELDTE","","○") -> ○ | AE68: =IF(AB68="○",IF(AH68="timestamp","now()",IF(LEFT(AH68,9)="character","' '","0")),"") -> 0 | AH68: =VLOOKUP(D68,カラムID辞書!C:H,3,FALSE) -> numeric | AM68: =VLOOKUP(D68,カラムID辞書!C:H,4,FALSE) -> 13 | AO68: =VLOOKUP(D68,カラムID辞書!C:H,6,FALSE) -> 13 | BR68: （未設定：ZERO）
B69: =IF($D69="","",MAX(OFFSET($B$8,0,0,ROW()-ROW($B$8),2))+1) -> 62 | D69: 値上高売価２ | L69: =VLOOKUP(D69,カラムID辞書!$C$4:$D$1266,2,FALSE) -> NEAGED2_BIK | AB69: =IF(L69="DELDTE","","○") -> ○ | AE69: =IF(AB69="○",IF(AH69="timestamp","now()",IF(LEFT(AH69,9)="character","' '","0")),"") -> 0 | AH69: =VLOOKUP(D69,カラムID辞書!C:H,3,FALSE) -> numeric | AM69: =VLOOKUP(D69,カラムID辞書!C:H,4,FALSE) -> 13 | AO69: =VLOOKUP(D69,カラムID辞書!C:H,6,FALSE) -> 13 | BR69: （未設定：ZERO）
B70: =IF($D70="","",MAX(OFFSET($B$8,0,0,ROW()-ROW($B$8),2))+1) -> 63 | D70: 値下高原価２ | L70: =VLOOKUP(D70,カラムID辞書!$C$4:$D$1266,2,FALSE) -> NESAGED2_GNK | AB70: =IF(L70="DELDTE","","○") -> ○ | AE70: =IF(AB70="○",IF(AH70="timestamp","now()",IF(LEFT(AH70,9)="character","' '","0")),"") -> 0 | AH70: =VLOOKUP(D70,カラムID辞書!C:H,3,FALSE) -> numeric | AM70: =VLOOKUP(D70,カラムID辞書!C:H,4,FALSE) -> 13 | AO70: =VLOOKUP(D70,カラムID辞書!C:H,6,FALSE) -> 13 | BR70: （未設定：ZERO）
B71: =IF($D71="","",MAX(OFFSET($B$8,0,0,ROW()-ROW($B$8),2))+1) -> 64 | D71: 値下高売価２ | L71: =VLOOKUP(D71,カラムID辞書!$C$4:$D$1266,2,FALSE) -> NESAGED2_BIK | AB71: =IF(L71="DELDTE","","○") -> ○ | AE71: =IF(AB71="○",IF(AH71="timestamp","now()",IF(LEFT(AH71,9)="character","' '","0")),"") -> 0 | AH71: =VLOOKUP(D71,カラムID辞書!C:H,3,FALSE) -> numeric | AM71: =VLOOKUP(D71,カラムID辞書!C:H,4,FALSE) -> 13 | AO71: =VLOOKUP(D71,カラムID辞書!C:H,6,FALSE) -> 13 | BR71: （未設定：ZERO）
B72: =IF($D72="","",MAX(OFFSET($B$8,0,0,ROW()-ROW($B$8),2))+1) -> 65 | D72: 店間振替高原価（払出） | L72: =VLOOKUP(D72,カラムID辞書!$C$4:$D$1266,2,FALSE) -> TNKANFURI_O_GNK | AB72: =IF(L72="DELDTE","","○") -> ○ | AE72: =IF(AB72="○",IF(AH72="timestamp","now()",IF(LEFT(AH72,9)="character","' '","0")),"") -> 0 | AH72: =VLOOKUP(D72,カラムID辞書!C:H,3,FALSE) -> numeric | AM72: =VLOOKUP(D72,カラムID辞書!C:H,4,FALSE) -> 13 | AO72: =VLOOKUP(D72,カラムID辞書!C:H,6,FALSE) -> 13 | AQ72: 店間振替伝票（払出）の原価集計値
B73: =IF($D73="","",MAX(OFFSET($B$8,0,0,ROW()-ROW($B$8),2))+1) -> 66 | D73: 店間振替高売価（払出） | L73: =VLOOKUP(D73,カラムID辞書!$C$4:$D$1266,2,FALSE) -> TNKANFURI_O_BIK | AB73: =IF(L73="DELDTE","","○") -> ○ | AE73: =IF(AB73="○",IF(AH73="timestamp","now()",IF(LEFT(AH73,9)="character","' '","0")),"") -> 0 | AH73: =VLOOKUP(D73,カラムID辞書!C:H,3,FALSE) -> numeric | AM73: =VLOOKUP(D73,カラムID辞書!C:H,4,FALSE) -> 13 | AO73: =VLOOKUP(D73,カラムID辞書!C:H,6,FALSE) -> 13 | AQ73: 店間振替伝票（払出）の売価集計値
B74: =IF($D74="","",MAX(OFFSET($B$8,0,0,ROW()-ROW($B$8),2))+1) -> 67 | D74: 店間振替高数量（払出） | L74: =VLOOKUP(D74,カラムID辞書!$C$4:$D$1266,2,FALSE) -> TNKANFURI_O_SU | AB74: =IF(L74="DELDTE","","○") -> ○ | AE74: =IF(AB74="○",IF(AH74="timestamp","now()",IF(LEFT(AH74,9)="character","' '","0")),"") -> 0 | AH74: =VLOOKUP(D74,カラムID辞書!C:H,3,FALSE) -> numeric | AM74: =VLOOKUP(D74,カラムID辞書!C:H,4,FALSE) -> 10 | AO74: =VLOOKUP(D74,カラムID辞書!C:H,6,FALSE) -> 10 | AQ74: 店間振替伝票（払出）の数量集計値
B75: =IF($D75="","",MAX(OFFSET($B$8,0,0,ROW()-ROW($B$8),2))+1) -> 68 | D75: 店間振替高原価（受入） | L75: =VLOOKUP(D75,カラムID辞書!$C$4:$D$1266,2,FALSE) -> TNKANFURI_I_GNK | AB75: =IF(L75="DELDTE","","○") -> ○ | AE75: =IF(AB75="○",IF(AH75="timestamp","now()",IF(LEFT(AH75,9)="character","' '","0")),"") -> 0 | AH75: =VLOOKUP(D75,カラムID辞書!C:H,3,FALSE) -> numeric | AM75: =VLOOKUP(D75,カラムID辞書!C:H,4,FALSE) -> 13 | AO75: =VLOOKUP(D75,カラムID辞書!C:H,6,FALSE) -> 13 | AQ75: 店間振替伝票（受入）の原価集計値
B76: =IF($D76="","",MAX(OFFSET($B$8,0,0,ROW()-ROW($B$8),2))+1) -> 69 | D76: 店間振替高売価（受入） | L76: =VLOOKUP(D76,カラムID辞書!$C$4:$D$1266,2,FALSE) -> TNKANFURI_I_BIK | AB76: =IF(L76="DELDTE","","○") -> ○ | AE76: =IF(AB76="○",IF(AH76="timestamp","now()",IF(LEFT(AH76,9)="character","' '","0")),"") -> 0 | AH76: =VLOOKUP(D76,カラムID辞書!C:H,3,FALSE) -> numeric | AM76: =VLOOKUP(D76,カラムID辞書!C:H,4,FALSE) -> 13 | AO76: =VLOOKUP(D76,カラムID辞書!C:H,6,FALSE) -> 13 | AQ76: 店間振替伝票（受入）の売価集計値
B77: =IF($D77="","",MAX(OFFSET($B$8,0,0,ROW()-ROW($B$8),2))+1) -> 70 | D77: 店間振替高数量（受入） | L77: =VLOOKUP(D77,カラムID辞書!$C$4:$D$1266,2,FALSE) -> TNKANFURI_I_SU | AB77: =IF(L77="DELDTE","","○") -> ○ | AE77: =IF(AB77="○",IF(AH77="timestamp","now()",IF(LEFT(AH77,9)="character","' '","0")),"") -> 0 | AH77: =VLOOKUP(D77,カラムID辞書!C:H,3,FALSE) -> numeric | AM77: =VLOOKUP(D77,カラムID辞書!C:H,4,FALSE) -> 10 | AO77: =VLOOKUP(D77,カラムID辞書!C:H,6,FALSE) -> 10 | AQ77: 店間振替伝票（受入）の数量集計値
B78: =IF($D78="","",MAX(OFFSET($B$8,0,0,ROW()-ROW($B$8),2))+1) -> 71 | D78: 店内振替高原価（払出） | L78: =VLOOKUP(D78,カラムID辞書!$C$4:$D$1266,2,FALSE) -> TNNAIFURI_O_GNK | AB78: =IF(L78="DELDTE","","○") -> ○ | AE78: =IF(AB78="○",IF(AH78="timestamp","now()",IF(LEFT(AH78,9)="character","' '","0")),"") -> 0 | AH78: =VLOOKUP(D78,カラムID辞書!C:H,3,FALSE) -> numeric | AM78: =VLOOKUP(D78,カラムID辞書!C:H,4,FALSE) -> 13 | AO78: =VLOOKUP(D78,カラムID辞書!C:H,6,FALSE) -> 13 | AQ78: 品番振替伝票（払出）の原価集計値
B79: =IF($D79="","",MAX(OFFSET($B$8,0,0,ROW()-ROW($B$8),2))+1) -> 72 | D79: 店内振替高売価（払出） | L79: =VLOOKUP(D79,カラムID辞書!$C$4:$D$1266,2,FALSE) -> TNNAIFURI_O_BIK | AB79: =IF(L79="DELDTE","","○") -> ○ | AE79: =IF(AB79="○",IF(AH79="timestamp","now()",IF(LEFT(AH79,9)="character","' '","0")),"") -> 0 | AH79: =VLOOKUP(D79,カラムID辞書!C:H,3,FALSE) -> numeric | AM79: =VLOOKUP(D79,カラムID辞書!C:H,4,FALSE) -> 13 | AO79: =VLOOKUP(D79,カラムID辞書!C:H,6,FALSE) -> 13 | AQ79: 品番振替伝票（払出）の売価集計値
B80: =IF($D80="","",MAX(OFFSET($B$8,0,0,ROW()-ROW($B$8),2))+1) -> 73 | D80: 店内振替高数量（払出） | L80: =VLOOKUP(D80,カラムID辞書!$C$4:$D$1266,2,FALSE) -> TNNAIFURI_O_SU | AB80: =IF(L80="DELDTE","","○") -> ○ | AE80: =IF(AB80="○",IF(AH80="timestamp","now()",IF(LEFT(AH80,9)="character","' '","0")),"") -> 0 | AH80: =VLOOKUP(D80,カラムID辞書!C:H,3,FALSE) -> numeric | AM80: =VLOOKUP(D80,カラムID辞書!C:H,4,FALSE) -> 10 | AO80: =VLOOKUP(D80,カラムID辞書!C:H,6,FALSE) -> 10 | AQ80: 品番振替伝票（払出）の数量集計値
B81: =IF($D81="","",MAX(OFFSET($B$8,0,0,ROW()-ROW($B$8),2))+1) -> 74 | D81: 店内振替高原価（受入） | L81: =VLOOKUP(D81,カラムID辞書!$C$4:$D$1266,2,FALSE) -> TNNAIFURI_I_GNK | AB81: =IF(L81="DELDTE","","○") -> ○ | AE81: =IF(AB81="○",IF(AH81="timestamp","now()",IF(LEFT(AH81,9)="character","' '","0")),"") -> 0 | AH81: =VLOOKUP(D81,カラムID辞書!C:H,3,FALSE) -> numeric | AM81: =VLOOKUP(D81,カラムID辞書!C:H,4,FALSE) -> 13 | AO81: =VLOOKUP(D81,カラムID辞書!C:H,6,FALSE) -> 13 | AQ81: 品番振替伝票（受入）の原価集計値
B82: =IF($D82="","",MAX(OFFSET($B$8,0,0,ROW()-ROW($B$8),2))+1) -> 75 | D82: 店内振替高売価（受入） | L82: =VLOOKUP(D82,カラムID辞書!$C$4:$D$1266,2,FALSE) -> TNNAIFURI_I_BIK | AB82: =IF(L82="DELDTE","","○") -> ○ | AE82: =IF(AB82="○",IF(AH82="timestamp","now()",IF(LEFT(AH82,9)="character","' '","0")),"") -> 0 | AH82: =VLOOKUP(D82,カラムID辞書!C:H,3,FALSE) -> numeric | AM82: =VLOOKUP(D82,カラムID辞書!C:H,4,FALSE) -> 13 | AO82: =VLOOKUP(D82,カラムID辞書!C:H,6,FALSE) -> 13 | AQ82: 品番振替伝票（受入）の売価集計値
B83: =IF($D83="","",MAX(OFFSET($B$8,0,0,ROW()-ROW($B$8),2))+1) -> 76 | D83: 店内振替高数量（受入） | L83: =VLOOKUP(D83,カラムID辞書!$C$4:$D$1266,2,FALSE) -> TNNAIFURI_I_SU | AB83: =IF(L83="DELDTE","","○") -> ○ | AE83: =IF(AB83="○",IF(AH83="timestamp","now()",IF(LEFT(AH83,9)="character","' '","0")),"") -> 0 | AH83: =VLOOKUP(D83,カラムID辞書!C:H,3,FALSE) -> numeric | AM83: =VLOOKUP(D83,カラムID辞書!C:H,4,FALSE) -> 10 | AO83: =VLOOKUP(D83,カラムID辞書!C:H,6,FALSE) -> 10 | AQ83: 品番振替伝票（受入）の数量集計値
B84: =IF($D84="","",MAX(OFFSET($B$8,0,0,ROW()-ROW($B$8),2))+1) -> 77 | D84: 商品振替高原価（払出） | L84: =VLOOKUP(D84,カラムID辞書!$C$4:$D$1266,2,FALSE) -> SHOHNFURI_O_GNK | AB84: =IF(L84="DELDTE","","○") -> ○ | AE84: =IF(AB84="○",IF(AH84="timestamp","now()",IF(LEFT(AH84,9)="character","' '","0")),"") -> 0 | AH84: =VLOOKUP(D84,カラムID辞書!C:H,3,FALSE) -> numeric | AM84: =VLOOKUP(D84,カラムID辞書!C:H,4,FALSE) -> 13 | AO84: =VLOOKUP(D84,カラムID辞書!C:H,6,FALSE) -> 13 | BR84: （未設定：ZERO）
B85: =IF($D85="","",MAX(OFFSET($B$8,0,0,ROW()-ROW($B$8),2))+1) -> 78 | D85: 商品振替高売価（払出） | L85: =VLOOKUP(D85,カラムID辞書!$C$4:$D$1266,2,FALSE) -> SHOHNFURI_O_BIK | AB85: =IF(L85="DELDTE","","○") -> ○ | AE85: =IF(AB85="○",IF(AH85="timestamp","now()",IF(LEFT(AH85,9)="character","' '","0")),"") -> 0 | AH85: =VLOOKUP(D85,カラムID辞書!C:H,3,FALSE) -> numeric | AM85: =VLOOKUP(D85,カラムID辞書!C:H,4,FALSE) -> 13 | AO85: =VLOOKUP(D85,カラムID辞書!C:H,6,FALSE) -> 13 | BR85: （未設定：ZERO）
B86: =IF($D86="","",MAX(OFFSET($B$8,0,0,ROW()-ROW($B$8),2))+1) -> 79 | D86: 商品振替高数量（払出） | L86: =VLOOKUP(D86,カラムID辞書!$C$4:$D$1266,2,FALSE) -> SHOHNFURI_O_SU | AB86: =IF(L86="DELDTE","","○") -> ○ | AE86: =IF(AB86="○",IF(AH86="timestamp","now()",IF(LEFT(AH86,9)="character","' '","0")),"") -> 0 | AH86: =VLOOKUP(D86,カラムID辞書!C:H,3,FALSE) -> numeric | AM86: =VLOOKUP(D86,カラムID辞書!C:H,4,FALSE) -> 10 | AO86: =VLOOKUP(D86,カラムID辞書!C:H,6,FALSE) -> 10 | BR86: （未設定：ZERO）
B87: =IF($D87="","",MAX(OFFSET($B$8,0,0,ROW()-ROW($B$8),2))+1) -> 80 | D87: 商品振替高原価（受入） | L87: =VLOOKUP(D87,カラムID辞書!$C$4:$D$1266,2,FALSE) -> SHOHNFURI_I_GNK | AB87: =IF(L87="DELDTE","","○") -> ○ | AE87: =IF(AB87="○",IF(AH87="timestamp","now()",IF(LEFT(AH87,9)="character","' '","0")),"") -> 0 | AH87: =VLOOKUP(D87,カラムID辞書!C:H,3,FALSE) -> numeric | AM87: =VLOOKUP(D87,カラムID辞書!C:H,4,FALSE) -> 13 | AO87: =VLOOKUP(D87,カラムID辞書!C:H,6,FALSE) -> 13 | BR87: （未設定：ZERO）
B88: =IF($D88="","",MAX(OFFSET($B$8,0,0,ROW()-ROW($B$8),2))+1) -> 81 | D88: 商品振替高売価（受入） | L88: =VLOOKUP(D88,カラムID辞書!$C$4:$D$1266,2,FALSE) -> SHOHNFURI_I_BIK | AB88: =IF(L88="DELDTE","","○") -> ○ | AE88: =IF(AB88="○",IF(AH88="timestamp","now()",IF(LEFT(AH88,9)="character","' '","0")),"") -> 0 | AH88: =VLOOKUP(D88,カラムID辞書!C:H,3,FALSE) -> numeric | AM88: =VLOOKUP(D88,カラムID辞書!C:H,4,FALSE) -> 13 | AO88: =VLOOKUP(D88,カラムID辞書!C:H,6,FALSE) -> 13 | BR88: （未設定：ZERO）
B89: =IF($D89="","",MAX(OFFSET($B$8,0,0,ROW()-ROW($B$8),2))+1) -> 82 | D89: 商品振替高数量（受入） | L89: =VLOOKUP(D89,カラムID辞書!$C$4:$D$1266,2,FALSE) -> SHOHNFURI_I_SU | AB89: =IF(L89="DELDTE","","○") -> ○ | AE89: =IF(AB89="○",IF(AH89="timestamp","now()",IF(LEFT(AH89,9)="character","' '","0")),"") -> 0 | AH89: =VLOOKUP(D89,カラムID辞書!C:H,3,FALSE) -> numeric | AM89: =VLOOKUP(D89,カラムID辞書!C:H,4,FALSE) -> 10 | AO89: =VLOOKUP(D89,カラムID辞書!C:H,6,FALSE) -> 10 | BR89: （未設定：ZERO）
B90: =IF($D90="","",MAX(OFFSET($B$8,0,0,ROW()-ROW($B$8),2))+1) -> 83 | D90: リベート | L90: =VLOOKUP(D90,カラムID辞書!$C$4:$D$1266,2,FALSE) -> REBATE | AB90: =IF(L90="DELDTE","","○") -> ○ | AE90: =IF(AB90="○",IF(AH90="timestamp","now()",IF(LEFT(AH90,9)="character","' '","0")),"") -> 0 | AH90: =VLOOKUP(D90,カラムID辞書!C:H,3,FALSE) -> numeric | AM90: =VLOOKUP(D90,カラムID辞書!C:H,4,FALSE) -> 13 | AO90: =VLOOKUP(D90,カラムID辞書!C:H,6,FALSE) -> 13 | BR90: （未設定：ZERO）
B91: =IF($D91="","",MAX(OFFSET($B$8,0,0,ROW()-ROW($B$8),2))+1) -> 84 | D91: リベート返金 | L91: =VLOOKUP(D91,カラムID辞書!$C$4:$D$1266,2,FALSE) -> REBATE_HENKIN | AB91: =IF(L91="DELDTE","","○") -> ○ | AE91: =IF(AB91="○",IF(AH91="timestamp","now()",IF(LEFT(AH91,9)="character","' '","0")),"") -> 0 | AH91: =VLOOKUP(D91,カラムID辞書!C:H,3,FALSE) -> numeric | AM91: =VLOOKUP(D91,カラムID辞書!C:H,4,FALSE) -> 13 | AO91: =VLOOKUP(D91,カラムID辞書!C:H,6,FALSE) -> 13 | BR91: （未設定：ZERO）
B92: =IF($D92="","",MAX(OFFSET($B$8,0,0,ROW()-ROW($B$8),2))+1) -> 85 | D92: 予備原価１ | L92: =VLOOKUP(D92,カラムID辞書!$C$4:$D$1266,2,FALSE) -> RSV_GNK1 | AB92: =IF(L92="DELDTE","","○") -> ○ | AE92: =IF(AB92="○",IF(AH92="timestamp","now()",IF(LEFT(AH92,9)="character","' '","0")),"") -> 0 | AH92: =VLOOKUP(D92,カラムID辞書!C:H,3,FALSE) -> numeric | AM92: =VLOOKUP(D92,カラムID辞書!C:H,4,FALSE) -> 13 | AO92: =VLOOKUP(D92,カラムID辞書!C:H,6,FALSE) -> 13 | BR92: （未設定：ZERO）
B93: =IF($D93="","",MAX(OFFSET($B$8,0,0,ROW()-ROW($B$8),2))+1) -> 86 | D93: 予備売価１ | L93: =VLOOKUP(D93,カラムID辞書!$C$4:$D$1266,2,FALSE) -> RSV_BIK1 | AB93: =IF(L93="DELDTE","","○") -> ○ | AE93: =IF(AB93="○",IF(AH93="timestamp","now()",IF(LEFT(AH93,9)="character","' '","0")),"") -> 0 | AH93: =VLOOKUP(D93,カラムID辞書!C:H,3,FALSE) -> numeric | AM93: =VLOOKUP(D93,カラムID辞書!C:H,4,FALSE) -> 13 | AO93: =VLOOKUP(D93,カラムID辞書!C:H,6,FALSE) -> 13 | BR93: （未設定：ZERO）
B94: =IF($D94="","",MAX(OFFSET($B$8,0,0,ROW()-ROW($B$8),2))+1) -> 87 | D94: 予備数量１ | L94: =VLOOKUP(D94,カラムID辞書!$C$4:$D$1266,2,FALSE) -> RSV_SU1 | AB94: =IF(L94="DELDTE","","○") -> ○ | AE94: =IF(AB94="○",IF(AH94="timestamp","now()",IF(LEFT(AH94,9)="character","' '","0")),"") -> 0 | AH94: =VLOOKUP(D94,カラムID辞書!C:H,3,FALSE) -> numeric | AM94: =VLOOKUP(D94,カラムID辞書!C:H,4,FALSE) -> 10 | AO94: =VLOOKUP(D94,カラムID辞書!C:H,6,FALSE) -> 10 | BR94: （未設定：ZERO）
B95: =IF($D95="","",MAX(OFFSET($B$8,0,0,ROW()-ROW($B$8),2))+1) -> 88 | D95: 予備原価２ | L95: =VLOOKUP(D95,カラムID辞書!$C$4:$D$1266,2,FALSE) -> RSV_GNK2 | AB95: =IF(L95="DELDTE","","○") -> ○ | AE95: =IF(AB95="○",IF(AH95="timestamp","now()",IF(LEFT(AH95,9)="character","' '","0")),"") -> 0 | AH95: =VLOOKUP(D95,カラムID辞書!C:H,3,FALSE) -> numeric | AM95: =VLOOKUP(D95,カラムID辞書!C:H,4,FALSE) -> 13 | AO95: =VLOOKUP(D95,カラムID辞書!C:H,6,FALSE) -> 13 | BR95: （未設定：ZERO）
... B121: =IF($D121="","",MAX(OFFSET($B$8,0,0,ROW()-ROW($B$8),2))+1) -> 114 | D121: 予備数量１０ | L121: =VLOOKUP(D121,カラムID辞書!$C$4:$D$1266,2,FALSE) -> RSV_SU10 | AB121: =IF(L121="DELDTE","","○") -> ○ | AE121: =IF(AB121="○",IF(AH121="timestamp","now()",IF(LEFT(AH121,9)="character","' '","0")),"") -> 0 | AH121: =VLOOKUP(D121,カラムID辞書!C:H,3,FALSE) -> numeric | AM121: =VLOOKUP(D121,カラムID辞書!C:H,4,FALSE) -> 10 | AO121: =VLOOKUP(D121,カラムID辞書!C:H,6,FALSE) -> 10 | BR121: （未設定：ZERO）
B122: =IF($D122="","",MAX(OFFSET($B$8,0,0,ROW()-ROW($B$8),2))+1) -> 115 | D122: 期首在高原価 | L122: =VLOOKUP(D122,カラムID辞書!$C$4:$D$1266,2,FALSE) -> KISHUZAID_GNK | AB122: =IF(L122="DELDTE","","○") -> ○ | AE122: =IF(AB122="○",IF(AH122="timestamp","now()",IF(LEFT(AH122,9)="character","' '","0")),"") -> 0 | AH122: =VLOOKUP(D122,カラムID辞書!C:H,3,FALSE) -> numeric | AM122: =VLOOKUP(D122,カラムID辞書!C:H,4,FALSE) -> 13 | AO122: =VLOOKUP(D122,カラムID辞書!C:H,6,FALSE) -> 13 | AQ122: 別紙「商品勘定利益計算」参照
B123: =IF($D123="","",MAX(OFFSET($B$8,0,0,ROW()-ROW($B$8),2))+1) -> 116 | D123: 期首在高売価 | L123: =VLOOKUP(D123,カラムID辞書!$C$4:$D$1266,2,FALSE) -> KISHUZAID_BIK | AB123: =IF(L123="DELDTE","","○") -> ○ | AE123: =IF(AB123="○",IF(AH123="timestamp","now()",IF(LEFT(AH123,9)="character","' '","0")),"") -> 0 | AH123: =VLOOKUP(D123,カラムID辞書!C:H,3,FALSE) -> numeric | AM123: =VLOOKUP(D123,カラムID辞書!C:H,4,FALSE) -> 13 | AO123: =VLOOKUP(D123,カラムID辞書!C:H,6,FALSE) -> 13 | AQ123: 別紙「商品勘定利益計算」参照
B124: =IF($D124="","",MAX(OFFSET($B$8,0,0,ROW()-ROW($B$8),2))+1) -> 117 | D124: 期首在高数量 | L124: =VLOOKUP(D124,カラムID辞書!$C$4:$D$1266,2,FALSE) -> KISHUZAID_SU | AB124: =IF(L124="DELDTE","","○") -> ○ | AE124: =IF(AB124="○",IF(AH124="timestamp","now()",IF(LEFT(AH124,9)="character","' '","0")),"") -> 0 | AH124: =VLOOKUP(D124,カラムID辞書!C:H,3,FALSE) -> numeric | AM124: =VLOOKUP(D124,カラムID辞書!C:H,4,FALSE) -> 10 | AO124: =VLOOKUP(D124,カラムID辞書!C:H,6,FALSE) -> 10 | AQ124: 別紙「商品勘定利益計算」参照
B125: =IF($D125="","",MAX(OFFSET($B$8,0,0,ROW()-ROW($B$8),2))+1) -> 118 | D125: 前期繰越評価損 | L125: =VLOOKUP(D125,カラムID辞書!$C$4:$D$1266,2,FALSE) -> ZENKIKRKSHYOKASON | AB125: =IF(L125="DELDTE","","○") -> ○ | AE125: =IF(AB125="○",IF(AH125="timestamp","now()",IF(LEFT(AH125,9)="character","' '","0")),"") -> 0 | AH125: =VLOOKUP(D125,カラムID辞書!C:H,3,FALSE) -> numeric | AM125: =VLOOKUP(D125,カラムID辞書!C:H,4,FALSE) -> 13 | AO125: =VLOOKUP(D125,カラムID辞書!C:H,6,FALSE) -> 13 | AQ125: 別紙「商品勘定利益計算」参照
B126: =IF($D126="","",MAX(OFFSET($B$8,0,0,ROW()-ROW($B$8),2))+1) -> 119 | D126: 期末帳簿在高原価 | L126: =VLOOKUP(D126,カラムID辞書!$C$4:$D$1266,2,FALSE) -> KIMATCHOBZAID_GNK | AB126: =IF(L126="DELDTE","","○") -> ○ | AE126: =IF(AB126="○",IF(AH126="timestamp","now()",IF(LEFT(AH126,9)="character","' '","0")),"") -> 0 | AH126: =VLOOKUP(D126,カラムID辞書!C:H,3,FALSE) -> numeric | AM126: =VLOOKUP(D126,カラムID辞書!C:H,4,FALSE) -> 13 | AO126: =VLOOKUP(D126,カラムID辞書!C:H,6,FALSE) -> 13 | AQ126: 別紙「商品勘定利益計算」参照
B127: =IF($D127="","",MAX(OFFSET($B$8,0,0,ROW()-ROW($B$8),2))+1) -> 120 | D127: 期末帳簿在高売価 | L127: =VLOOKUP(D127,カラムID辞書!$C$4:$D$1266,2,FALSE) -> KIMATCHOBZAID_BIK | AB127: =IF(L127="DELDTE","","○") -> ○ | AE127: =IF(AB127="○",IF(AH127="timestamp","now()",IF(LEFT(AH127,9)="character","' '","0")),"") -> 0 | AH127: =VLOOKUP(D127,カラムID辞書!C:H,3,FALSE) -> numeric | AM127: =VLOOKUP(D127,カラムID辞書!C:H,4,FALSE) -> 13 | AO127: =VLOOKUP(D127,カラムID辞書!C:H,6,FALSE) -> 13 | AQ127: 別紙「商品勘定利益計算」参照
B128: =IF($D128="","",MAX(OFFSET($B$8,0,0,ROW()-ROW($B$8),2))+1) -> 121 | D128: 期末帳簿在高数量 | L128: =VLOOKUP(D128,カラムID辞書!$C$4:$D$1266,2,FALSE) -> KIMATCHOBZAID_SU | AB128: =IF(L128="DELDTE","","○") -> ○ | AE128: =IF(AB128="○",IF(AH128="timestamp","now()",IF(LEFT(AH128,9)="character","' '","0")),"") -> 0 | AH128: =VLOOKUP(D128,カラムID辞書!C:H,3,FALSE) -> numeric | AM128: =VLOOKUP(D128,カラムID辞書!C:H,4,FALSE) -> 10 | AO128: =VLOOKUP(D128,カラムID辞書!C:H,6,FALSE) -> 10 | AQ128: 別紙「商品勘定利益計算」参照
...

Sheet 売価還元単位別年別実績
B2: ユーザインタフェース 設計書 | J2: サブシステム分類 | O2: ドキュメント ID | T2: ドキュメント名 | BK2: 更新者 | BN2: 最終更新日 | BR2: 履歴 | BT2: 作成者 | BW2: 作成日
J3: 商品勘定 | O3: 2.04 | T3: テーブル定義 | BR3: 第1版 | BT3: 富士通 | BW3: 42917
B5: 概念データ名／ID | J5: 売価還元単位別年別実績テーブル | U5: ／ | V5: LBT04_BAIKAN_Y | AD5: OID | AK5: 最大レコード長 | AR5: =ROUNDUP((27+ROUNDUP((MAX(B:B)-COUNTIF(AB:AB,"○"))/8,0)+IF(AF5="",0,4))/8,0)*8+SUM(AO8:AO1028) -> 1770 | AU5: Byte | AW5: 用途 | BB5: 商品勘定実績を年度単位で管理する。
B7: 項番 | D7: 項目論理名称 | L7: 項目物理名称 | T7: PKey | V7: IDX1 | X7: IDX2 | Z7: IDX3 | AB7: NOTNULL | AE7: DEFAULT | AH7: Type | AM7: 桁数 | AO7: Byte | AQ7: 項目説明 | BR7: 備考
B8: 1 | D8: 年 | L8: =VLOOKUP(D8,カラムID辞書!$C$4:$D$1266,2,FALSE) -> NENDO | T8: 1 | AB8: =IF(L8="DELDTE","","○") -> ○ | AE8: =IF(AB8="○",IF(AH8="timestamp","now()",IF(LEFT(AH8,9)="character","' '","0")),"") -> 0 | AH8: =VLOOKUP(D8,カラムID辞書!C:H,3,FALSE) -> numeric | AM8: =VLOOKUP(D8,カラムID辞書!C:H,4,FALSE) -> 6 | AO8: =VLOOKUP(D8,カラムID辞書!C:H,6,FALSE) -> 6 | AQ8: 伝票計上日に該当する期首月（YYYYMM）
B9: =IF($D9="","",MAX(OFFSET($B$8,0,0,ROW()-ROW($B$8),2))+1) -> 2 | D9: システムグループコード | L9: =VLOOKUP(D9,カラムID辞書!$C$4:$D$1266,2,FALSE) -> SYSGRPCD | T9: 2 | AB9: =IF(L9="DELDTE","","○") -> ○ | AE9: =IF(AB9="○",IF(AH9="timestamp","now()",IF(LEFT(AH9,9)="character","' '","0")),"") -> ' ' | AH9: =VLOOKUP(D9,カラムID辞書!C:H,3,FALSE) -> character varying | AM9: =VLOOKUP(D9,カラムID辞書!C:H,4,FALSE) -> 4 | AO9: =VLOOKUP(D9,カラムID辞書!C:H,6,FALSE) -> 4 | AQ9: ユーザ分類コード | BR9: "0010"固定
B10: =IF($D10="","",MAX(OFFSET($B$8,0,0,ROW()-ROW($B$8),2))+1) -> 3 | D10: 企業グループコード | L10: =VLOOKUP(D10,カラムID辞書!$C$4:$D$1266,2,FALSE) -> KGYGRPCD | T10: 3 | AB10: =IF(L10="DELDTE","","○") -> ○ | AE10: =IF(AB10="○",IF(AH10="timestamp","now()",IF(LEFT(AH10,9)="character","' '","0")),"") -> ' ' | AH10: =VLOOKUP(D10,カラムID辞書!C:H,3,FALSE) -> character varying | AM10: =VLOOKUP(D10,カラムID辞書!C:H,4,FALSE) -> 3 | AO10: =VLOOKUP(D10,カラムID辞書!C:H,6,FALSE) -> 3 | AQ10: 売上、仕入伝票の企業グループコード
B11: =IF($D11="","",MAX(OFFSET($B$8,0,0,ROW()-ROW($B$8),2))+1) -> 4 | D11: 店コード | L11: =VLOOKUP(D11,カラムID辞書!$C$4:$D$1266,2,FALSE) -> TENCD | T11: 4 | AB11: =IF(L11="DELDTE","","○") -> ○ | AE11: =IF(AB11="○",IF(AH11="timestamp","now()",IF(LEFT(AH11,9)="character","' '","0")),"") -> ' ' | AH11: =VLOOKUP(D11,カラムID辞書!C:H,3,FALSE) -> character varying | AM11: =VLOOKUP(D11,カラムID辞書!C:H,4,FALSE) -> 4 | AO11: =VLOOKUP(D11,カラムID辞書!C:H,6,FALSE) -> 4 | AQ11: 売上、仕入伝票の店コード
B12: =IF($D12="","",MAX(OFFSET($B$8,0,0,ROW()-ROW($B$8),2))+1) -> 5 | D12: 商品コード１ | L12: =VLOOKUP(D12,カラムID辞書!$C$4:$D$1266,2,FALSE) -> SHOHINCD1 | T12: 5 | AB12: =IF(L12="DELDTE","","○") -> ○ | AE12: =IF(AB12="○",IF(AH12="timestamp","now()",IF(LEFT(AH12,9)="character","' '","0")),"") -> ' ' | AH12: =VLOOKUP(D12,カラムID辞書!C:H,3,FALSE) -> character varying | AM12: =VLOOKUP(D12,カラムID辞書!C:H,4,FALSE) -> 6 | AO12: =VLOOKUP(D12,カラムID辞書!C:H,6,FALSE) -> 6 | AQ12: 売上、仕入伝票の商品コード１ | BR12: 品番
B13: =IF($D13="","",MAX(OFFSET($B$8,0,0,ROW()-ROW($B$8),2))+1) -> 6 | D13: 商品コード２ | L13: =VLOOKUP(D13,カラムID辞書!$C$4:$D$1266,2,FALSE) -> SHOHINCD2 | T13: 6 | AB13: =IF(L13="DELDTE","","○") -> ○ | AE13: =IF(AB13="○",IF(AH13="timestamp","now()",IF(LEFT(AH13,9)="character","' '","0")),"") -> ' ' | AH13: =VLOOKUP(D13,カラムID辞書!C:H,3,FALSE) -> character varying | AM13: =VLOOKUP(D13,カラムID辞書!C:H,4,FALSE) -> 6 | AO13: =VLOOKUP(D13,カラムID辞書!C:H,6,FALSE) -> 6 | AQ13: 売上、仕入伝票の商品コード２ | BR13: （未設定）
B14: =IF($D14="","",MAX(OFFSET($B$8,0,0,ROW()-ROW($B$8),2))+1) -> 7 | D14: 商品コード３ | L14: =VLOOKUP(D14,カラムID辞書!$C$4:$D$1266,2,FALSE) -> SHOHINCD3 | T14: 7 | AB14: =IF(L14="DELDTE","","○") -> ○ | AE14: =IF(AB14="○",IF(AH14="timestamp","now()",IF(LEFT(AH14,9)="character","' '","0")),"") -> ' ' | AH14: =VLOOKUP(D14,カラムID辞書!C:H,3,FALSE) -> character varying | AM14: =VLOOKUP(D14,カラムID辞書!C:H,4,FALSE) -> 6 | AO14: =VLOOKUP(D14,カラムID辞書!C:H,6,FALSE) -> 6 | AQ14: 売上、仕入伝票の商品コード３ | BR14: （未設定）
B15: =IF($D15="","",MAX(OFFSET($B$8,0,0,ROW()-ROW($B$8),2))+1) -> 8 | D15: 商品コード４ | L15: =VLOOKUP(D15,カラムID辞書!$C$4:$D$1266,2,FALSE) -> SHOHINCD4 | T15: 8 | AB15: =IF(L15="DELDTE","","○") -> ○ | AE15: =IF(AB15="○",IF(AH15="timestamp","now()",IF(LEFT(AH15,9)="character","' '","0")),"") -> ' ' | AH15: =VLOOKUP(D15,カラムID辞書!C:H,3,FALSE) -> character varying | AM15: =VLOOKUP(D15,カラムID辞書!C:H,4,FALSE) -> 6 | AO15: =VLOOKUP(D15,カラムID辞書!C:H,6,FALSE) -> 6 | AQ15: 売上、仕入伝票の商品コード４ | BR15: （未設定）
B16: =IF($D16="","",MAX(OFFSET($B$8,0,0,ROW()-ROW($B$8),2))+1) -> 9 | D16: 商品コード５ | L16: =VLOOKUP(D16,カラムID辞書!$C$4:$D$1266,2,FALSE) -> SHOHINCD5 | T16: 9 | AB16: =IF(L16="DELDTE","","○") -> ○ | AE16: =IF(AB16="○",IF(AH16="timestamp","now()",IF(LEFT(AH16,9)="character","' '","0")),"") -> ' ' | AH16: =VLOOKUP(D16,カラムID辞書!C:H,3,FALSE) -> character varying | AM16: =VLOOKUP(D16,カラムID辞書!C:H,4,FALSE) -> 6 | AO16: =VLOOKUP(D16,カラムID辞書!C:H,6,FALSE) -> 6 | AQ16: 売上、仕入伝票の商品コード５ | BR16: （未設定）
B17: =IF($D17="","",MAX(OFFSET($B$8,0,0,ROW()-ROW($B$8),2))+1) -> 10 | D17: 細別コード１ | L17: =VLOOKUP(D17,カラムID辞書!$C$4:$D$1266,2,FALSE) -> SIBTCD1 | T17: 10 | AB17: =IF(L17="DELDTE","","○") -> ○ | AE17: =IF(AB17="○",IF(AH17="timestamp","now()",IF(LEFT(AH17,9)="character","' '","0")),"") -> ' ' | AH17: =VLOOKUP(D17,カラムID辞書!C:H,3,FALSE) -> character varying | AM17: =VLOOKUP(D17,カラムID辞書!C:H,4,FALSE) -> 10 | AO17: =VLOOKUP(D17,カラムID辞書!C:H,6,FALSE) -> 10 | AQ17: 売上、仕入伝票の細別コード１ | BR17: （未設定）
B18: =IF($D18="","",MAX(OFFSET($B$8,0,0,ROW()-ROW($B$8),2))+1) -> 11 | D18: 細別コード２ | L18: =VLOOKUP(D18,カラムID辞書!$C$4:$D$1266,2,FALSE) -> SIBTCD2 | T18: 11 | AB18: =IF(L18="DELDTE","","○") -> ○ | AE18: =IF(AB18="○",IF(AH18="timestamp","now()",IF(LEFT(AH18,9)="character","' '","0")),"") -> ' ' | AH18: =VLOOKUP(D18,カラムID辞書!C:H,3,FALSE) -> character varying | AM18: =VLOOKUP(D18,カラムID辞書!C:H,4,FALSE) -> 10 | AO18: =VLOOKUP(D18,カラムID辞書!C:H,6,FALSE) -> 10 | AQ18: 売上、仕入伝票の細別コード２ | BR18: （未設定）
B19: =IF($D19="","",MAX(OFFSET($B$8,0,0,ROW()-ROW($B$8),2))+1) -> 12 | D19: 単品コード１ | L19: =VLOOKUP(D19,カラムID辞書!$C$4:$D$1266,2,FALSE) -> TNPNCD1 | T19: 12 | AB19: =IF(L19="DELDTE","","○") -> ○ | AE19: =IF(AB19="○",IF(AH19="timestamp","now()",IF(LEFT(AH19,9)="character","' '","0")),"") -> ' ' | AH19: =VLOOKUP(D19,カラムID辞書!C:H,3,FALSE) -> character varying | AM19: =VLOOKUP(D19,カラムID辞書!C:H,4,FALSE) -> 13 | AO19: =VLOOKUP(D19,カラムID辞書!C:H,6,FALSE) -> 13 | AQ19: 売上、仕入伝票の単品コード１ | BR19: （未設定）
B20: =IF($D20="","",MAX(OFFSET($B$8,0,0,ROW()-ROW($B$8),2))+1) -> 13 | D20: 単品コード２ | L20: =VLOOKUP(D20,カラムID辞書!$C$4:$D$1266,2,FALSE) -> TNPNCD2 | T20: 13 | AB20: =IF(L20="DELDTE","","○") -> ○ | AE20: =IF(AB20="○",IF(AH20="timestamp","now()",IF(LEFT(AH20,9)="character","' '","0")),"") -> ' ' | AH20: =VLOOKUP(D20,カラムID辞書!C:H,3,FALSE) -> character varying | AM20: =VLOOKUP(D20,カラムID辞書!C:H,4,FALSE) -> 13 | AO20: =VLOOKUP(D20,カラムID辞書!C:H,6,FALSE) -> 13 | AQ20: 売上、仕入伝票の単品コード２ | BR20: （未設定）
B21: =IF($D21="","",MAX(OFFSET($B$8,0,0,ROW()-ROW($B$8),2))+1) -> 14 | D21: 仕入区分 | L21: =VLOOKUP(D21,カラムID辞書!$C$4:$D$1266,2,FALSE) -> SHIIREKBN | T21: 14 | AB21: =IF(L21="DELDTE","","○") -> ○ | AE21: =IF(AB21="○",IF(AH21="timestamp","now()",IF(LEFT(AH21,9)="character","' '","0")),"") -> ' ' | AH21: =VLOOKUP(D21,カラムID辞書!C:H,3,FALSE) -> character varying | AM21: =VLOOKUP(D21,カラムID辞書!C:H,4,FALSE) -> 2 | AO21: =VLOOKUP(D21,カラムID辞書!C:H,6,FALSE) -> 2 | AQ21: 01：直扱 / 04：売仕
B22: =IF($D22="","",MAX(OFFSET($B$8,0,0,ROW()-ROW($B$8),2))+1) -> 15 | D22: 原価管理区分 | L22: =VLOOKUP(D22,カラムID辞書!$C$4:$D$1266,2,FALSE) -> GNKKBN | T22: 15 | AB22: =IF(L22="DELDTE","","○") -> ○ | AE22: =IF(AB22="○",IF(AH22="timestamp","now()",IF(LEFT(AH22,9)="character","' '","0")),"") -> ' ' | AH22: =VLOOKUP(D22,カラムID辞書!C:H,3,FALSE) -> character varying | AM22: =VLOOKUP(D22,カラムID辞書!C:H,4,FALSE) -> 1 | AO22: =VLOOKUP(D22,カラムID辞書!C:H,6,FALSE) -> 1 | AQ22: 1：売価品 / 2：原価品
B23: =IF($D23="","",MAX(OFFSET($B$8,0,0,ROW()-ROW($B$8),2))+1) -> 16 | D23: ＤＳ区分 | L23: =VLOOKUP(D23,カラムID辞書!$C$4:$D$1266,2,FALSE) -> DSKBN | T23: 16 | AB23: =IF(L23="DELDTE","","○") -> ○ | AE23: =IF(AB23="○",IF(AH23="timestamp","now()",IF(LEFT(AH23,9)="character","' '","0")),"") -> ' ' | AH23: =VLOOKUP(D23,カラムID辞書!C:H,3,FALSE) -> character varying | AM23: =VLOOKUP(D23,カラムID辞書!C:H,4,FALSE) -> 1 | AO23: =VLOOKUP(D23,カラムID辞書!C:H,6,FALSE) -> 1 | AQ23: 0：プロパー / 1：セール
B24: =IF($D24="","",MAX(OFFSET($B$8,0,0,ROW()-ROW($B$8),2))+1) -> 17 | D24: 利益計算式区分 | L24: =VLOOKUP(D24,カラムID辞書!$C$4:$D$1266,2,FALSE) -> RIEKICMPKBN | T24: 17 | AB24: =IF(L24="DELDTE","","○") -> ○ | AE24: =IF(AB24="○",IF(AH24="timestamp","now()",IF(LEFT(AH24,9)="character","' '","0")),"") -> ' ' | AH24: =VLOOKUP(D24,カラムID辞書!C:H,3,FALSE) -> character varying | AM24: =VLOOKUP(D24,カラムID辞書!C:H,4,FALSE) -> 1 | AO24: =VLOOKUP(D24,カラムID辞書!C:H,6,FALSE) -> 1 | AQ24: 0：利益計算対象外 / 1：売価還元原価法 / 3：売仕原価計算 /7：原価品計算
B25: =IF($D25="","",MAX(OFFSET($B$8,0,0,ROW()-ROW($B$8),2))+1) -> 18 | D25: 売上高原価 | L25: =VLOOKUP(D25,カラムID辞書!$C$4:$D$1266,2,FALSE) -> URIAGED_GNK | AB25: =IF(L25="DELDTE","","○") -> ○ | AE25: =IF(AB25="○",IF(AH25="timestamp","now()",IF(LEFT(AH25,9)="character","' '","0")),"") -> 0 | AH25: =VLOOKUP(D25,カラムID辞書!C:H,3,FALSE) -> numeric | AM25: =VLOOKUP(D25,カラムID辞書!C:H,4,FALSE) -> 13 | AO25: =VLOOKUP(D25,カラムID辞書!C:H,6,FALSE) -> 13 | AQ25: 別紙「商品勘定利益計算」参照
B26: =IF($D26="","",MAX(OFFSET($B$8,0,0,ROW()-ROW($B$8),2))+1) -> 19 | D26: 売上高売価 | L26: =VLOOKUP(D26,カラムID辞書!$C$4:$D$1266,2,FALSE) -> URIAGED_BIK | AB26: =IF(L26="DELDTE","","○") -> ○ | AE26: =IF(AB26="○",IF(AH26="timestamp","now()",IF(LEFT(AH26,9)="character","' '","0")),"") -> 0 | AH26: =VLOOKUP(D26,カラムID辞書!C:H,3,FALSE) -> numeric | AM26: =VLOOKUP(D26,カラムID辞書!C:H,4,FALSE) -> 13 | AO26: =VLOOKUP(D26,カラムID辞書!C:H,6,FALSE) -> 13 | AQ26: 売上伝票の売上高集計値（総売上高）
B27: =IF($D27="","",MAX(OFFSET($B$8,0,0,ROW()-ROW($B$8),2))+1) -> 20 | D27: 売上高分類１ | L27: =VLOOKUP(D27,カラムID辞書!$C$4:$D$1266,2,FALSE) -> URIAGED_BNRI1 | AB27: =IF(L27="DELDTE","","○") -> ○ | AE27: =IF(AB27="○",IF(AH27="timestamp","now()",IF(LEFT(AH27,9)="character","' '","0")),"") -> 0 | AH27: =VLOOKUP(D27,カラムID辞書!C:H,3,FALSE) -> numeric | AM27: =VLOOKUP(D27,カラムID辞書!C:H,4,FALSE) -> 13 | AO27: =VLOOKUP(D27,カラムID辞書!C:H,6,FALSE) -> 13 | AQ27: 売上伝票の売上高集計値（店頭・普通品）
B28: =IF($D28="","",MAX(OFFSET($B$8,0,0,ROW()-ROW($B$8),2))+1) -> 21 | D28: 売上高分類２ | L28: =VLOOKUP(D28,カラムID辞書!$C$4:$D$1266,2,FALSE) -> URIAGED_BNRI2 | AB28: =IF(L28="DELDTE","","○") -> ○ | AE28: =IF(AB28="○",IF(AH28="timestamp","now()",IF(LEFT(AH28,9)="character","' '","0")),"") -> 0 | AH28: =VLOOKUP(D28,カラムID辞書!C:H,3,FALSE) -> numeric | AM28: =VLOOKUP(D28,カラムID辞書!C:H,4,FALSE) -> 13 | AO28: =VLOOKUP(D28,カラムID辞書!C:H,6,FALSE) -> 13 | AQ28: 売上伝票の売上高集計値（店頭・催事）
B29: =IF($D29="","",MAX(OFFSET($B$8,0,0,ROW()-ROW($B$8),2))+1) -> 22 | D29: 売上高分類３ | L29: =VLOOKUP(D29,カラムID辞書!$C$4:$D$1266,2,FALSE) -> URIAGED_BNRI3 | AB29: =IF(L29="DELDTE","","○") -> ○ | AE29: =IF(AB29="○",IF(AH29="timestamp","now()",IF(LEFT(AH29,9)="character","' '","0")),"") -> 0 | AH29: =VLOOKUP(D29,カラムID辞書!C:H,3,FALSE) -> numeric | AM29: =VLOOKUP(D29,カラムID辞書!C:H,4,FALSE) -> 13 | AO29: =VLOOKUP(D29,カラムID辞書!C:H,6,FALSE) -> 13 | AQ29: 売上伝票の売上高集計値（店頭・店外）
B30: =IF($D30="","",MAX(OFFSET($B$8,0,0,ROW()-ROW($B$8),2))+1) -> 23 | D30: 売上高分類４ | L30: =VLOOKUP(D30,カラムID辞書!$C$4:$D$1266,2,FALSE) -> URIAGED_BNRI4 | AB30: =IF(L30="DELDTE","","○") -> ○ | AE30: =IF(AB30="○",IF(AH30="timestamp","now()",IF(LEFT(AH30,9)="character","' '","0")),"") -> 0 | AH30: =VLOOKUP(D30,カラムID辞書!C:H,3,FALSE) -> numeric | AM30: =VLOOKUP(D30,カラムID辞書!C:H,4,FALSE) -> 13 | AO30: =VLOOKUP(D30,カラムID辞書!C:H,6,FALSE) -> 13 | AQ30: 売上伝票の売上高集計値（店頭・ギフト）
B31: =IF($D31="","",MAX(OFFSET($B$8,0,0,ROW()-ROW($B$8),2))+1) -> 24 | D31: 売上高分類５ | L31: =VLOOKUP(D31,カラムID辞書!$C$4:$D$1266,2,FALSE) -> URIAGED_BNRI5 | AB31: =IF(L31="DELDTE","","○") -> ○ | AE31: =IF(AB31="○",IF(AH31="timestamp","now()",IF(LEFT(AH31,9)="character","' '","0")),"") -> 0 | AH31: =VLOOKUP(D31,カラムID辞書!C:H,3,FALSE) -> numeric | AM31: =VLOOKUP(D31,カラムID辞書!C:H,4,FALSE) -> 13 | AO31: =VLOOKUP(D31,カラムID辞書!C:H,6,FALSE) -> 13 | AQ31: 売上伝票の売上高集計値（店頭・ネット）
B32: =IF($D32="","",MAX(OFFSET($B$8,0,0,ROW()-ROW($B$8),2))+1) -> 25 | D32: 売上高分類６ | L32: =VLOOKUP(D32,カラムID辞書!$C$4:$D$1266,2,FALSE) -> URIAGED_BNRI6 | AB32: =IF(L32="DELDTE","","○") -> ○ | AE32: =IF(AB32="○",IF(AH32="timestamp","now()",IF(LEFT(AH32,9)="character","' '","0")),"") -> 0 | AH32: =VLOOKUP(D32,カラムID辞書!C:H,3,FALSE) -> numeric | AM32: =VLOOKUP(D32,カラムID辞書!C:H,4,FALSE) -> 13 | AO32: =VLOOKUP(D32,カラムID辞書!C:H,6,FALSE) -> 13 | AQ32: 売上伝票の売上高集計値（店頭・その他）
B33: =IF($D33="","",MAX(OFFSET($B$8,0,0,ROW()-ROW($B$8),2))+1) -> 26 | D33: 売上高分類７ | L33: =VLOOKUP(D33,カラムID辞書!$C$4:$D$1266,2,FALSE) -> URIAGED_BNRI7 | AB33: =IF(L33="DELDTE","","○") -> ○ | AE33: =IF(AB33="○",IF(AH33="timestamp","now()",IF(LEFT(AH33,9)="character","' '","0")),"") -> 0 | AH33: =VLOOKUP(D33,カラムID辞書!C:H,3,FALSE) -> numeric | AM33: =VLOOKUP(D33,カラムID辞書!C:H,4,FALSE) -> 13 | AO33: =VLOOKUP(D33,カラムID辞書!C:H,6,FALSE) -> 13 | AQ33: 売上伝票の売上高集計値（非店頭・店外）
B34: =IF($D34="","",MAX(OFFSET($B$8,0,0,ROW()-ROW($B$8),2))+1) -> 27 | D34: 売上高分類８ | L34: =VLOOKUP(D34,カラムID辞書!$C$4:$D$1266,2,FALSE) -> URIAGED_BNRI8 | AB34: =IF(L34="DELDTE","","○") -> ○ | AE34: =IF(AB34="○",IF(AH34="timestamp","now()",IF(LEFT(AH34,9)="character","' '","0")),"") -> 0 | AH34: =VLOOKUP(D34,カラムID辞書!C:H,3,FALSE) -> numeric | AM34: =VLOOKUP(D34,カラムID辞書!C:H,4,FALSE) -> 13 | AO34: =VLOOKUP(D34,カラムID辞書!C:H,6,FALSE) -> 13 | AQ34: 売上伝票の売上高集計値（非店頭・ギフト）
B35: =IF($D35="","",MAX(OFFSET($B$8,0,0,ROW()-ROW($B$8),2))+1) -> 28 | D35: 売上高分類９ | L35: =VLOOKUP(D35,カラムID辞書!$C$4:$D$1266,2,FALSE) -> URIAGED_BNRI9 | AB35: =IF(L35="DELDTE","","○") -> ○ | AE35: =IF(AB35="○",IF(AH35="timestamp","now()",IF(LEFT(AH35,9)="character","' '","0")),"") -> 0 | AH35: =VLOOKUP(D35,カラムID辞書!C:H,3,FALSE) -> numeric | AM35: =VLOOKUP(D35,カラムID辞書!C:H,4,FALSE) -> 13 | AO35: =VLOOKUP(D35,カラムID辞書!C:H,6,FALSE) -> 13 | AQ35: 売上伝票の売上高集計値（非店頭・その他）
B36: =IF($D36="","",MAX(OFFSET($B$8,0,0,ROW()-ROW($B$8),2))+1) -> 29 | D36: 売上高分類１０ | L36: =VLOOKUP(D36,カラムID辞書!$C$4:$D$1266,2,FALSE) -> URIAGED_BNRI10 | AB36: =IF(L36="DELDTE","","○") -> ○ | AE36: =IF(AB36="○",IF(AH36="timestamp","now()",IF(LEFT(AH36,9)="character","' '","0")),"") -> 0 | AH36: =VLOOKUP(D36,カラムID辞書!C:H,3,FALSE) -> numeric | AM36: =VLOOKUP(D36,カラムID辞書!C:H,4,FALSE) -> 13 | AO36: =VLOOKUP(D36,カラムID辞書!C:H,6,FALSE) -> 13 | BR36: （未設定：ZERO）
B37: =IF($D37="","",MAX(OFFSET($B$8,0,0,ROW()-ROW($B$8),2))+1) -> 30 | D37: 売上高数量 | L37: =VLOOKUP(D37,カラムID辞書!$C$4:$D$1266,2,FALSE) -> URIAGED_SU | AB37: =IF(L37="DELDTE","","○") -> ○ | AE37: =IF(AB37="○",IF(AH37="timestamp","now()",IF(LEFT(AH37,9)="character","' '","0")),"") -> 0 | AH37: =VLOOKUP(D37,カラムID辞書!C:H,3,FALSE) -> numeric | AM37: =VLOOKUP(D37,カラムID辞書!C:H,4,FALSE) -> 10 | AO37: =VLOOKUP(D37,カラムID辞書!C:H,6,FALSE) -> 10 | AQ37: 売上伝票の売上数量集計値
B38: =IF($D38="","",MAX(OFFSET($B$8,0,0,ROW()-ROW($B$8),2))+1) -> 31 | D38: 利益高 | L38: =VLOOKUP(D38,カラムID辞書!$C$4:$D$1266,2,FALSE) -> RIEKID | AB38: =IF(L38="DELDTE","","○") -> ○ | AE38: =IF(AB38="○",IF(AH38="timestamp","now()",IF(LEFT(AH38,9)="character","' '","0")),"") -> 0 | AH38: =VLOOKUP(D38,カラムID辞書!C:H,3,FALSE) -> numeric | AM38: =VLOOKUP(D38,カラムID辞書!C:H,4,FALSE) -> 13 | AO38: =VLOOKUP(D38,カラムID辞書!C:H,6,FALSE) -> 13 | AQ38: 別紙「商品勘定利益計算」参照 | BR38: 売益金
B39: =IF($D39="","",MAX(OFFSET($B$8,0,0,ROW()-ROW($B$8),2))+1) -> 32 | D39: 割引額 | L39: =VLOOKUP(D39,カラムID辞書!$C$4:$D$1266,2,FALSE) -> WARIBIKI_GAK | AB39: =IF(L39="DELDTE","","○") -> ○ | AE39: =IF(AB39="○",IF(AH39="timestamp","now()",IF(LEFT(AH39,9)="character","' '","0")),"") -> 0 | AH39: =VLOOKUP(D39,カラムID辞書!C:H,3,FALSE) -> numeric | AM39: =VLOOKUP(D39,カラムID辞書!C:H,4,FALSE) -> 13 | AO39: =VLOOKUP(D39,カラムID辞書!C:H,6,FALSE) -> 13 | AQ39: 売上伝票の割引額集計値
B40: =IF($D40="","",MAX(OFFSET($B$8,0,0,ROW()-ROW($B$8),2))+1) -> 33 | D40: 値引額 | L40: =VLOOKUP(D40,カラムID辞書!$C$4:$D$1266,2,FALSE) -> NEBIKI_GAK | AB40: =IF(L40="DELDTE","","○") -> ○ | AE40: =IF(AB40="○",IF(AH40="timestamp","now()",IF(LEFT(AH40,9)="character","' '","0")),"") -> 0 | AH40: =VLOOKUP(D40,カラムID辞書!C:H,3,FALSE) -> numeric | AM40: =VLOOKUP(D40,カラムID辞書!C:H,4,FALSE) -> 13 | AO40: =VLOOKUP(D40,カラムID辞書!C:H,6,FALSE) -> 13 | AQ40: 売上伝票の値引額集計値
B41: =IF($D41="","",MAX(OFFSET($B$8,0,0,ROW()-ROW($B$8),2))+1) -> 34 | D41: 客数１ | L41: =VLOOKUP(D41,カラムID辞書!$C$4:$D$1266,2,FALSE) -> KYAKU1_SU | AB41: =IF(L41="DELDTE","","○") -> ○ | AE41: =IF(AB41="○",IF(AH41="timestamp","now()",IF(LEFT(AH41,9)="character","' '","0")),"") -> 0 | AH41: =VLOOKUP(D41,カラムID辞書!C:H,3,FALSE) -> numeric | AM41: =VLOOKUP(D41,カラムID辞書!C:H,4,FALSE) -> 10,2 | AO41: =VLOOKUP(D41,カラムID辞書!C:H,6,FALSE) -> 10 | AQ41: 売上伝票の客数１集計値
B42: =IF($D42="","",MAX(OFFSET($B$8,0,0,ROW()-ROW($B$8),2))+1) -> 35 | D42: 客数２ | L42: =VLOOKUP(D42,カラムID辞書!$C$4:$D$1266,2,FALSE) -> KYAKU2_SU | AB42: =IF(L42="DELDTE","","○") -> ○ | AE42: =IF(AB42="○",IF(AH42="timestamp","now()",IF(LEFT(AH42,9)="character","' '","0")),"") -> 0 | AH42: =VLOOKUP(D42,カラムID辞書!C:H,3,FALSE) -> numeric | AM42: =VLOOKUP(D42,カラムID辞書!C:H,4,FALSE) -> 10,2 | AO42: =VLOOKUP(D42,カラムID辞書!C:H,6,FALSE) -> 10 | AQ42: 売上伝票の客数２集計値
B43: =IF($D43="","",MAX(OFFSET($B$8,0,0,ROW()-ROW($B$8),2))+1) -> 36 | D43: 客数３ | L43: =VLOOKUP(D43,カラムID辞書!$C$4:$D$1266,2,FALSE) -> KYAKU3_SU | AB43: =IF(L43="DELDTE","","○") -> ○ | AE43: =IF(AB43="○",IF(AH43="timestamp","now()",IF(LEFT(AH43,9)="character","' '","0")),"") -> 0 | AH43: =VLOOKUP(D43,カラムID辞書!C:H,3,FALSE) -> numeric | AM43: =VLOOKUP(D43,カラムID辞書!C:H,4,FALSE) -> 10,2 | AO43: =VLOOKUP(D43,カラムID辞書!C:H,6,FALSE) -> 10 | AQ43: 売上伝票の客数３集計値 | BR43: （未設定：ZERO）
B44: =IF($D44="","",MAX(OFFSET($B$8,0,0,ROW()-ROW($B$8),2))+1) -> 37 | D44: 純仕入高原価 | L44: =VLOOKUP(D44,カラムID辞書!$C$4:$D$1266,2,FALSE) -> JNSHIIRED_GNK | AB44: =IF(L44="DELDTE","","○") -> ○ | AE44: =IF(AB44="○",IF(AH44="timestamp","now()",IF(LEFT(AH44,9)="character","' '","0")),"") -> 0 | AH44: =VLOOKUP(D44,カラムID辞書!C:H,3,FALSE) -> numeric | AM44: =VLOOKUP(D44,カラムID辞書!C:H,4,FALSE) -> 13 | AO44: =VLOOKUP(D44,カラムID辞書!C:H,6,FALSE) -> 13 | AQ44: 別紙「商品勘定利益計算」参照
B45: =IF($D45="","",MAX(OFFSET($B$8,0,0,ROW()-ROW($B$8),2))+1) -> 38 | D45: 純仕入高売価 | L45: =VLOOKUP(D45,カラムID辞書!$C$4:$D$1266,2,FALSE) -> JNSHIIRED_BIK | AB45: =IF(L45="DELDTE","","○") -> ○ | AE45: =IF(AB45="○",IF(AH45="timestamp","now()",IF(LEFT(AH45,9)="character","' '","0")),"") -> 0 | AH45: =VLOOKUP(D45,カラムID辞書!C:H,3,FALSE) -> numeric | AM45: =VLOOKUP(D45,カラムID辞書!C:H,4,FALSE) -> 13 | AO45: =VLOOKUP(D45,カラムID辞書!C:H,6,FALSE) -> 13 | AQ45: 別紙「商品勘定利益計算」参照
B46: =IF($D46="","",MAX(OFFSET($B$8,0,0,ROW()-ROW($B$8),2))+1) -> 39 | D46: 純仕入高数量 | L46: =VLOOKUP(D46,カラムID辞書!$C$4:$D$1266,2,FALSE) -> JNSHIIRED_SU | AB46: =IF(L46="DELDTE","","○") -> ○ | AE46: =IF(AB46="○",IF(AH46="timestamp","now()",IF(LEFT(AH46,9)="character","' '","0")),"") -> 0 | AH46: =VLOOKUP(D46,カラムID辞書!C:H,3,FALSE) -> numeric | AM46: =VLOOKUP(D46,カラムID辞書!C:H,4,FALSE) -> 10 | AO46: =VLOOKUP(D46,カラムID辞書!C:H,6,FALSE) -> 10 | AQ46: 別紙「商品勘定利益計算」参照
B47: =IF($D47="","",MAX(OFFSET($B$8,0,0,ROW()-ROW($B$8),2))+1) -> 40 | D47: 仕入高原価 | L47: =VLOOKUP(D47,カラムID辞書!$C$4:$D$1266,2,FALSE) -> SHIIRED_GNK | AB47: =IF(L47="DELDTE","","○") -> ○ | AE47: =IF(AB47="○",IF(AH47="timestamp","now()",IF(LEFT(AH47,9)="character","' '","0")),"") -> 0 | AH47: =VLOOKUP(D47,カラムID辞書!C:H,3,FALSE) -> numeric | AM47: =VLOOKUP(D47,カラムID辞書!C:H,4,FALSE) -> 13 | AO47: =VLOOKUP(D47,カラムID辞書!C:H,6,FALSE) -> 13 | AQ47: 仕入伝票の原価集計値
B48: =IF($D48="","",MAX(OFFSET($B$8,0,0,ROW()-ROW($B$8),2))+1) -> 41 | D48: 仕入高売価 | L48: =VLOOKUP(D48,カラムID辞書!$C$4:$D$1266,2,FALSE) -> SHIIRED_BIK | AB48: =IF(L48="DELDTE","","○") -> ○ | AE48: =IF(AB48="○",IF(AH48="timestamp","now()",IF(LEFT(AH48,9)="character","' '","0")),"") -> 0 | AH48: =VLOOKUP(D48,カラムID辞書!C:H,3,FALSE) -> numeric | AM48: =VLOOKUP(D48,カラムID辞書!C:H,4,FALSE) -> 13 | AO48: =VLOOKUP(D48,カラムID辞書!C:H,6,FALSE) -> 13 | AQ48: 仕入伝票の売価集計値
B49: =IF($D49="","",MAX(OFFSET($B$8,0,0,ROW()-ROW($B$8),2))+1) -> 42 | D49: 仕入高数量 | L49: =VLOOKUP(D49,カラムID辞書!$C$4:$D$1266,2,FALSE) -> SHIIRED_SU | AB49: =IF(L49="DELDTE","","○") -> ○ | AE49: =IF(AB49="○",IF(AH49="timestamp","now()",IF(LEFT(AH49,9)="character","' '","0")),"") -> 0 | AH49: =VLOOKUP(D49,カラムID辞書!C:H,3,FALSE) -> numeric | AM49: =VLOOKUP(D49,カラムID辞書!C:H,4,FALSE) -> 10 | AO49: =VLOOKUP(D49,カラムID辞書!C:H,6,FALSE) -> 10 | AQ49: 仕入伝票の数量集計値
B50: =IF($D50="","",MAX(OFFSET($B$8,0,0,ROW()-ROW($B$8),2))+1) -> 43 | D50: 付帯仕入高原価 | L50: =VLOOKUP(D50,カラムID辞書!$C$4:$D$1266,2,FALSE) -> FUTAISHIIRED_GNK | AB50: =IF(L50="DELDTE","","○") -> ○ | AE50: =IF(AB50="○",IF(AH50="timestamp","now()",IF(LEFT(AH50,9)="character","' '","0")),"") -> 0 | AH50: =VLOOKUP(D50,カラムID辞書!C:H,3,FALSE) -> numeric | AM50: =VLOOKUP(D50,カラムID辞書!C:H,4,FALSE) -> 13 | AO50: =VLOOKUP(D50,カラムID辞書!C:H,6,FALSE) -> 13 | BR50: （未設定：ZERO）
B51: =IF($D51="","",MAX(OFFSET($B$8,0,0,ROW()-ROW($B$8),2))+1) -> 44 | D51: 返品高原価 | L51: =VLOOKUP(D51,カラムID辞書!$C$4:$D$1266,2,FALSE) -> HENPND_GNK | AB51: =IF(L51="DELDTE","","○") -> ○ | AE51: =IF(AB51="○",IF(AH51="timestamp","now()",IF(LEFT(AH51,9)="character","' '","0")),"") -> 0 | AH51: =VLOOKUP(D51,カラムID辞書!C:H,3,FALSE) -> numeric | AM51: =VLOOKUP(D51,カラムID辞書!C:H,4,FALSE) -> 13 | AO51: =VLOOKUP(D51,カラムID辞書!C:H,6,FALSE) -> 13 | AQ51: 返品伝票の原価集計値
B52: =IF($D52="","",MAX(OFFSET($B$8,0,0,ROW()-ROW($B$8),2))+1) -> 45 | D52: 返品高売価 | L52: =VLOOKUP(D52,カラムID辞書!$C$4:$D$1266,2,FALSE) -> HENPND_BIK | AB52: =IF(L52="DELDTE","","○") -> ○ | AE52: =IF(AB52="○",IF(AH52="timestamp","now()",IF(LEFT(AH52,9)="character","' '","0")),"") -> 0 | AH52: =VLOOKUP(D52,カラムID辞書!C:H,3,FALSE) -> numeric | AM52: =VLOOKUP(D52,カラムID辞書!C:H,4,FALSE) -> 13 | AO52: =VLOOKUP(D52,カラムID辞書!C:H,6,FALSE) -> 13 | AQ52: 返品伝票の売価集計値
B53: =IF($D53="","",MAX(OFFSET($B$8,0,0,ROW()-ROW($B$8),2))+1) -> 46 | D53: 返品高数量 | L53: =VLOOKUP(D53,カラムID辞書!$C$4:$D$1266,2,FALSE) -> HENPND_SU | AB53: =IF(L53="DELDTE","","○") -> ○ | AE53: =IF(AB53="○",IF(AH53="timestamp","now()",IF(LEFT(AH53,9)="character","' '","0")),"") -> 0 | AH53: =VLOOKUP(D53,カラムID辞書!C:H,3,FALSE) -> numeric | AM53: =VLOOKUP(D53,カラムID辞書!C:H,4,FALSE) -> 10 | AO53: =VLOOKUP(D53,カラムID辞書!C:H,6,FALSE) -> 10 | AQ53: 返品伝票の数量集計値
B54: =IF($D54="","",MAX(OFFSET($B$8,0,0,ROW()-ROW($B$8),2))+1) -> 47 | D54: 付帯返品高原価 | L54: =VLOOKUP(D54,カラムID辞書!$C$4:$D$1266,2,FALSE) -> FUTAIHENPND_GNK | AB54: =IF(L54="DELDTE","","○") -> ○ | AE54: =IF(AB54="○",IF(AH54="timestamp","now()",IF(LEFT(AH54,9)="character","' '","0")),"") -> 0 | AH54: =VLOOKUP(D54,カラムID辞書!C:H,3,FALSE) -> numeric | AM54: =VLOOKUP(D54,カラムID辞書!C:H,4,FALSE) -> 13 | AO54: =VLOOKUP(D54,カラムID辞書!C:H,6,FALSE) -> 13 | BR54: （未設定：ZERO）
B55: =IF($D55="","",MAX(OFFSET($B$8,0,0,ROW()-ROW($B$8),2))+1) -> 48 | D55: 価格訂正仕入高原価 | L55: =VLOOKUP(D55,カラムID辞書!$C$4:$D$1266,2,FALSE) -> TEISEISHIIRED_GNK | AB55: =IF(L55="DELDTE","","○") -> ○ | AE55: =IF(AB55="○",IF(AH55="timestamp","now()",IF(LEFT(AH55,9)="character","' '","0")),"") -> 0 | AH55: =VLOOKUP(D55,カラムID辞書!C:H,3,FALSE) -> numeric | AM55: =VLOOKUP(D55,カラムID辞書!C:H,4,FALSE) -> 13 | AO55: =VLOOKUP(D55,カラムID辞書!C:H,6,FALSE) -> 13 | AQ55: 価格変更による再仕入伝票の原価集計値
B56: =IF($D56="","",MAX(OFFSET($B$8,0,0,ROW()-ROW($B$8),2))+1) -> 49 | D56: 価格訂正仕入高売価 | L56: =VLOOKUP(D56,カラムID辞書!$C$4:$D$1266,2,FALSE) -> TEISEISHIIRED_BIK | AB56: =IF(L56="DELDTE","","○") -> ○ | AE56: =IF(AB56="○",IF(AH56="timestamp","now()",IF(LEFT(AH56,9)="character","' '","0")),"") -> 0 | AH56: =VLOOKUP(D56,カラムID辞書!C:H,3,FALSE) -> numeric | AM56: =VLOOKUP(D56,カラムID辞書!C:H,4,FALSE) -> 13 | AO56: =VLOOKUP(D56,カラムID辞書!C:H,6,FALSE) -> 13 | AQ56: 価格変更による再仕入伝票の売価集計値
B57: =IF($D57="","",MAX(OFFSET($B$8,0,0,ROW()-ROW($B$8),2))+1) -> 50 | D57: 価格訂正仕入高数量 | L57: =VLOOKUP(D57,カラムID辞書!$C$4:$D$1266,2,FALSE) -> TEISEISHIIRED_SU | AB57: =IF(L57="DELDTE","","○") -> ○ | AE57: =IF(AB57="○",IF(AH57="timestamp","now()",IF(LEFT(AH57,9)="character","' '","0")),"") -> 0 | AH57: =VLOOKUP(D57,カラムID辞書!C:H,3,FALSE) -> numeric | AM57: =VLOOKUP(D57,カラムID辞書!C:H,4,FALSE) -> 10 | AO57: =VLOOKUP(D57,カラムID辞書!C:H,6,FALSE) -> 10 | AQ57: 価格変更による再仕入伝票の数量集計値
B58: =IF($D58="","",MAX(OFFSET($B$8,0,0,ROW()-ROW($B$8),2))+1) -> 51 | D58: 価格訂正返品高原価 | L58: =VLOOKUP(D58,カラムID辞書!$C$4:$D$1266,2,FALSE) -> TEISEIHENPIND_GNK | AB58: =IF(L58="DELDTE","","○") -> ○ | AE58: =IF(AB58="○",IF(AH58="timestamp","now()",IF(LEFT(AH58,9)="character","' '","0")),"") -> 0 | AH58: =VLOOKUP(D58,カラムID辞書!C:H,3,FALSE) -> numeric | AM58: =VLOOKUP(D58,カラムID辞書!C:H,4,FALSE) -> 13 | AO58: =VLOOKUP(D58,カラムID辞書!C:H,6,FALSE) -> 13 | AQ58: 価格変更による返品伝票の原価集計値
B59: =IF($D59="","",MAX(OFFSET($B$8,0,0,ROW()-ROW($B$8),2))+1) -> 52 | D59: 価格訂正返品高売価 | L59: =VLOOKUP(D59,カラムID辞書!$C$4:$D$1266,2,FALSE) -> TEISEIHENPIND_BIK | AB59: =IF(L59="DELDTE","","○") -> ○ | AE59: =IF(AB59="○",IF(AH59="timestamp","now()",IF(LEFT(AH59,9)="character","' '","0")),"") -> 0 | AH59: =VLOOKUP(D59,カラムID辞書!C:H,3,FALSE) -> numeric | AM59: =VLOOKUP(D59,カラムID辞書!C:H,4,FALSE) -> 13 | AO59: =VLOOKUP(D59,カラムID辞書!C:H,6,FALSE) -> 13 | AQ59: 価格変更による返品伝票の売価集計値
B60: =IF($D60="","",MAX(OFFSET($B$8,0,0,ROW()-ROW($B$8),2))+1) -> 53 | D60: 価格訂正返品高数量 | L60: =VLOOKUP(D60,カラムID辞書!$C$4:$D$1266,2,FALSE) -> TEISEIHENPIND_SU | AB60: =IF(L60="DELDTE","","○") -> ○ | AE60: =IF(AB60="○",IF(AH60="timestamp","now()",IF(LEFT(AH60,9)="character","' '","0")),"") -> 0 | AH60: =VLOOKUP(D60,カラムID辞書!C:H,3,FALSE) -> numeric | AM60: =VLOOKUP(D60,カラムID辞書!C:H,4,FALSE) -> 10 | AO60: =VLOOKUP(D60,カラムID辞書!C:H,6,FALSE) -> 10 | AQ60: 価格変更による返品伝票の数量集計値
B61: =IF($D61="","",MAX(OFFSET($B$8,0,0,ROW()-ROW($B$8),2))+1) -> 54 | D61: 自社値上高売価 | L61: =VLOOKUP(D61,カラムID辞書!$C$4:$D$1266,2,FALSE) -> JISHANEAGED_BIK | AB61: =IF(L61="DELDTE","","○") -> ○ | AE61: =IF(AB61="○",IF(AH61="timestamp","now()",IF(LEFT(AH61,9)="character","' '","0")),"") -> 0 | AH61: =VLOOKUP(D61,カラムID辞書!C:H,3,FALSE) -> numeric | AM61: =VLOOKUP(D61,カラムID辞書!C:H,4,FALSE) -> 13 | AO61: =VLOOKUP(D61,カラムID辞書!C:H,6,FALSE) -> 13 | AQ61: 値上伝票の売価集計値
B62: =IF($D62="","",MAX(OFFSET($B$8,0,0,ROW()-ROW($B$8),2))+1) -> 55 | D62: 自社値下高売価 | L62: =VLOOKUP(D62,カラムID辞書!$C$4:$D$1266,2,FALSE) -> JISHANESAGED_BIK | AB62: =IF(L62="DELDTE","","○") -> ○ | AE62: =IF(AB62="○",IF(AH62="timestamp","now()",IF(LEFT(AH62,9)="character","' '","0")),"") -> 0 | AH62: =VLOOKUP(D62,カラムID辞書!C:H,3,FALSE) -> numeric | AM62: =VLOOKUP(D62,カラムID辞書!C:H,4,FALSE) -> 13 | AO62: =VLOOKUP(D62,カラムID辞書!C:H,6,FALSE) -> 13 | AQ62: 値下伝票の売価集計値
B63: =IF($D63="","",MAX(OFFSET($B$8,0,0,ROW()-ROW($B$8),2))+1) -> 56 | D63: 値上高原価１ | L63: =VLOOKUP(D63,カラムID辞書!$C$4:$D$1266,2,FALSE) -> NEAGED1_GNK | AB63: =IF(L63="DELDTE","","○") -> ○ | AE63: =IF(AB63="○",IF(AH63="timestamp","now()",IF(LEFT(AH63,9)="character","' '","0")),"") -> 0 | AH63: =VLOOKUP(D63,カラムID辞書!C:H,3,FALSE) -> numeric | AM63: =VLOOKUP(D63,カラムID辞書!C:H,4,FALSE) -> 13 | AO63: =VLOOKUP(D63,カラムID辞書!C:H,6,FALSE) -> 13 | BR63: （未設定：ZERO）
B64: =IF($D64="","",MAX(OFFSET($B$8,0,0,ROW()-ROW($B$8),2))+1) -> 57 | D64: 値上高売価１ | L64: =VLOOKUP(D64,カラムID辞書!$C$4:$D$1266,2,FALSE) -> NEAGED1_BIK | AB64: =IF(L64="DELDTE","","○") -> ○ | AE64: =IF(AB64="○",IF(AH64="timestamp","now()",IF(LEFT(AH64,9)="character","' '","0")),"") -> 0 | AH64: =VLOOKUP(D64,カラムID辞書!C:H,3,FALSE) -> numeric | AM64: =VLOOKUP(D64,カラムID辞書!C:H,4,FALSE) -> 13 | AO64: =VLOOKUP(D64,カラムID辞書!C:H,6,FALSE) -> 13 | BR64: （未設定：ZERO）
B65: =IF($D65="","",MAX(OFFSET($B$8,0,0,ROW()-ROW($B$8),2))+1) -> 58 | D65: 値下高原価１ | L65: =VLOOKUP(D65,カラムID辞書!$C$4:$D$1266,2,FALSE) -> NESAGED1_GNK | AB65: =IF(L65="DELDTE","","○") -> ○ | AE65: =IF(AB65="○",IF(AH65="timestamp","now()",IF(LEFT(AH65,9)="character","' '","0")),"") -> 0 | AH65: =VLOOKUP(D65,カラムID辞書!C:H,3,FALSE) -> numeric | AM65: =VLOOKUP(D65,カラムID辞書!C:H,4,FALSE) -> 13 | AO65: =VLOOKUP(D65,カラムID辞書!C:H,6,FALSE) -> 13 | AQ65: 破損伝票の数量集計値
B66: =IF($D66="","",MAX(OFFSET($B$8,0,0,ROW()-ROW($B$8),2))+1) -> 59 | D66: 値下高売価１ | L66: =VLOOKUP(D66,カラムID辞書!$C$4:$D$1266,2,FALSE) -> NESAGED1_BIK | AB66: =IF(L66="DELDTE","","○") -> ○ | AE66: =IF(AB66="○",IF(AH66="timestamp","now()",IF(LEFT(AH66,9)="character","' '","0")),"") -> 0 | AH66: =VLOOKUP(D66,カラムID辞書!C:H,3,FALSE) -> numeric | AM66: =VLOOKUP(D66,カラムID辞書!C:H,4,FALSE) -> 13 | AO66: =VLOOKUP(D66,カラムID辞書!C:H,6,FALSE) -> 13 | AQ66: 破損伝票の売価集計値
B67: =IF($D67="","",MAX(OFFSET($B$8,0,0,ROW()-ROW($B$8),2))+1) -> 60 | D67: 値上高原価２ | L67: =VLOOKUP(D67,カラムID辞書!$C$4:$D$1266,2,FALSE) -> NEAGED2_GNK | AB67: =IF(L67="DELDTE","","○") -> ○ | AE67: =IF(AB67="○",IF(AH67="timestamp","now()",IF(LEFT(AH67,9)="character","' '","0")),"") -> 0 | AH67: =VLOOKUP(D67,カラムID辞書!C:H,3,FALSE) -> numeric | AM67: =VLOOKUP(D67,カラムID辞書!C:H,4,FALSE) -> 13 | AO67: =VLOOKUP(D67,カラムID辞書!C:H,6,FALSE) -> 13 | BR67: （未設定：ZERO）
B68: =IF($D68="","",MAX(OFFSET($B$8,0,0,ROW()-ROW($B$8),2))+1) -> 61 | D68: 値上高売価２ | L68: =VLOOKUP(D68,カラムID辞書!$C$4:$D$1266,2,FALSE) -> NEAGED2_BIK | AB68: =IF(L68="DELDTE","","○") -> ○ | AE68: =IF(AB68="○",IF(AH68="timestamp","now()",IF(LEFT(AH68,9)="character","' '","0")),"") -> 0 | AH68: =VLOOKUP(D68,カラムID辞書!C:H,3,FALSE) -> numeric | AM68: =VLOOKUP(D68,カラムID辞書!C:H,4,FALSE) -> 13 | AO68: =VLOOKUP(D68,カラムID辞書!C:H,6,FALSE) -> 13 | BR68: （未設定：ZERO）
B69: =IF($D69="","",MAX(OFFSET($B$8,0,0,ROW()-ROW($B$8),2))+1) -> 62 | D69: 値下高原価２ | L69: =VLOOKUP(D69,カラムID辞書!$C$4:$D$1266,2,FALSE) -> NESAGED2_GNK | AB69: =IF(L69="DELDTE","","○") -> ○ | AE69: =IF(AB69="○",IF(AH69="timestamp","now()",IF(LEFT(AH69,9)="character","' '","0")),"") -> 0 | AH69: =VLOOKUP(D69,カラムID辞書!C:H,3,FALSE) -> numeric | AM69: =VLOOKUP(D69,カラムID辞書!C:H,4,FALSE) -> 13 | AO69: =VLOOKUP(D69,カラムID辞書!C:H,6,FALSE) -> 13 | BR69: （未設定：ZERO）
B70: =IF($D70="","",MAX(OFFSET($B$8,0,0,ROW()-ROW($B$8),2))+1) -> 63 | D70: 値下高売価２ | L70: =VLOOKUP(D70,カラムID辞書!$C$4:$D$1266,2,FALSE) -> NESAGED2_BIK | AB70: =IF(L70="DELDTE","","○") -> ○ | AE70: =IF(AB70="○",IF(AH70="timestamp","now()",IF(LEFT(AH70,9)="character","' '","0")),"") -> 0 | AH70: =VLOOKUP(D70,カラムID辞書!C:H,3,FALSE) -> numeric | AM70: =VLOOKUP(D70,カラムID辞書!C:H,4,FALSE) -> 13 | AO70: =VLOOKUP(D70,カラムID辞書!C:H,6,FALSE) -> 13 | BR70: （未設定：ZERO）
B71: =IF($D71="","",MAX(OFFSET($B$8,0,0,ROW()-ROW($B$8),2))+1) -> 64 | D71: 店間振替高原価（払出） | L71: =VLOOKUP(D71,カラムID辞書!$C$4:$D$1266,2,FALSE) -> TNKANFURI_O_GNK | AB71: =IF(L71="DELDTE","","○") -> ○ | AE71: =IF(AB71="○",IF(AH71="timestamp","now()",IF(LEFT(AH71,9)="character","' '","0")),"") -> 0 | AH71: =VLOOKUP(D71,カラムID辞書!C:H,3,FALSE) -> numeric | AM71: =VLOOKUP(D71,カラムID辞書!C:H,4,FALSE) -> 13 | AO71: =VLOOKUP(D71,カラムID辞書!C:H,6,FALSE) -> 13 | AQ71: 店間振替伝票（払出）の原価集計値
B72: =IF($D72="","",MAX(OFFSET($B$8,0,0,ROW()-ROW($B$8),2))+1) -> 65 | D72: 店間振替高売価（払出） | L72: =VLOOKUP(D72,カラムID辞書!$C$4:$D$1266,2,FALSE) -> TNKANFURI_O_BIK | AB72: =IF(L72="DELDTE","","○") -> ○ | AE72: =IF(AB72="○",IF(AH72="timestamp","now()",IF(LEFT(AH72,9)="character","' '","0")),"") -> 0 | AH72: =VLOOKUP(D72,カラムID辞書!C:H,3,FALSE) -> numeric | AM72: =VLOOKUP(D72,カラムID辞書!C:H,4,FALSE) -> 13 | AO72: =VLOOKUP(D72,カラムID辞書!C:H,6,FALSE) -> 13 | AQ72: 店間振替伝票（払出）の売価集計値
B73: =IF($D73="","",MAX(OFFSET($B$8,0,0,ROW()-ROW($B$8),2))+1) -> 66 | D73: 店間振替高数量（払出） | L73: =VLOOKUP(D73,カラムID辞書!$C$4:$D$1266,2,FALSE) -> TNKANFURI_O_SU | AB73: =IF(L73="DELDTE","","○") -> ○ | AE73: =IF(AB73="○",IF(AH73="timestamp","now()",IF(LEFT(AH73,9)="character","' '","0")),"") -> 0 | AH73: =VLOOKUP(D73,カラムID辞書!C:H,3,FALSE) -> numeric | AM73: =VLOOKUP(D73,カラムID辞書!C:H,4,FALSE) -> 10 | AO73: =VLOOKUP(D73,カラムID辞書!C:H,6,FALSE) -> 10 | AQ73: 店間振替伝票（払出）の数量集計値
B74: =IF($D74="","",MAX(OFFSET($B$8,0,0,ROW()-ROW($B$8),2))+1) -> 67 | D74: 店間振替高原価（受入） | L74: =VLOOKUP(D74,カラムID辞書!$C$4:$D$1266,2,FALSE) -> TNKANFURI_I_GNK | AB74: =IF(L74="DELDTE","","○") -> ○ | AE74: =IF(AB74="○",IF(AH74="timestamp","now()",IF(LEFT(AH74,9)="character","' '","0")),"") -> 0 | AH74: =VLOOKUP(D74,カラムID辞書!C:H,3,FALSE) -> numeric | AM74: =VLOOKUP(D74,カラムID辞書!C:H,4,FALSE) -> 13 | AO74: =VLOOKUP(D74,カラムID辞書!C:H,6,FALSE) -> 13 | AQ74: 店間振替伝票（受入）の原価集計値
B75: =IF($D75="","",MAX(OFFSET($B$8,0,0,ROW()-ROW($B$8),2))+1) -> 68 | D75: 店間振替高売価（受入） | L75: =VLOOKUP(D75,カラムID辞書!$C$4:$D$1266,2,FALSE) -> TNKANFURI_I_BIK | AB75: =IF(L75="DELDTE","","○") -> ○ | AE75: =IF(AB75="○",IF(AH75="timestamp","now()",IF(LEFT(AH75,9)="character","' '","0")),"") -> 0 | AH75: =VLOOKUP(D75,カラムID辞書!C:H,3,FALSE) -> numeric | AM75: =VLOOKUP(D75,カラムID辞書!C:H,4,FALSE) -> 13 | AO75: =VLOOKUP(D75,カラムID辞書!C:H,6,FALSE) -> 13 | AQ75: 店間振替伝票（受入）の売価集計値
B76: =IF($D76="","",MAX(OFFSET($B$8,0,0,ROW()-ROW($B$8),2))+1) -> 69 | D76: 店間振替高数量（受入） | L76: =VLOOKUP(D76,カラムID辞書!$C$4:$D$1266,2,FALSE) -> TNKANFURI_I_SU | AB76: =IF(L76="DELDTE","","○") -> ○ | AE76: =IF(AB76="○",IF(AH76="timestamp","now()",IF(LEFT(AH76,9)="character","' '","0")),"") -> 0 | AH76: =VLOOKUP(D76,カラムID辞書!C:H,3,FALSE) -> numeric | AM76: =VLOOKUP(D76,カラムID辞書!C:H,4,FALSE) -> 10 | AO76: =VLOOKUP(D76,カラムID辞書!C:H,6,FALSE) -> 10 | AQ76: 店間振替伝票（受入）の数量集計値
B77: =IF($D77="","",MAX(OFFSET($B$8,0,0,ROW()-ROW($B$8),2))+1) -> 70 | D77: 店内振替高原価（払出） | L77: =VLOOKUP(D77,カラムID辞書!$C$4:$D$1266,2,FALSE) -> TNNAIFURI_O_GNK | AB77: =IF(L77="DELDTE","","○") -> ○ | AE77: =IF(AB77="○",IF(AH77="timestamp","now()",IF(LEFT(AH77,9)="character","' '","0")),"") -> 0 | AH77: =VLOOKUP(D77,カラムID辞書!C:H,3,FALSE) -> numeric | AM77: =VLOOKUP(D77,カラムID辞書!C:H,4,FALSE) -> 13 | AO77: =VLOOKUP(D77,カラムID辞書!C:H,6,FALSE) -> 13 | AQ77: 品番振替伝票（払出）の原価集計値
B78: =IF($D78="","",MAX(OFFSET($B$8,0,0,ROW()-ROW($B$8),2))+1) -> 71 | D78: 店内振替高売価（払出） | L78: =VLOOKUP(D78,カラムID辞書!$C$4:$D$1266,2,FALSE) -> TNNAIFURI_O_BIK | AB78: =IF(L78="DELDTE","","○") -> ○ | AE78: =IF(AB78="○",IF(AH78="timestamp","now()",IF(LEFT(AH78,9)="character","' '","0")),"") -> 0 | AH78: =VLOOKUP(D78,カラムID辞書!C:H,3,FALSE) -> numeric | AM78: =VLOOKUP(D78,カラムID辞書!C:H,4,FALSE) -> 13 | AO78: =VLOOKUP(D78,カラムID辞書!C:H,6,FALSE) -> 13 | AQ78: 品番振替伝票（払出）の売価集計値
B79: =IF($D79="","",MAX(OFFSET($B$8,0,0,ROW()-ROW($B$8),2))+1) -> 72 | D79: 店内振替高数量（払出） | L79: =VLOOKUP(D79,カラムID辞書!$C$4:$D$1266,2,FALSE) -> TNNAIFURI_O_SU | AB79: =IF(L79="DELDTE","","○") -> ○ | AE79: =IF(AB79="○",IF(AH79="timestamp","now()",IF(LEFT(AH79,9)="character","' '","0")),"") -> 0 | AH79: =VLOOKUP(D79,カラムID辞書!C:H,3,FALSE) -> numeric | AM79: =VLOOKUP(D79,カラムID辞書!C:H,4,FALSE) -> 10 | AO79: =VLOOKUP(D79,カラムID辞書!C:H,6,FALSE) -> 10 | AQ79: 品番振替伝票（払出）の数量集計値
B80: =IF($D80="","",MAX(OFFSET($B$8,0,0,ROW()-ROW($B$8),2))+1) -> 73 | D80: 店内振替高原価（受入） | L80: =VLOOKUP(D80,カラムID辞書!$C$4:$D$1266,2,FALSE) -> TNNAIFURI_I_GNK | AB80: =IF(L80="DELDTE","","○") -> ○ | AE80: =IF(AB80="○",IF(AH80="timestamp","now()",IF(LEFT(AH80,9)="character","' '","0")),"") -> 0 | AH80: =VLOOKUP(D80,カラムID辞書!C:H,3,FALSE) -> numeric | AM80: =VLOOKUP(D80,カラムID辞書!C:H,4,FALSE) -> 13 | AO80: =VLOOKUP(D80,カラムID辞書!C:H,6,FALSE) -> 13 | AQ80: 品番振替伝票（受入）の原価集計値
B81: =IF($D81="","",MAX(OFFSET($B$8,0,0,ROW()-ROW($B$8),2))+1) -> 74 | D81: 店内振替高売価（受入） | L81: =VLOOKUP(D81,カラムID辞書!$C$4:$D$1266,2,FALSE) -> TNNAIFURI_I_BIK | AB81: =IF(L81="DELDTE","","○") -> ○ | AE81: =IF(AB81="○",IF(AH81="timestamp","now()",IF(LEFT(AH81,9)="character","' '","0")),"") -> 0 | AH81: =VLOOKUP(D81,カラムID辞書!C:H,3,FALSE) -> numeric | AM81: =VLOOKUP(D81,カラムID辞書!C:H,4,FALSE) -> 13 | AO81: =VLOOKUP(D81,カラムID辞書!C:H,6,FALSE) -> 13 | AQ81: 品番振替伝票（受入）の売価集計値
B82: =IF($D82="","",MAX(OFFSET($B$8,0,0,ROW()-ROW($B$8),2))+1) -> 75 | D82: 店内振替高数量（受入） | L82: =VLOOKUP(D82,カラムID辞書!$C$4:$D$1266,2,FALSE) -> TNNAIFURI_I_SU | AB82: =IF(L82="DELDTE","","○") -> ○ | AE82: =IF(AB82="○",IF(AH82="timestamp","now()",IF(LEFT(AH82,9)="character","' '","0")),"") -> 0 | AH82: =VLOOKUP(D82,カラムID辞書!C:H,3,FALSE) -> numeric | AM82: =VLOOKUP(D82,カラムID辞書!C:H,4,FALSE) -> 10 | AO82: =VLOOKUP(D82,カラムID辞書!C:H,6,FALSE) -> 10 | AQ82: 品番振替伝票（受入）の数量集計値
B83: =IF($D83="","",MAX(OFFSET($B$8,0,0,ROW()-ROW($B$8),2))+1) -> 76 | D83: 商品振替高原価（払出） | L83: =VLOOKUP(D83,カラムID辞書!$C$4:$D$1266,2,FALSE) -> SHOHNFURI_O_GNK | AB83: =IF(L83="DELDTE","","○") -> ○ | AE83: =IF(AB83="○",IF(AH83="timestamp","now()",IF(LEFT(AH83,9)="character","' '","0")),"") -> 0 | AH83: =VLOOKUP(D83,カラムID辞書!C:H,3,FALSE) -> numeric | AM83: =VLOOKUP(D83,カラムID辞書!C:H,4,FALSE) -> 13 | AO83: =VLOOKUP(D83,カラムID辞書!C:H,6,FALSE) -> 13 | BR83: （未設定：ZERO）
B84: =IF($D84="","",MAX(OFFSET($B$8,0,0,ROW()-ROW($B$8),2))+1) -> 77 | D84: 商品振替高売価（払出） | L84: =VLOOKUP(D84,カラムID辞書!$C$4:$D$1266,2,FALSE) -> SHOHNFURI_O_BIK | AB84: =IF(L84="DELDTE","","○") -> ○ | AE84: =IF(AB84="○",IF(AH84="timestamp","now()",IF(LEFT(AH84,9)="character","' '","0")),"") -> 0 | AH84: =VLOOKUP(D84,カラムID辞書!C:H,3,FALSE) -> numeric | AM84: =VLOOKUP(D84,カラムID辞書!C:H,4,FALSE) -> 13 | AO84: =VLOOKUP(D84,カラムID辞書!C:H,6,FALSE) -> 13 | BR84: （未設定：ZERO）
B85: =IF($D85="","",MAX(OFFSET($B$8,0,0,ROW()-ROW($B$8),2))+1) -> 78 | D85: 商品振替高数量（払出） | L85: =VLOOKUP(D85,カラムID辞書!$C$4:$D$1266,2,FALSE) -> SHOHNFURI_O_SU | AB85: =IF(L85="DELDTE","","○") -> ○ | AE85: =IF(AB85="○",IF(AH85="timestamp","now()",IF(LEFT(AH85,9)="character","' '","0")),"") -> 0 | AH85: =VLOOKUP(D85,カラムID辞書!C:H,3,FALSE) -> numeric | AM85: =VLOOKUP(D85,カラムID辞書!C:H,4,FALSE) -> 10 | AO85: =VLOOKUP(D85,カラムID辞書!C:H,6,FALSE) -> 10 | BR85: （未設定：ZERO）
B86: =IF($D86="","",MAX(OFFSET($B$8,0,0,ROW()-ROW($B$8),2))+1) -> 79 | D86: 商品振替高原価（受入） | L86: =VLOOKUP(D86,カラムID辞書!$C$4:$D$1266,2,FALSE) -> SHOHNFURI_I_GNK | AB86: =IF(L86="DELDTE","","○") -> ○ | AE86: =IF(AB86="○",IF(AH86="timestamp","now()",IF(LEFT(AH86,9)="character","' '","0")),"") -> 0 | AH86: =VLOOKUP(D86,カラムID辞書!C:H,3,FALSE) -> numeric | AM86: =VLOOKUP(D86,カラムID辞書!C:H,4,FALSE) -> 13 | AO86: =VLOOKUP(D86,カラムID辞書!C:H,6,FALSE) -> 13 | BR86: （未設定：ZERO）
B87: =IF($D87="","",MAX(OFFSET($B$8,0,0,ROW()-ROW($B$8),2))+1) -> 80 | D87: 商品振替高売価（受入） | L87: =VLOOKUP(D87,カラムID辞書!$C$4:$D$1266,2,FALSE) -> SHOHNFURI_I_BIK | AB87: =IF(L87="DELDTE","","○") -> ○ | AE87: =IF(AB87="○",IF(AH87="timestamp","now()",IF(LEFT(AH87,9)="character","' '","0")),"") -> 0 | AH87: =VLOOKUP(D87,カラムID辞書!C:H,3,FALSE) -> numeric | AM87: =VLOOKUP(D87,カラムID辞書!C:H,4,FALSE) -> 13 | AO87: =VLOOKUP(D87,カラムID辞書!C:H,6,FALSE) -> 13 | BR87: （未設定：ZERO）
B88: =IF($D88="","",MAX(OFFSET($B$8,0,0,ROW()-ROW($B$8),2))+1) -> 81 | D88: 商品振替高数量（受入） | L88: =VLOOKUP(D88,カラムID辞書!$C$4:$D$1266,2,FALSE) -> SHOHNFURI_I_SU | AB88: =IF(L88="DELDTE","","○") -> ○ | AE88: =IF(AB88="○",IF(AH88="timestamp","now()",IF(LEFT(AH88,9)="character","' '","0")),"") -> 0 | AH88: =VLOOKUP(D88,カラムID辞書!C:H,3,FALSE) -> numeric | AM88: =VLOOKUP(D88,カラムID辞書!C:H,4,FALSE) -> 10 | AO88: =VLOOKUP(D88,カラムID辞書!C:H,6,FALSE) -> 10 | BR88: （未設定：ZERO）
B89: =IF($D89="","",MAX(OFFSET($B$8,0,0,ROW()-ROW($B$8),2))+1) -> 82 | D89: リベート | L89: =VLOOKUP(D89,カラムID辞書!$C$4:$D$1266,2,FALSE) -> REBATE | AB89: =IF(L89="DELDTE","","○") -> ○ | AE89: =IF(AB89="○",IF(AH89="timestamp","now()",IF(LEFT(AH89,9)="character","' '","0")),"") -> 0 | AH89: =VLOOKUP(D89,カラムID辞書!C:H,3,FALSE) -> numeric | AM89: =VLOOKUP(D89,カラムID辞書!C:H,4,FALSE) -> 13 | AO89: =VLOOKUP(D89,カラムID辞書!C:H,6,FALSE) -> 13 | BR89: （未設定：ZERO）
B90: =IF($D90="","",MAX(OFFSET($B$8,0,0,ROW()-ROW($B$8),2))+1) -> 83 | D90: リベート返金 | L90: =VLOOKUP(D90,カラムID辞書!$C$4:$D$1266,2,FALSE) -> REBATE_HENKIN | AB90: =IF(L90="DELDTE","","○") -> ○ | AE90: =IF(AB90="○",IF(AH90="timestamp","now()",IF(LEFT(AH90,9)="character","' '","0")),"") -> 0 | AH90: =VLOOKUP(D90,カラムID辞書!C:H,3,FALSE) -> numeric | AM90: =VLOOKUP(D90,カラムID辞書!C:H,4,FALSE) -> 13 | AO90: =VLOOKUP(D90,カラムID辞書!C:H,6,FALSE) -> 13 | BR90: （未設定：ZERO）
B91: =IF($D91="","",MAX(OFFSET($B$8,0,0,ROW()-ROW($B$8),2))+1) -> 84 | D91: 予備原価１ | L91: =VLOOKUP(D91,カラムID辞書!$C$4:$D$1266,2,FALSE) -> RSV_GNK1 | AB91: =IF(L91="DELDTE","","○") -> ○ | AE91: =IF(AB91="○",IF(AH91="timestamp","now()",IF(LEFT(AH91,9)="character","' '","0")),"") -> 0 | AH91: =VLOOKUP(D91,カラムID辞書!C:H,3,FALSE) -> numeric | AM91: =VLOOKUP(D91,カラムID辞書!C:H,4,FALSE) -> 13 | AO91: =VLOOKUP(D91,カラムID辞書!C:H,6,FALSE) -> 13 | BR91: （未設定：ZERO）
B92: =IF($D92="","",MAX(OFFSET($B$8,0,0,ROW()-ROW($B$8),2))+1) -> 85 | D92: 予備売価１ | L92: =VLOOKUP(D92,カラムID辞書!$C$4:$D$1266,2,FALSE) -> RSV_BIK1 | AB92: =IF(L92="DELDTE","","○") -> ○ | AE92: =IF(AB92="○",IF(AH92="timestamp","now()",IF(LEFT(AH92,9)="character","' '","0")),"") -> 0 | AH92: =VLOOKUP(D92,カラムID辞書!C:H,3,FALSE) -> numeric | AM92: =VLOOKUP(D92,カラムID辞書!C:H,4,FALSE) -> 13 | AO92: =VLOOKUP(D92,カラムID辞書!C:H,6,FALSE) -> 13 | BR92: （未設定：ZERO）
B93: =IF($D93="","",MAX(OFFSET($B$8,0,0,ROW()-ROW($B$8),2))+1) -> 86 | D93: 予備数量１ | L93: =VLOOKUP(D93,カラムID辞書!$C$4:$D$1266,2,FALSE) -> RSV_SU1 | AB93: =IF(L93="DELDTE","","○") -> ○ | AE93: =IF(AB93="○",IF(AH93="timestamp","now()",IF(LEFT(AH93,9)="character","' '","0")),"") -> 0 | AH93: =VLOOKUP(D93,カラムID辞書!C:H,3,FALSE) -> numeric | AM93: =VLOOKUP(D93,カラムID辞書!C:H,4,FALSE) -> 10 | AO93: =VLOOKUP(D93,カラムID辞書!C:H,6,FALSE) -> 10 | BR93: （未設定：ZERO）
B94: =IF($D94="","",MAX(OFFSET($B$8,0,0,ROW()-ROW($B$8),2))+1) -> 87 | D94: 予備原価２ | L94: =VLOOKUP(D94,カラムID辞書!$C$4:$D$1266,2,FALSE) -> RSV_GNK2 | AB94: =IF(L94="DELDTE","","○") -> ○ | AE94: =IF(AB94="○",IF(AH94="timestamp","now()",IF(LEFT(AH94,9)="character","' '","0")),"") -> 0 | AH94: =VLOOKUP(D94,カラムID辞書!C:H,3,FALSE) -> numeric | AM94: =VLOOKUP(D94,カラムID辞書!C:H,4,FALSE) -> 13 | AO94: =VLOOKUP(D94,カラムID辞書!C:H,6,FALSE) -> 13 | BR94: （未設定：ZERO）
... B120: =IF($D120="","",MAX(OFFSET($B$8,0,0,ROW()-ROW($B$8),2))+1) -> 113 | D120: 予備数量１０ | L120: =VLOOKUP(D120,カラムID辞書!$C$4:$D$1266,2,FALSE) -> RSV_SU10 | AB120: =IF(L120="DELDTE","","○") -> ○ | AE120: =IF(AB120="○",IF(AH120="timestamp","now()",IF(LEFT(AH120,9)="character","' '","0")),"") -> 0 | AH120: =VLOOKUP(D120,カラムID辞書!C:H,3,FALSE) -> numeric | AM120: =VLOOKUP(D120,カラムID辞書!C:H,4,FALSE) -> 10 | AO120: =VLOOKUP(D120,カラムID辞書!C:H,6,FALSE) -> 10 | BR120: （未設定：ZERO）
B121: =IF($D121="","",MAX(OFFSET($B$8,0,0,ROW()-ROW($B$8),2))+1) -> 114 | D121: 年初在高原価 | L121: =VLOOKUP(D121,カラムID辞書!$C$4:$D$1266,2,FALSE) -> NENSHOZAID_GNK | AB121: =IF(L121="DELDTE","","○") -> ○ | AE121: =IF(AB121="○",IF(AH121="timestamp","now()",IF(LEFT(AH121,9)="character","' '","0")),"") -> 0 | AH121: =VLOOKUP(D121,カラムID辞書!C:H,3,FALSE) -> numeric | AM121: =VLOOKUP(D121,カラムID辞書!C:H,4,FALSE) -> 13 | AO121: =VLOOKUP(D121,カラムID辞書!C:H,6,FALSE) -> 13 | AQ121: 別紙「商品勘定利益計算」参照
B122: =IF($D122="","",MAX(OFFSET($B$8,0,0,ROW()-ROW($B$8),2))+1) -> 115 | D122: 年初在高売価 | L122: =VLOOKUP(D122,カラムID辞書!$C$4:$D$1266,2,FALSE) -> NENSHOZAID_BIK | AB122: =IF(L122="DELDTE","","○") -> ○ | AE122: =IF(AB122="○",IF(AH122="timestamp","now()",IF(LEFT(AH122,9)="character","' '","0")),"") -> 0 | AH122: =VLOOKUP(D122,カラムID辞書!C:H,3,FALSE) -> numeric | AM122: =VLOOKUP(D122,カラムID辞書!C:H,4,FALSE) -> 13 | AO122: =VLOOKUP(D122,カラムID辞書!C:H,6,FALSE) -> 13 | AQ122: 別紙「商品勘定利益計算」参照
B123: =IF($D123="","",MAX(OFFSET($B$8,0,0,ROW()-ROW($B$8),2))+1) -> 116 | D123: 年初在高数量 | L123: =VLOOKUP(D123,カラムID辞書!$C$4:$D$1266,2,FALSE) -> NENSHOZAID_SU | AB123: =IF(L123="DELDTE","","○") -> ○ | AE123: =IF(AB123="○",IF(AH123="timestamp","now()",IF(LEFT(AH123,9)="character","' '","0")),"") -> 0 | AH123: =VLOOKUP(D123,カラムID辞書!C:H,3,FALSE) -> numeric | AM123: =VLOOKUP(D123,カラムID辞書!C:H,4,FALSE) -> 10 | AO123: =VLOOKUP(D123,カラムID辞書!C:H,6,FALSE) -> 10 | AQ123: 別紙「商品勘定利益計算」参照
B124: =IF($D124="","",MAX(OFFSET($B$8,0,0,ROW()-ROW($B$8),2))+1) -> 117 | D124: 前期繰越評価損 | L124: =VLOOKUP(D124,カラムID辞書!$C$4:$D$1266,2,FALSE) -> ZENKIKRKSHYOKASON | AB124: =IF(L124="DELDTE","","○") -> ○ | AE124: =IF(AB124="○",IF(AH124="timestamp","now()",IF(LEFT(AH124,9)="character","' '","0")),"") -> 0 | AH124: =VLOOKUP(D124,カラムID辞書!C:H,3,FALSE) -> numeric | AM124: =VLOOKUP(D124,カラムID辞書!C:H,4,FALSE) -> 13 | AO124: =VLOOKUP(D124,カラムID辞書!C:H,6,FALSE) -> 13 | AQ124: 別紙「商品勘定利益計算」参照
B125: =IF($D125="","",MAX(OFFSET($B$8,0,0,ROW()-ROW($B$8),2))+1) -> 118 | D125: 年度末帳簿在高原価 | L125: =VLOOKUP(D125,カラムID辞書!$C$4:$D$1266,2,FALSE) -> NENMATCHOBZAID_GNK | AB125: =IF(L125="DELDTE","","○") -> ○ | AE125: =IF(AB125="○",IF(AH125="timestamp","now()",IF(LEFT(AH125,9)="character","' '","0")),"") -> 0 | AH125: =VLOOKUP(D125,カラムID辞書!C:H,3,FALSE) -> numeric | AM125: =VLOOKUP(D125,カラムID辞書!C:H,4,FALSE) -> 13 | AO125: =VLOOKUP(D125,カラムID辞書!C:H,6,FALSE) -> 13 | AQ125: 別紙「商品勘定利益計算」参照
B126: =IF($D126="","",MAX(OFFSET($B$8,0,0,ROW()-ROW($B$8),2))+1) -> 119 | D126: 年度末帳簿在高売価 | L126: =VLOOKUP(D126,カラムID辞書!$C$4:$D$1266,2,FALSE) -> NENMATCHOBZAID_BIK | AB126: =IF(L126="DELDTE","","○") -> ○ | AE126: =IF(AB126="○",IF(AH126="timestamp","now()",IF(LEFT(AH126,9)="character","' '","0")),"") -> 0 | AH126: =VLOOKUP(D126,カラムID辞書!C:H,3,FALSE) -> numeric | AM126: =VLOOKUP(D126,カラムID辞書!C:H,4,FALSE) -> 13 | AO126: =VLOOKUP(D126,カラムID辞書!C:H,6,FALSE) -> 13 | AQ126: 別紙「商品勘定利益計算」参照
B127: =IF($D127="","",MAX(OFFSET($B$8,0,0,ROW()-ROW($B$8),2))+1) -> 120 | D127: 年度末帳簿在高数量 | L127: =VLOOKUP(D127,カラムID辞書!$C$4:$D$1266,2,FALSE) -> NENMATCHOBZAID_SU | AB127: =IF(L127="DELDTE","","○") -> ○ | AE127: =IF(AB127="○",IF(AH127="timestamp","now()",IF(LEFT(AH127,9)="character","' '","0")),"") -> 0 | AH127: =VLOOKUP(D127,カラムID辞書!C:H,3,FALSE) -> numeric | AM127: =VLOOKUP(D127,カラムID辞書!C:H,4,FALSE) -> 10 | AO127: =VLOOKUP(D127,カラムID辞書!C:H,6,FALSE) -> 10 | AQ127: 別紙「商品勘定利益計算」参照
B128: =IF($D128="","",MAX(OFFSET($B$8,0,0,ROW()-ROW($B$8),2))+1) -> 121 | D128: 原価法年度末棚卸在高原価 | L128: =VLOOKUP(D128,カラムID辞書!$C$4:$D$1266,2,FALSE) -> GNK_NENMATTANAZAID_GNK | AB128: =IF(L128="DELDTE","","○") -> ○ | AE128: =IF(AB128="○",IF(AH128="timestamp","now()",IF(LEFT(AH128,9)="character","' '","0")),"") -> 0 | AH128: =VLOOKUP(D128,カラムID辞書!C:H,3,FALSE) -> numeric | AM128: =VLOOKUP(D128,カラムID辞書!C:H,4,FALSE) -> 13 | AO128: =VLOOKUP(D128,カラムID辞書!C:H,6,FALSE) -> 13 | AQ128: 別紙「商品勘定利益計算」参照
...

Sheet 商品明細日別実績
B2: ユーザインタフェース 設計書 | J2: サブシステム分類 | O2: ドキュメント ID | T2: ドキュメント名 | BK2: 更新者 | BN2: 最終更新日 | BR2: 履歴 | BT2: 作成者 | BW2: 作成日
J3: 商品勘定 | O3: 2.04 | T3: テーブル定義 | BR3: 第1版 | BT3: 富士通 | BW3: 42917
B5: 概念データ名／ID | J5: 商品明細日別実績テーブル | U5: ／ | V5: LBT05_MEISAI_D | AD5: OID | AK5: 最大レコード長 | AR5: =ROUNDUP((27+ROUNDUP((MAX(B:B)-COUNTIF(AB:AB,"○"))/8,0)+IF(AF5="",0,4))/8,0)*8+SUM(AO8:AO1017) -> 1525 | AU5: Byte | AW5: 用途 | BB5: 明細データを特定のコードで集約し日単位で管理する。
B7: 項番 | D7: 項目論理名称 | L7: 項目物理名称 | T7: PKey | V7: IDX1 | X7: IDX2 | Z7: IDX3 | AB7: NOTNULL | AE7: DEFAULT | AH7: Type | AM7: 桁数 | AO7: Byte | AQ7: 項目説明 | BR7: 備考
B8: 1 | D8: 年月日 | L8: =VLOOKUP(D8,カラムID辞書!$C$4:$D$1266,2,FALSE) -> YMD | T8: 1 | AB8: =IF(L8="DELDTE","","○") -> ○ | AE8: =IF(AB8="○",IF(AH8="timestamp","now()",IF(LEFT(AH8,9)="character","' '","0")),"") -> 0 | AH8: =VLOOKUP(D8,カラムID辞書!C:H,3,FALSE) -> numeric | AM8: =VLOOKUP(D8,カラムID辞書!C:H,4,FALSE) -> 8 | AO8: =VLOOKUP(D8,カラムID辞書!C:H,6,FALSE) -> 8 | AQ8: 伝票計上日（修正伝票は月末日）
B9: =IF($D9="","",MAX(OFFSET($B$8,0,0,ROW()-ROW($B$8),2))+1) -> 2 | D9: SEQ№ | L9: =VLOOKUP(D9,カラムID辞書!$C$4:$D$1266,2,FALSE) -> SEQNO | T9: 2 | AB9: =IF(L9="DELDTE","","○") -> ○ | AE9: =IF(AB9="○",IF(AH9="timestamp","now()",IF(LEFT(AH9,9)="character","' '","0")),"") -> 0 | AH9: =VLOOKUP(D9,カラムID辞書!C:H,3,FALSE) -> numeric | AM9: =VLOOKUP(D9,カラムID辞書!C:H,4,FALSE) -> 2 | AO9: =VLOOKUP(D9,カラムID辞書!C:H,6,FALSE) -> 2
B10: =IF($D10="","",MAX(OFFSET($B$8,0,0,ROW()-ROW($B$8),2))+1) -> 3 | D10: システムグループコード | L10: =VLOOKUP(D10,カラムID辞書!$C$4:$D$1266,2,FALSE) -> SYSGRPCD | T10: 3 | AB10: =IF(L10="DELDTE","","○") -> ○ | AE10: =IF(AB10="○",IF(AH10="timestamp","now()",IF(LEFT(AH10,9)="character","' '","0")),"") -> ' ' | AH10: =VLOOKUP(D10,カラムID辞書!C:H,3,FALSE) -> character varying | AM10: =VLOOKUP(D10,カラムID辞書!C:H,4,FALSE) -> 4 | AO10: =VLOOKUP(D10,カラムID辞書!C:H,6,FALSE) -> 4 | AQ10: ユーザ分類コード | BR10: "0010"固定
B11: =IF($D11="","",MAX(OFFSET($B$8,0,0,ROW()-ROW($B$8),2))+1) -> 4 | D11: 企業グループコード | L11: =VLOOKUP(D11,カラムID辞書!$C$4:$D$1266,2,FALSE) -> KGYGRPCD | T11: 4 | AB11: =IF(L11="DELDTE","","○") -> ○ | AE11: =IF(AB11="○",IF(AH11="timestamp","now()",IF(LEFT(AH11,9)="character","' '","0")),"") -> ' ' | AH11: =VLOOKUP(D11,カラムID辞書!C:H,3,FALSE) -> character varying | AM11: =VLOOKUP(D11,カラムID辞書!C:H,4,FALSE) -> 3 | AO11: =VLOOKUP(D11,カラムID辞書!C:H,6,FALSE) -> 3 | AQ11: 売上、仕入伝票の企業グループコード
